Workbook

Sheet Duke release copy DEV
A1: Key | B1: FIGMA | C1: en-US | D1: en-CA | E1: en-GB | F1: da-DK | G1: de-DE | H1: de-CH | I1: fr-FR | J1: fr-CH | K1: fr-BE | L1: fr-CA | M1: it-IT | N1: it-CH | O1: ja-JP | P1: es-MX | Q1: nl-NL | R1: nb-NO | S1: es-ES | T1: sv-SE | U1: en-AU | V1: en-NZ | W1: en-RW | X1: zh-CN | Y1: cs-CZ | Z1: fi-FI | AA1: pl-PL | AB1: de-LU | AC1: fr-LU | AD1: es-CO
A2: fet-feature-dimensions | B2: Dimensions | C2: Dimensions | D2: Dimensions | E2: Dimensions | F2: Mål | G2: Abmessungen | H2: Abmessungen | I2: Dimensions | J2: Dimensions | K2: Dimensions | L2: Dimensions | M2: Dimensioni | N2: Dimensioni | O2: 寸法 | P2: Dimensiones | Q2: Afmetingen | R2: Mål | S2: Dimensiones | T2: Mått | U2: Dimensions | V2: Dimensions | W2: Dimensions | X2: 尺寸 | Y2: Rozměry | Z2: Mitat | AA2: Wymiary | AB2: Abmessungen | AC2: Dimensions | AD2: Dimensiones
A3: fet-feature-weight | B3: Weight | C3: Weight | D3: Weight | E3: Weight | F3: Vægt | G3: Gewicht | H3: Gewicht | I3: Poids | J3: Poids | K3: Poids | L3: Poids | M3: Peso | N3: Peso | O3: 重量 | P3: Peso | Q3: Gewicht | R3: Vekt | S3: Peso | T3: Vikt | U3: Weight | V3: Weight | W3: Weight | X3: 重量 | Y3: Hmotnost | Z3: Paino | AA3: Waga | AB3: Gewicht | AC3: Poids | AD3: Peso
A4: fet-feature-weight-arc | C4: 13.78 lbs (6.25 kg) | D4: 13.78 lb (6.25 kg) | E4: 13.78 lb (6.25 kg) | F4: 6,25 kg | G4: 6,25 kg | H4: 6,25 kg | I4: 6,25 kg | J4: 6,25 kg | K4: 6,25 kg | L4: 6,25 kg (13,78 lb) | M4: 6,25 kg (13,78 lb) | N4: 6,25 kg (13,78 lb) | O4: 6.25 kg | P4: 6.25 kg (13.78 lb) | Q4: 6,25 kg | R4: 6,25 kg | S4: 6,25 kg (13,78 lb) | T4: 6,25 kg | U4: 6.25 kg | V4: 6.25 kg | W4: 13.78 lb (6.25 kg) | X4: 6.25千克（13.78磅） | Y4: 13,78 libry (6,25 kg) | Z4: 6,25 kg | AA4: 6,25 kg | AB4: 6,25 kg | AC4: 6,25 kg | AD4: 6,25 kg (13,78 lb)
A5: fet-feature-weight-beam | B5: 6.2 lbs (2.8 kg) | C5: 6.2 lbs (2.8 kg) | D5: 6.2 lb (2.8 kg) | E5: 6.2 lb (2.8 kg) | F5: 2,8 kg | G5: 2,8 kg | H5: 2,8 kg | I5: 2,8 kg | J5: 2,8 kg | K5: 2,8 kg | L5: 2,8 kg (6,2 lb) | M5: 2,8 kg (6,2 lb) | N5: 2,8 kg (6,2 lb) | O5: 2.8 kg | P5: 2.8 kg (6.2 lb) | Q5: 2,8 kg | R5: 2,8 kg | S5: 2,8 kg (6,2 lb) | T5: 2,8 kg | U5: 2.8 kg | V5: 2.8 kg | W5: 6.2 lb (2.8 kg) | X5: 2.8千克（6.2磅） | Y5: 6,2 libry (2,8 kg) | Z5: 2,8 kg | AA5: 2,8 kg | AB5: 2,8 kg | AC5: 2,8 kg | AD5: 2,8 kg (6,2 lb)
A6: fet-feature-weight-ray | B6: 4.29 lbs (1.95 kg) | C6: 4.29 lbs (1.95 kg) | D6: 4.29 lb (1.95 kg) | E6: 4.29 lb (1.95 kg) | F6: 1,95 kg | G6: 1,95 kg | H6: 1,95 kg | I6: 1,95 kg | J6: 1,95 kg | K6: 1,95 kg | L6: 1,95 kg (4,29 lb) | M6: 1,95 kg (4,29 lb) | N6: 1,95 kg (4,29 lb) | O6: 1.95 kg | P6: 1.95 kg (4.29 lb) | Q6: 1,95 kg | R6: 1,95 kg | S6: 1,95 kg (4,29 lb) | T6: 1,95 kg | U6: 1.95 kg | V6: 1.95 kg | W6: 4.29 lb (1.95 kg) | X6: 1.95千克（4.29磅） | Y6: 4,29 libry (1,95 kg) | Z6: 1,95 kg | AA6: 1,95 kg | AB6: 1,95 kg | AC6: 1,95 kg | AD6: 1,95 kg (4,29 lb)
A7: fet-feature-weight-sub | C7: 29 lbs (13.15 kg) | D7: 29 lb (13.15 kg) | E7: 29 lb (13.15 kg) | F7: 13,15 kg | G7: 13,15 kg | H7: 13,15 kg | I7: 13,15 kg | J7: 13,15 kg | K7: 13,15 kg | L7: 13,15 kg (29 lb) | M7: 13,15 kg (29 lb) | N7: 13,15 kg (29 lb) | O7: 13.15 kg | P7: 13.15 kg (29 lb) | Q7: 13,15 kg | R7: 13,15 kg | S7: 13,15 kg (29 lb) | T7: 13,15 kg | U7: 13.15 kg | V7: 13.15 kg | W7: 29 lb (13.15 kg) | X7: 13.15千克（29磅） | Y7: 29 liber (13,15 kg) | Z7: 13,15 kg | AA7: 13,15 kg | AB7: 13,15 kg | AC7: 13,15 kg | AD7: 13,15 kg (29 lb)
A8: fet-feature-weight-gravity | B8: 14 lbs (6.35 kg) | C8: 14 lbs (6.35 kg) | D8: 14 lbs (6.35 kg) | E8: 14 lb (6.35 kg) | F8: 6,35 kg | G8: 6,35 kg | H8: 6,35 kg | I8: 6,35 kg | J8: 6,35 kg | K8: 6,35 kg | L8: 6,35 kg (14 lb) | M8: 6,35 kg (14 lb) | N8: 6,35 kg (14 lb) | O8: 6.35 kg | P8: 6.35 kg (14 lb) | Q8: 6,35 kg | R8: 6,35 kg | S8: 6,35 kg (14 lb) | T8: 6,35 kg | U8: 6.35 kg | V8: 6.35 kg | W8: 14 lb (6.35 kg) | X8: 6.35千克（14磅） | Y8: 14 liber (6,35 kg) | Z8: 6,35 kg | AA8: 6,35 kg | AB8: 6,35 kg | AC8: 6,35 kg | AD8: 6.35 kg (14 lb)
A9: fet-feature-weight-optimo1 | B9: 4.44 lbs (2.02 kg) | C9: 4.44 lbs (2.02 kg) | D9: 4.44 lb (2.02 kg) | E9: 4.44 lb (2.02 kg) | F9: 2,02 kg | G9: 2,02 kg | H9: 2,02 kg | I9: 2,02 kg | J9: 2,02 kg | K9: 2,02 kg | L9: 2,02 kg (4,44 lb) | M9: 2,02 kg (4,44 lb) | N9: 2,02 kg (4,44 lb) | O9: 2.02 kg | P9: 2.02 kg (4.44 lb) | Q9: 2,02 kg | R9: 2,02 kg | S9: 2,02 kg (4,44 lb) | T9: 2,02 kg | U9: 2.02 kg | V9: 2.02 kg | W9: 4.44 lb (2.02 kg) | X9: 2.02千克（4.44磅） | Y9: 4,44 libry (2,02 kg) | Z9: 2,02 kg | AA9: 2,02 kg | AB9: 2,02 kg | AC9: 2,02 kg | AD9: 2,02 kg (4,44 lb)
A10: fet-feature-weight-optimo2 | B10: 9.85 lbs (4.47 kg) | C10: 9.85 lbs (4.47 kg) | D10: 9.85 lb (4.47 kg) | E10: 9.85 lb (4.47 kg) | F10: 4,47 kg | G10: 4,47 kg | H10: 4,47 kg | I10: 4,47 kg | J10: 4,47 kg | K10: 4,47 kg | L10: 4,47 kg (9,85 lb) | M10: 4,47 kg (9,85 lb) | N10: 4,47 kg (9,85 lb) | O10: 4.47 kg | P10: 4.47 kg (9.85 lb) | Q10: 4,47 kg | R10: 4,47 kg | S10: 4,47 kg (9,85 lb) | T10: 4,47 kg | U10: 4.47 kg | V10: 4.47 kg | W10: 9.85 lb (4.47 kg) | X10: 4.47千克（9.85磅） | Y10: 9,85 libry (4,47 kg) | Z10: 4,47 kg | AA10: 4,47 kg | AB10: 4,47 kg | AC10: 4,47 kg | AD10: 4,47 kg (9,85 lb)
A11: fet-feature-weight-five | B11: 14 lbs (6.36 kg) | C11: 14 lbs (6.36 kg) | D11: 14 lb (6.36 kg) | E11: 14 lb (6.36 kg) | F11: 6,36 kg | G11: 6,36 kg | H11: 6,36 kg | I11: 6,36 kg | J11: 6,36 kg | K11: 6,36 kg | L11: 6,36 kg (14 lb) | M11: 6,36 kg (14 lb) | N11: 6,36 kg (14 lb) | O11: 6.36 kg | P11: 6.36 kg (14 lb) | Q11: 6,36 kg | R11: 6,36 kg | S11: 6,36 kg (14 lb) | T11: 6,36 kg | U11: 6.36 kg | V11: 6.36 kg | W11: 14 lb (6.36 kg) | X11: 6.36千克（14磅） | Y11: 14 liber (6,36 kg) | Z11: 6,36 kg | AA11: 6,36 kg | AB11: 6,36 kg | AC11: 6,36 kg | AD11: 6,36 kg (14 lb)
A12: fet-feature-weight-move | C12: 14 lbs (6.36 kg) | D12: 14 lb (6.36 kg) | E12: 14 lb (6.36 kg) | F12: 6,36 kg | G12: 6,36 kg | H12: 6,36 kg | I12: 6,36 kg | J12: 6,36 kg | K12: 6,36 kg | L12: 6,36 kg (14 lb) | M12: 6,36 kg (14 lb) | N12: 6,36 kg (14 lb) | O12: 6.36 kg | P12: 6.36 kg (14 lb) | Q12: 6,36 kg | R12: 6,36 kg | S12: 6,36 kg (14 lb) | T12: 6,36 kg | U12: 6.36 kg | V12: 6.36 kg | W12: 14 lb (6.36 kg) | X12: 6.36千克（14磅） | Y12: 14 liber (6,36 kg) | Z12: 6,36 kg | AA12: 6,36 kg | AB12: 6,36 kg | AC12: 6,36 kg | AD12: 6,36 kg (14 lb)
A13: fet-feature-weight-prima | B13: 6.61 lbs (3 kg) | C13: 6.61 lbs (3 kg) | D13: 6.61 lb (3 kg) | E13: 6.61 lb (3 kg) | F13: 3 kg | G13: 3 kg | H13: 3 kg | I13: 3,0 kg | J13: 3,0 kg | K13: 3,0 kg | L13: 3 kg (6,61 lb) | M13: 3 kg (6,61 lb) | N13: 3 kg (6,61 lb) | O13: 3 kg | P13: 3 kg (6.61 lb) | Q13: 3 kg | R13: 3 kg | S13: 3 kg (6,61 lb) | T13: 3 kg | U13: 3 kg | V13: 3 kg | W13: 6.61 lb (3 kg) | X13: 3千克（6.61磅） | Y13: 6,61 libry (3 kg) | Z13: 3 kg | AA13: 3 kg | AB13: 3 kg | AC13: 3,0 kg | AD13: 3 kg (6,61 lb)
A14: fet-feature-weight-roam | C14: 0.95 lbs (0.43 kg) | D14: 0.95 lb (0.43 kg) | E14: 0.95 lb (0.43 kg) | F14: 0,43 kg | G14: 0,43 kg | H14: 0,43 kg | I14: 0,43 kg | J14: 0,43 kg | K14: 0,43 kg | L14: 0,43 kg (0,95 lb) | M14: 0,43 kg (0,95 lb) | N14: 0,43 kg (0,95 lb) | O14: 0.43 kg | P14: 0.43 kg (0.95 lb) | Q14: 0,43 kg | R14: 0,43 kg | S14: 0,43 kg (0,95 lb) | T14: 0,43 kg | U14: 0.43 kg | V14: 0.43 kg | W14: 0.95 lb (0.43 kg) | X14: 0.43千克（0.95磅） | Y14: 0,95 libry (0,43 kg) | Z14: 0,43 kg | AA14: 0,43 kg | AB14: 0,43 kg | AC14: 0,43 kg | AD14: 0,43 kg (0,95 lb)
A15: fet-feature-weight-roamsl | C15: 0.95 lbs (0.43 kg) | D15: 0.95 lb (0.43 kg) | E15: 0.95 lb (0.43 kg) | F15: 0,43 kg | G15: 0,43 kg | H15: 0,43 kg | I15: 0,43 kg | J15: 0,43 kg | K15: 0,43 kg | L15: 0,43 kg (0,95 lb) | M15: 0,43 kg (0,95 lb) | N15: 0,43 kg (0,95 lb) | O15: 0.43 kg | P15: 0.43 kg (0.95 lb) | Q15: 0,43 kg | R15: 0,43 kg | S15: 0,43 kg (0,95 lb) | T15: 0,43 kg | U15: 0.43 kg | V15: 0.43 kg | W15: 0.95 lb (0.43 kg) | X15: 0.43千克（0.95磅） | Y15: 0,95 libry (0,43 kg) | Z15: 0,43 kg | AA15: 0,43 kg | AB15: 0,43 kg | AC15: 0,43 kg | AD15: 0,43 kg (0,95 lb)
A16: fet-feature-weight-roam2 | B16: 0.95 lbs (0.43 kg) | C16: 0.95 lbs (0.43 kg) | D16: 0.95 lb (0.43 kg) | E16: 0.95 lb (0.43 kg) | F16: 0,43 kg | G16: 0,43 kg | H16: 0,43 kg | I16: 0,43 kg | J16: 0,43 kg | K16: 0,43 kg | L16: 0,43 kg (0,95 lb) | M16: 0,43 kg (0,95 lb) | N16: 0,43 kg (0,95 lb) | O16: 0.43 kg | P16: 0.43 kg (0.95 lb) | Q16: 0,43 kg | R16: 0,43 kg | S16: 0,43 kg (0,95 lb) | T16: 0,43 kg | U16: 0.43 kg | V16: 0.43 kg | W16: 0.95 lb (0.43 kg) | X16: 0.43千克（0.95磅） | Y16: 0,95 libry (0,43 kg) | Z16: 0,43 kg | AA16: 0,43 kg | AB16: 0,43 kg | AC16: 0,43 kg | AD16: 0,43 kg (0,95 lb)
A17: fet-feature-weight-duke | B17: 11.11 oz (315 g) | C17: 11.11 oz (315 g) | D17: 11.11 oz (315 g) | E17: 11.11 oz (315 g) | F17: 315 g | G17: 315 g | H17: 315 g | I17: 315 g | J17: 315 g | K17: 315 g | L17: 315 g (11,11 oz) | M17: 315 g (11,11 oz) | N17: 315 g (11,11 oz) | O17: 315 g | P17: 315 g (11.11 oz) | Q17: 315 g | R17: 315 g | S17: 315 g (11,11 oz) | T17: 315 g | U17: 315 g | V17: 315 g | W17: 11.11 oz (315 g) | X17: 315克（11.11盎司） | Y17: 11,11 libry (315 g) | Z17: 315 g | AA17: 315 g | AB17: 315 g | AC17: 315 g | AD17: 315 g (11,11 oz)
A18: fet-feature-weight-amp | C18: 4.63 lbs (2.1 kg) | D18: 4.63 lbs (2.1 kg) | E18: 4.63 lbs (2.1 kg) | F18: 2.1 kg | G18: 2.1 kg | H18: 2.1 kg | I18: 2,1 kg | J18: 2,1 kg | K18: 2,1 kg | L18: 2.1 kg (4,63 lb) | M18: 2.1 kg (4,63 lb) | N18: 2.1 kg (4,63 lb) | O18: 2.1 kg | P18: 2.1 kg (4.63 lb) | Q18: 2.1 kg | R18: 2.1 kg | S18: 2.1 kg (4.63 lb) | T18: 2.1 kg | U18: 2.1 kg | V18: 2.1 kg | W18: 4.63 lbs (2.1 kg) | X18: 2.1千克（4.63磅） | Y18: 4,63 libry (2.1 kg) | Z18: 2.1 kg | AA18: 2.1 kg | AB18: 2.1 kg | AC18: 2,1 kg | AD18: 2.1 kg (4.63 lb)
A19: fet-name-arc | B19: Arc | C19: Arc | D19: Arc | E19: Arc | F19: Arc | G19: Arc | H19: Arc | I19: Sonos Arc | J19: Sonos Arc | K19: Sonos Arc | L19: Arc | M19: Arc | N19: Arc | O19: Sonos Arc | P19: Arc | Q19: Arc | R19: Arc | S19: Arc | T19: Arc | U19: Arc | V19: Arc | W19: Arc | X19: Arc | Y19: Arc | Z19: Arc | AA19: Arc | AB19: Arc | AC19: Sonos Arc | AD19: Arc
A20: fet-name-beam | B20: Beam | C20: Beam | D20: Beam | E20: Beam | F20: Beam | G20: Beam | H20: Beam | I20: Sonos Beam | J20: Sonos Beam | K20: Sonos Beam | L20: Beam | M20: Beam | N20: Beam | O20: Sonos Beam | P20: Beam | Q20: Beam | R20: Beam | S20: Beam | T20: Beam | U20: Beam | V20: Beam | W20: Beam | X20: Beam | Y20: Beam | Z20: Beam | AA20: Beam | AB20: Beam | AC20: Sonos Beam | AD20: Beam
A21: fet-name-ray | B21: Ray | C21: Ray | D21: Ray | E21: Ray | F21: Ray | G21: Ray | H21: Ray | I21: Sonos Ray | J21: Sonos Ray | K21: Sonos Ray | L21: Ray | M21: Ray | N21: Ray | O21: Sonos Ray | P21: Ray | Q21: Ray | R21: Ray | S21: Ray | T21: Ray | U21: Ray | V21: Ray | W21: Ray | X21: Ray | Y21: Ray | Z21: Ray | AA21: Ray | AB21: Ray | AC21: Sonos Ray | AD21: Ray
A22: fet-name-sub | C22: Sub | D22: Sub | E22: Sub | F22: Sub | G22: Sub | H22: Sub | I22: Sonos Sub | J22: Sonos Sub | K22: Sonos Sub | L22: Sub | M22: Sub | N22: Sub | O22: Sonos Sub | P22: Sub | Q22: Sub | R22: Sub | S22: Sub | T22: Sub | U22: Sub | V22: Sub | W22: Sub | X22: Sub | Y22: Sub | Z22: Sub | AA22: Sub | AB22: Sub | AC22: Sonos Sub | AD22: Sub
A23: fet-name-gravity | B23: Sub Mini | C23: Sub Mini | D23: Sub Mini | E23: Sub Mini | F23: Sub Mini | G23: Sub Mini | H23: Sub Mini | I23: Sonos Sub Mini | J23: Sonos Sub Mini | K23: Sonos Sub Mini | L23: Sub Mini | M23: Sub Mini | N23: Sub Mini | O23: Sonos Sub Mini | P23: Sub Mini | Q23: Sub Mini | R23: Sub Mini | S23: Sub Mini | T23: Sub Mini | U23: Sub Mini | V23: Sub Mini | W23: Sub Mini | X23: Sub Mini | Y23: Sub Mini | Z23: Sub Mini | AA23: Sub Mini | AB23: Sub Mini | AC23: Sonos Sub Mini | AD23: Sub Mini
A24: fet-name-optimo1 | B24: Era 100 | C24: Era 100 | D24: Era 100 | E24: Era 100 | F24: Era 100 | G24: Era 100 | H24: Era 100 | I24: Sonos Era 100 | J24: Sonos Era 100 | K24: Sonos Era 100 | L24: Era 100 | M24: Era 100 | N24: Era 100 | O24: Sonos Era 100 | P24: Era 100 | Q24: Era 100 | R24: Era 100 | S24: Era 100 | T24: Era 100 | U24: Era 100 | V24: Era 100 | W24: Era 100 | X24: Era 100 | Y24: Era 100 | Z24: Era 100 | AA24: Era 100 | AB24: Era 100 | AC24: Sonos Era 100 | AD24: Era 100
A25: fet-name-optimo2 | B25: Era 300 | C25: Era 300 | D25: Era 300 | E25: Era 300 | F25: Era 300 | G25: Era 300 | H25: Era 300 | I25: Sonos Era 300 | J25: Sonos Era 300 | K25: Sonos Era 300 | L25: Era 300 | M25: Era 300 | N25: Era 300 | O25: Sonos Era 300 | P25: Era 300 | Q25: Era 300 | R25: Era 300 | S25: Era 300 | T25: Era 300 | U25: Era 300 | V25: Era 300 | W25: Era 300 | X25: Era 300 | Y25: Era 300 | Z25: Era 300 | AA25: Era 300 | AB25: Era 300 | AC25: Sonos Era 300 | AD25: Era 300
A26: fet-name-five | B26: Five | C26: Five | D26: Five | E26: Five | F26: Five | G26: Five | H26: Five | I26: Sonos Five | J26: Sonos Five | K26: Sonos Five | L26: Five | M26: Five | N26: Five | O26: Sonos Five | P26: Five | Q26: Five | R26: Five | S26: Five | T26: Five | U26: Five | V26: Five | W26: Five | X26: Five | Y26: Five | Z26: Five | AA26: Five | AB26: Five | AC26: Sonos Five | AD26: Five
A27: fet-name-roam | C27: Roam | D27: Roam | E27: Roam | F27: Roam | G27: Roam | H27: Roam | I27: Sonos Roam | J27: Sonos Roam | K27: Sonos Roam | L27: Roam | M27: Roam | N27: Roam | O27: Sonos Roam | P27: Roam | Q27: Roam | R27: Roam | S27: Roam | T27: Roam | U27: Roam | V27: Roam | W27: Roam | X27: Roam | Y27: Roam | Z27: Roam | AA27: Roam | AB27: Roam | AC27: Sonos Roam | AD27: Roam
A28: fet-name-roam2 | B28: Roam 2 | C28: Roam 2 | D28: Roam 2 | E28: Roam 2 | F28: Roam 2 | G28: Roam 2 | H28: Roam 2 | I28: Sonos Roam 2 | J28: Sonos Roam 2 | K28: Sonos Roam 2 | L28: Roam 2 | M28: Roam 2 | N28: Roam 2 | O28: Sonos Roam 2 | P28: Roam 2 | Q28: Roam 2 | R28: Roam 2 | S28: Roam 2 | T28: Roam 2 | U28: Roam 2 | V28: Roam 2 | W28: Roam 2 | X28: Roam 2 | Y28: Roam 2 | Z28: Roam 2 | AA28: Roam 2 | AB28: Roam 2 | AC28: Sonos Roam 2 | AD28: Roam 2
A29: fet-name-roamsl | C29: Roam SL | D29: Roam SL | E29: Roam SL | F29: Roam SL | G29: Roam SL | H29: Roam SL | I29: Sonos Roam SL | J29: Sonos Roam SL | K29: Sonos Roam SL | L29: Roam SL | M29: Roam SL | N29: Roam SL | O29: Sonos Roam SL | P29: Roam SL | Q29: Roam SL | R29: Roam SL | S29: Roam SL | T29: Roam SL | U29: Roam SL | V29: Roam SL | W29: Roam SL | X29: Roam SL | Y29: Roam SL | Z29: Roam SL | AA29: Roam SL | AB29: Roam SL | AC29: Sonos Roam SL | AD29: Roam SL
A30: fet-name-duke | B30: Sonos Ace | C30: Sonos Ace | D30: Sonos Ace | E30: Sonos Ace | F30: Sonos Ace | G30: Sonos Ace | H30: Sonos Ace | I30: Sonos Ace | J30: Sonos Ace | K30: Sonos Ace | L30: Sonos Ace | M30: Sonos Ace | N30: Sonos Ace | O30: Sonos Ace | P30: Sonos Ace | Q30: Sonos Ace | R30: Sonos Ace | S30: Sonos Ace | T30: Sonos Ace | U30: Sonos Ace | V30: Sonos Ace | W30: Sonos Ace | X30: Sonos Ace | Y30: Sonos Ace | Z30: Sonos Ace | AA30: Sonos Ace | AB30: Sonos Ace | AC30: Sonos Ace | AD30: Sonos Ace
A31: fet-name-move | C31: Move | D31: Move | E31: Move | F31: Move | G31: Move | H31: Move | I31: Sonos Move | J31: Sonos Move | K31: Sonos Move | L31: Move | M31: Move | N31: Move | O31: Sonos Move | P31: Move | Q31: Move | R31: Move | S31: Move | T31: Move | U31: Move | V31: Move | W31: Move | X31: Move | Y31: Move | Z31: Move | AA31: Move | AB31: Move | AC31: Sonos Move | AD31: Move
A32: fet-name-prima | B32: Move 2 | C32: Move 2 | D32: Move 2 | E32: Move 2 | F32: Move 2 | G32: Move 2 | H32: Move 2 | I32: Sonos Move 2 | J32: Sonos Move 2 | K32: Sonos Move 2 | L32: Move 2 | M32: Move 2 | N32: Move 2 | O32: Sonos Move 2 | P32: Move 2 | Q32: Move 2 | R32: Move 2 | S32: Move 2 | T32: Move 2 | U32: Move 2 | V32: Move 2 | W32: Move 2 | X32: Move 2 | Y32: Move 2 | Z32: Move 2 | AA32: Move 2 | AB32: Move 2 | AC32: Sonos Move 2 | AD32: Move 2
A33: fet-name-amp | C33: Amp | D33: Amp | E33: Amp | F33: Amp | G33: Amp | H33: Amp | I33: Sonos Amp | J33: Sonos Amp | K33: Sonos Amp | L33: Amp | M33: Amp | N33: Amp | O33: Sonos Amp | P33: Amp | Q33: Amp | R33: Amp | S33: Amp | T33: Amp | U33: Amp | V33: Amp | W33: Amp | X33: Amp | Y33: Amp | Z33: Amp | AA33: Amp | AB33: Amp | AC33: Sonos Amp | AD33: Amp
A34: fet-badge-dolby-atmos | B34: Dolby Atmos | C34: Dolby Atmos | D34: Dolby Atmos | E34: Dolby Atmos | F34: Dolby Atmos | G34: Dolby Atmos | H34: Dolby Atmos | I34: Dolby Atmos | J34: Dolby Atmos | K34: Dolby Atmos | L34: Dolby Atmos | M34: Dolby Atmos | N34: Dolby Atmos | O34: Dolby Atmos（ドルビーアトモス） | P34: Dolby Atmos | Q34: Dolby Atmos | R34: Dolby Atmos | S34: Dolby Atmos | T34: Dolby Atmos | U34: Dolby Atmos | V34: Dolby Atmos | W34: Dolby Atmos | X34: 杜比全景声 | Y34: Dolby Atmos | Z34: Dolby Atmos | AA34: Dolby Atmos | AB34: Dolby Atmos | AC34: Dolby Atmos | AD34: Dolby Atmos
A35: fet-badge-dolby-head-tracking | C35: Dolby head tracking | D35: Dolby head tracking | E35: Dolby head tracking | F35: Dynamisk hovedsporing | G35: Dolby Head Tracking | H35: Dolby Head Tracking | I35: Suivi dynamique des mouvements de la tête | J35: Suivi dynamique des mouvements de la tête | K35: Suivi dynamique des mouvements de la tête | L35: Suivi dynamique de la tête | M35: Rilevamento dinamico della posizione della testa | N35: Rilevamento dinamico della posizione della testa | O35: Dolbyヘッドトラッキング | P35: Rastreo de cabeza Dolby | Q35: Dolby Head Tracking | R35: Dynamisk hodesporing | S35: Seguimiento de la cabeza Dolby | T35: Dynamisk huvudspårning | U35: Dolby head tracking | V35: Dolby head tracking | W35: Dolby head tracking | X35: 杜比头部追踪 | Y35: Dynamické sledování hlavy | Z35: Dolbyn pään asennon seuranta | AA35: Dynamiczne śledzenie ruchu głowy | AB35: Dolby Head Tracking | AC35: Suivi dynamique des mouvements de la tête | AD35: Rastreo de cabeza Dolby
A36: fet-badge-spatial-audio-with-dynamic-head-tracking-1 | B36: Spatial audio with dynamic head tracking¹ | C36: Spatial audio with dynamic head tracking¹ | D36: Spatial audio with dynamic head tracking¹ | E36: Spatial audio with dynamic head tracking¹ | F36: Rumlig lyd med dynamisk hovedsporing¹ | G36: 3D-Audio mit dynamischem Head Tracking¹ | H36: 3D-Audio mit dynamischem Head Tracking¹ | I36: Audio spatial avec suivi dynamique des mouvements de la tête¹ | J36: Audio spatial avec suivi dynamique des mouvements de la tête¹ | K36: Audio spatial avec suivi dynamique des mouvements de la tête¹ | L36: Audio spatial avec suivi dynamique de la tête¹ | M36: Audio spaziale con rilevamento dinamico della posizione della testa¹ | N36: Audio spaziale con rilevamento dinamico della posizione della testa¹ | O36: 空間オーディオとダイナミックヘッドトラッキング¹ | P36: Audio espacial con seguimiento dinámico de la cabeza¹ | Q36: Ruimtelijke audio met dynamische hoofdtracking | R36: Romtilpasset lyd med dynamisk hodesporing¹ | S36: Audio espacial con seguimiento dinámico de la cabeza¹ | T36: Rymligt ljud med dynamisk huvudspårning¹ | U36: Spatial audio with dynamic head tracking¹ | V36: Spatial audio with dynamic head tracking¹ | W36: Spatial audio with dynamic head tracking¹ | X36: 支持动态头部追踪的空间音频¹ | Y36: Prostorový zvuk s dynamickým sledováním hlavy¹ | Z36: Tilaääni dynaamisella pään asennon seurannalla¹ | AA36: Dźwięk przestrzenny z dynamicznym śledzeniem ruchu głowy¹ | AB36: 3D-Audio mit dynamischem Head Tracking¹ | AC36: Audio spatial avec suivi dynamique des mouvements de la tête¹ | AD36: Audio espacial con seguimiento dinámico de la cabeza1
A37: fet-badge-lossless-audio-2 | B37: Lossless audio² | C37: Lossless audio² | D37: Lossless audio² | E37: Lossless audio² | F37: Tabsfri lyd² | G37: Verlustfreies Audio² | H37: Verlustfreies Audio² | I37: Contenus audio sans perte² | J37: Contenus audio sans perte² | K37: Contenus audio sans perte² | L37: Audio sans perte² | M37: Audio lossless² | N37: Audio lossless² | O37: ロスレスオーディオ² | P37: Audio lossless² | Q37: Lossless audio² | R37: Tapsfri lyd² | S37: Sonido sin pérdidas² | T37: Losslessljud² | U37: Lossless audio² | V37: Lossless audio² | W37: Lossless audio² | X37: 无损音频² | Y37: Bezztrátový zvuk² | Z37: Häviötön ääni² | AA37: Dźwięk bezstratny² | AB37: Verlustfreies Audio² | AC37: Contenus audio sans perte² | AD37: Audio lossless²
A38: fet-badge-enhanced-call-clarity | B38: Enhanced call clarity | C38: Enhanced call clarity | D38: Enhanced call clarity | E38: Enhanced call clarity | F38: Tydeligere opkald | G38: Verbesserte Sprachqualität | H38: Verbesserte Sprachqualität | I38: Un son encore plus clair pour les appels | J38: Un son encore plus clair pour les appels | K38: Un son encore plus clair pour les appels | L38: Clarté accrue des appels | M38: Ottimizzazione della nitidezza delle chiamate | N38: Ottimizzazione della nitidezza delle chiamate | O38: より明瞭な音声 | P38: Nitidez de llamada mejorada | Q38: Duidelijkere telefoongesprekken | R38: Økt anropsklarhet | S38: Mejor calidad de las llamadas | T38: Ökad klarhet för samtal | U38: Enhanced call clarity | V38: Enhanced call clarity | W38: Enhanced call clarity | X38: 增强通话清晰度 | Y38: Zvýšená srozumitelnost hovorů | Z38: Kehittyneempi puhelun selkeys | AA38: Większa wyrazistość połączeń telefonicznych | AB38: Verbesserte Sprachqualität | AC38: Un son encore plus clair pour les appels | AD38: Nitidez de llamada mejorada
A39: fet-badge-active-noise-cancellation-capitalized | C39: Active Noise Cancellation | D39: Active Noise Cancellation | E39: Active Noise Cancellation | F39: Aktiv støjreduktion | G39: Aktive Geräuschunterdrückung | H39: Aktive Geräuschunterdrückung | I39: Réduction active du bruit | J39: Réduction active du bruit | K39: Réduction active du bruit | L39: Annulation active des bruits | M39: Cancellazione attiva del rumore | N39: Cancellazione attiva del rumore | O39: ノイズキャンセリング機能 | P39: Cancelación activa de ruido | Q39: Actieve ruisonderdrukking | R39: Aktiv støykansellering | S39: Cancelación activa de ruido | T39: Aktiv brusreducering | U39: Active Noise Cancellation | V39: Active Noise Cancellation | W39: Active Noise Cancellation | X39: 主动消噪 | Y39: Aktivní potlačení hluku | Z39: Aktiivinen melunvaimennus | AA39: Aktywne tłumienie hałasu | AB39: Aktive Geräuschunterdrückung | AC39: Réduction active du bruit | AD39: Cancelación activa de ruido
A40: fet-badge-active-noise-cancellation | B40: Active Noise Cancellation | C40: Active Noise Cancellation | D40: Active Noise Cancellation | E40: Active Noise Cancellation | F40: Aktiv støjreduktion | G40: Aktive Geräuschunterdrückung | H40: Aktive Geräuschunterdrückung | I40: Réduction active du bruit | J40: Réduction active du bruit | K40: Réduction active du bruit | L40: Annulation active des bruits | M40: Cancellazione attiva del rumore | N40: Cancellazione attiva del rumore | O40: ノイズキャンセリング機能 | P40: Cancelación activa de ruido | Q40: Actieve ruisonderdrukking | R40: Aktiv støykansellering | S40: Cancelación activa de ruido | T40: Aktiv brusreducering | U40: Active Noise Cancellation | V40: Active Noise Cancellation | W40: Active Noise Cancellation | X40: 主动消噪 | Y40: Aktivní potlačení hluku | Z40: Aktiivinen melunvaimennus | AA40: Aktywne tłumienie hałasu | AB40: Aktive Geräuschunterdrückung | AC40: Réduction active du bruit | AD40: Cancelación activa de ruido
A41: fet-badge-aware-mode | B41: Aware mode | C41: Aware mode | D41: Aware mode | E41: Aware mode | F41: Aware mode | G41: Aware Modus | H41: Aware Modus | I41: Mode Aware | J41: Mode Aware | K41: Mode Aware | L41: Mode conscient | M41: Modalità Trasparenza | N41: Modalità Trasparenza | O41: アウェアモード | P41: Modo Ambiente | Q41: Aware-modus | R41: Bevisst modus | S41: Modo Aware | T41: Transparensläge | U41: Aware mode | V41: Aware mode | W41: Aware mode | X41: 感知模式 | Y41: Režim pozornosti | Z41: Valppaustila | AA41: Tryb kontaktu | AB41: Aware Modus | AC41: Mode Aware | AD41: Modo Ambiente
A42: fet-badge-crafted-for-comfort | B42: Crafted for comfort | C42: Crafted for comfort | D42: Crafted for comfort | E42: Crafted for comfort | F42: Designet til komfort | G42: Maximaler Tragekomfort | H42: Maximaler Tragekomfort | I42: Conçu pour un maximum de confort | J42: Conçu pour un maximum de confort | K42: Conçu pour un maximum de confort | L42: Conçu pour le confort | M42: Per la massima comodità | N42: Per la massima comodità | O42: 快適さを求めたデザイン | P42: Diseñados para tu comodidad | Q42: Gemaakt voor comfort | R42: Designet for komfort | S42: Comodidad total | T42: Utformade för bekvämlighet | U42: Crafted for comfort | V42: Crafted for comfort | W42: Crafted for comfort | X42: 精心打造舒适体验 | Y42: Vytvořeno pro pohodlí | Z42: Muotoiltu mukavaksi | AA42: Stworzony z myślą o wygodzie | AB42: Maximaler Tragekomfort | AC42: Conçu pour un maximum de confort | AD42: Diseñados para tu comodidad
A43: fet-badge-badges-dynamic-head-tracking | B43: Dynamic head tracking | C43: Dynamic head tracking | D43: Dynamic head tracking | E43: Dynamic head tracking | F43: Dynamisk hovedsporing | G43: Dynamisches Head Tracking | H43: Dynamisches Head Tracking | I43: Suivi dynamique des mouvements de la tête | J43: Suivi dynamique des mouvements de la tête | K43: Suivi dynamique des mouvements de la tête | L43: Suivi dynamique de la tête | M43: Rilevamento dinamico della posizione della testa | N43: Rilevamento dinamico della posizione della testa | O43: ダイナミックヘッドトラッキング | P43: Seguimiento dinámico de la cabeza | Q43: Dynamische hoofdtracking | R43: Dynamisk hodesporing | S43: Seguimiento dinámico de la cabeza | T43: Dynamisk huvudspårning | U43: Dynamic head tracking | V43: Dynamic head tracking | W43: Dynamic head tracking | X43: 动态头部追踪 | Y43: Dynamické sledování hlavy | Z43: Dynaaminen pään asennon seuranta | AA43: Dynamiczne śledzenie ruchu głowy | AB43: Dynamisches Head Tracking | AC43: Suivi dynamique des mouvements de la tête | AD43: Seguimiento dinámico de la cabeza
A44: fet-badge-custom-designed-40mm-dynamic-drivers | B44: Custom-designed 40mm dynamic drivers | C44: Custom-designed 40mm dynamic drivers | D44: Custom-designed 40 mm dynamic drivers | E44: Custom-designed 40 mm dynamic drivers | F44: Specialudviklede dynamiske drivere på 40 mm | G44: Spezielle dynamische 40-mm-Treiber | H44: Spezielle dynamische 40-mm-Treiber | I44: Haut-parleurs dynamiques de 40 mm conçus sur mesure | J44: Haut-parleurs dynamiques de 40 mm conçus sur mesure | K44: Haut-parleurs dynamiques de 40 mm conçus sur mesure | L44: Haut-parleurs dynamiques de 40 mm conçus sur mesure | M44: Driver dinamici da 40 mm progettati su misura | N44: Driver dinamici da 40 mm progettati su misura | O44: カスタム設計の40mmダイナミックドライバー | P44: Diafragmas dinámicos de diseño exclusivo de 40 mm | Q44: Speciaal ontworpen 40 mm dynamische drivers | R44: Spesialkonstruerte 40 mm dynamiske drivere | S44: Altavoces dinámicos de 40 mm diseñados a medida | T44: Specialdesignade, dynamiska högtalarelement på 40 mm | U44: Custom-designed 40 mm dynamic drivers | V44: Custom-designed 40 mm dynamic drivers | W44: Custom-designed 40 mm dynamic drivers | X44: 定制设计40毫米动态驱动器 | Y44: Na míru vytvořené 40mm dynamické ovladače | Z44: Kustomoidut 40 mm:n dynaamiset ohjaimet | AA44: Specjalnie zaprojektowane przetworniki dynamiczne o średnicy 40 mm | AB44: Spezielle dynamische 40-mm-Treiber | AC44: Haut-parleurs dynamiques de 40 mm conçus sur mesure | AD44: Diafragmas dinámicos de diseño exclusivo de 40 mm
A45: fet-badge-adjustable-eq | B45: Adjustable EQ | C45: Adjustable EQ | D45: Adjustable EQ | E45: Adjustable EQ | F45: Justerbar equalizer | G45: Verstellbarer Equalizer | H45: Verstellbarer Equalizer | I45: Égalisation réglable | J45: Égalisation réglable | K45: Égalisation réglable | L45: EQ ajustable | M45: Equalizzazione regolabile | N45: Equalizzazione regolabile | O45: 調整可能なイコライザー | P45: Ecualización ajustable | Q45: Aanpasbare EQ | R45: Justerbar EQ | S45: Ecualización regulable | T45: Justerbar EQ | U45: Adjustable EQ | V45: Adjustable EQ | W45: Adjustable EQ | X45: 可调整EQ | Y45: Nastavitelný ekvalizér | Z45: Säädettävä äänentasaus | AA45: Korektor graficzny (EQ) z możliwością regulacji | AB45: Verstellbarer Equalizer | AC45: Égalisation réglable | AD45: Ecualización ajustable
A46: fet-badge-voice-enabled | B46: Voice enabled | C46: Voice enabled | D46: Voice-enabled | E46: Voice-enabled | F46: Indbygget stemmestyring | G46: Sprachsteuerung | H46: Sprachsteuerung | I46: Contrôle vocal | J46: Contrôle vocal | K46: Contrôle vocal | L46: Compatible avec le contrôle vocal | M46: Controllo vocale | N46: Controllo vocale | O46: 音声操作対応 | P46: Control por voz | Q46: Met spraakbediening | R46: Stemmestyring er aktivert | S46: Control por voz | T46: Redo för röststyrning | U46: Voice-enabled | V46: Voice-enabled | W46: Voice-enabled | X46: 支持语音功能 | Y46: Aktivace hlasem | Z46: Puheohjaus | AA46: Funkcja sterowania głosowego | AB46: Sprachsteuerung | AC46: Contrôle vocal | AD46: Control por voz
A47: fet-badge-wifi | B47: WiFi | C47: WiFi | D47: WiFi | E47: WiFi | F47: WiFi | G47: WLAN | H47: WLAN | I47: Wi-Fi | J47: Wi-Fi | K47: Wi-Fi | L47: Wi-Fi | M47: Wi-Fi | N47: Wi-Fi | O47: WiFi | P47: WiFi | Q47: Wifi | R47: Wi-Fi | S47: Wi-Fi | T47: Wi-Fi | U47: WiFi | V47: WiFi | W47: WiFi | X47: Wi-Fi | Y47: Wi-Fi | Z47: WiFi | AA47: Wi-Fi | AB47: WLAN | AC47: Wi-Fi | AD47: WiFi
A48: fet-badge-trueplay-tm | B48: Trueplay™ | C48: Trueplay™ | D48: Trueplay™ | E48: Trueplay™ | F48: Trueplay™ | G48: Trueplay™ | H48: Trueplay™ | I48: Trueplay™ | J48: Trueplay™ | K48: Trueplay™ | L48: Trueplay™ | M48: Trueplay™ | N48: Trueplay™ | O48: Trueplay™ | P48: Trueplay™ | Q48: Trueplay™ | R48: Trueplay™ | S48: Trueplay™ | T48: Trueplay™ | U48: Trueplay™ | V48: Trueplay™ | W48: Trueplay™ | X48: Trueplay™调音 | Y48: Trueplay™ | Z48: Trueplay™ | AA48: Trueplay™ | AB48: Trueplay™ | AC48: Trueplay™ | AD48: Trueplay™
A49: fet-badge-tv-remote-sync | C49: TV remote sync | D49: TV remote sync | E49: TV remote sync | F49: Synkronisering med TV-remote | G49: Synchronisierung mit der TV-Fernbedienung | H49: Synchronisierung mit der TV-Fernbedienung | I49: Synchronisation avec la télécommande de votre TV | J49: Synchronisation avec la télécommande de votre TV | K49: Synchronisation avec la télécommande de votre TV | L49: Synchronisation de la télécommande du téléviseur | M49: Sincronizzazione del telecomando della TV | N49: Sincronizzazione del telecomando della TV | O49: テレビのリモコンと同期 | P49: Sincronización con el control de la TV | Q49: Afstandsbediening-synchronisatie | R49: Synkronisering av fjernkontroll til TV | S49: Sincronización con el mando de la tele | T49: Synkronisering med fjärrkontrollen till tv:n | U49: TV remote sync | V49: TV remote sync | W49: TV remote sync | X49: 电视遥控器同步 | Y49: Synchronní s dálkovým ovladačem televize | Z49: TV-kaukosäätimen synkronointi | AA49: Synchronizacja pilota telewizyjnego | AB49: Synchronisierung mit der TV-Fernbedienung | AC49: Synchronisation avec la télécommande de votre TV | AD49: Sincronización con el control de la TV
A50: fet-badge-hdmi-earc | C50: HDMI eARC | D50: HDMI eARC | E50: HDMI eARC | F50: HDMI eARC | G50: HDMI eARC | H50: HDMI eARC | I50: HDMI eARC | J50: HDMI eARC | K50: HDMI eARC | L50: HDMI eARC | M50: HDMI eARC | N50: HDMI eARC | O50: HDMI eARC | P50: HDMI eARC | Q50: HDMI eARC | R50: HDMI eARC | S50: HDMI eARC | T50: HDMI eARC | U50: HDMI eARC | V50: HDMI eARC | W50: HDMI eARC | X50: HDMI eARC | Y50: HDMI eARC | Z50: HDMI eARC | AA50: HDMI eARC | AB50: HDMI eARC | AC50: HDMI eARC | AD50: HDMI eARC
A51: fet-badge-hdmi-arc | C51: HDMI ARC | D51: HDMI ARC | E51: HDMI ARC | F51: HDMI ARC | G51: HDMI ARC | H51: HDMI ARC | I51: HDMI ARC | J51: HDMI ARC | K51: HDMI ARC | L51: HDMI ARC | M51: HDMI ARC | N51: HDMI ARC | O51: HDMI ARC | P51: HDMI ARC | Q51: HDMI ARC | R51: HDMI ARC | S51: HDMI ARC | T51: HDMI ARC | U51: HDMI ARC | V51: HDMI ARC | W51: HDMI ARC | X51: HDMI ARC | Y51: HDMI ARC | Z51: HDMI ARC | AA51: HDMI ARC | AB51: HDMI ARC | AC51: HDMI ARC | AD51: HDMI ARC
A52: fet-badge-apple-airplay2 | C52: Apple AirPlay 2 | D52: Apple AirPlay 2 | E52: Apple AirPlay 2 | F52: Apple AirPlay 2 | G52: Apple AirPlay 2 | H52: Apple AirPlay 2 | I52: Apple AirPlay 2 | J52: Apple AirPlay 2 | K52: Apple AirPlay 2 | L52: AirPlay 2 d’Apple | M52: Apple AirPlay 2 | N52: Apple AirPlay 2 | O52: Apple AirPlay 2 | P52: Apple AirPlay 2 | Q52: Apple AirPlay 2 | R52: Apple AirPlay 2 | S52: AirPlay 2 de Apple | T52: Apple AirPlay 2 | U52: Apple AirPlay 2 | V52: Apple AirPlay 2 | W52: Apple AirPlay 2 | X52: Apple AirPlay 2 | Y52: Apple AirPlay 2 | Z52: Apple AirPlay 2 | AA52: Apple AirPlay 2 | AB52: Apple AirPlay 2 | AC52: Apple AirPlay 2 | AD52: Apple AirPlay 2
A53: fet-badge-touch-controls | C53: Touch controls | D53: Touch controls | E53: Touch controls | F53: Touchbetjening | G53: Touch Steuerung | H53: Touch Steuerung | I53: Commandes tactiles | J53: Commandes tactiles | K53: Commandes tactiles | L53: Commandes tactiles | M53: Controlli touch | N53: Controlli touch | O53: タッチ操作 | P53: Controles táctiles | Q53: Touchtoetsen | R53: Berøringskontroller | S53: Controles táctiles | T53: Touchkontroller | U53: Touch controls | V53: Touch controls | W53: Touch controls | X53: 触摸控件 | Y53: Dotykové ovládací prvky | Z53: Kosketussäätimet | AA53: Sterowanie dotykowe | AB53: Touch Steuerung | AC53: Commandes tactiles | AD53: Controles táctiles
A54: fet-badge-optical | C54: Optical | D54: Optical | E54: Optical | F54: Optisk | G54: Optisches Kabel | H54: Optisches Kabel | I54: Optique | J54: Optique | K54: Optique | L54: Optique | M54: Ottico | N54: Ottico | O54: 光デジタルオーディオ | P54: Conexión óptica | Q54: Optisch | R54: Optisk | S54: Óptico | T54: Optisk | U54: Optical | V54: Optical | W54: Optical | X54: 光纤 | Y54: Optický | Z54: Optinen | AA54: Optyczny | AB54: Optisches Kabel | AC54: Optique | AD54: Conexión óptica
A55: fet-badge-dual-orientation | C55: Dual orientation | D55: Dual orientation | E55: Dual orientation | F55: To positioner | G55: Duale Ausrichtung | H55: Duale Ausrichtung | I55: Double orientation | J55: Double orientation | K55: Double orientation | L55: Deux orientations | M55: Doppio orientamento | N55: Doppio orientamento | O55: 縦横どちらでも設置可能 | P55: Orientación doble | Q55: Twee standen | R55: Flere plasseringsmuligheter | S55: Dos posiciones | T55: Dubbelriktad | U55: Dual orientation | V55: Dual orientation | W55: Dual orientation | X55: 两种摆放方向 | Y55: Dvojí umístění | Z55: Kaksisuuntainen | AA55: Możliwość ustawienia w dwóch pozycjach | AB55: Duale Ausrichtung | AC55: Double orientation | AD55: Orientación doble
A56: fet-badge-line-in | C56: Line in | D56: Line-in | E56: Line-in | F56: Line-in | G56: Eingang | H56: Eingang | I56: Entrée auxiliaire | J56: Entrée auxiliaire | K56: Entrée auxiliaire | L56: Connexion d’entrée | M56: Line-in | N56: Line-in | O56: ライン入力 | P56: Entrada de línea | Q56: Lijningang | R56: Line-in | S56: Entrada de línea | T56: Linjeingång | U56: Line-in | V56: Line-in | W56: Line-in | X56: 线路输入 | Y56: Linkový vstup | Z56: Linjatulo | AA56: Wejście liniowe | AB56: Eingang | AC56: Entrée auxiliaire | AD56: Entrada de línea
A57: fet-badge-humidity-resistant | C57: Humidity resistant | D57: Humidity resistant | E57: Humidity resistant | F57: Fugtresistent | G57: Feuchtigkeitsbeständig | H57: Feuchtigkeitsbeständig | I57: Résistant à l'humidité | J57: Résistant à l'humidité | K57: Résistant à l'humidité | L57: Résistant à l’humidité | M57: Resistente all’umidità | N57: Resistente all’umidità | O57: 防湿設計 | P57: Resistente a la humedad | Q57: Vochtbestendig | R57: Fuktighetsbestandig | S57: Resistente a la humedad | T57: Fukttålig | U57: Humidity resistant | V57: Humidity resistant | W57: Humidity resistant | X57: 防潮 | Y57: Odolný proti vlhkosti | Z57: Kosteudenkestävä | AA57: Odporny na wilgoć | AB57: Feuchtigkeitsbeständig | AC57: Résistant à l'humidité | AD57: Resistente a la humedad
A58: fet-badge-bluetooth-r | C58: Bluetooth® | D58: Bluetooth® | E58: Bluetooth® | F58: Bluetooth® | G58: Bluetooth® | H58: Bluetooth® | I58: Bluetooth® | J58: Bluetooth® | K58: Bluetooth® | L58: Bluetooth® | M58: Bluetooth® | N58: Bluetooth® | O58: Bluetooth® | P58: Bluetooth® | Q58: Bluetooth® | R58: Bluetooth® | S58: Bluetooth® | T58: Bluetooth® | U58: Bluetooth® | V58: Bluetooth® | W58: Bluetooth® | X58: 蓝牙 | Y58: Bluetooth® | Z58: Bluetooth® | AA58: Bluetooth® | AB58: Bluetooth® | AC58: Bluetooth® | AD58: Bluetooth®
A59: fet-badge-bluetooth | C59: Bluetooth | D59: Bluetooth | E59: Bluetooth | F59: Bluetooth | G59: Bluetooth | H59: Bluetooth | I59: Bluetooth | J59: Bluetooth | K59: Bluetooth | L59: Bluetooth | M59: Bluetooth | N59: Bluetooth | O59: Bluetooth | P59: Bluetooth | Q59: Bluetooth | R59: Bluetooth | S59: Bluetooth | T59: Bluetooth | U59: Bluetooth | V59: Bluetooth | W59: Bluetooth | X59: 蓝牙 | Y59: Bluetooth | Z59: Bluetooth | AA59: Bluetooth | AB59: Bluetooth | AC59: Bluetooth | AD59: Bluetooth
A60: fet-badge-battery-life-30 | C60: 30 hour battery life | D60: 30-hour battery life | E60: 30-hour battery life | F60: 30 timers batteritid | G60: 30 Stunden Akkulaufzeit | H60: 30 Stunden Akkulaufzeit | I60: Jusqu'à 30 heures d'autonomie | J60: Jusqu'à 30 heures d'autonomie | K60: Jusqu'à 30 heures d'autonomie | L60: 30 heures d’autonomie | M60: Batteria con un’autonomia di 30 ore | N60: Batteria con un’autonomia di 30 ore | O60: 30時間駆動可能のバッテリー | P60: 30 horas de batería | Q60: 30 uur batterijduur | R60: 30 timers batteritid | S60: 30 horas de autonomía | T60: 30 timmars batteritid | U60: 30-hour battery life | V60: 30-hour battery life | W60: 30-hour battery life | X60: 30小时电池续航时间 | Y60: 30hodinová výdrž baterie | Z60: 30 tunnin akunkesto | AA60: 30 godzin pracy na akumulatorze | AB60: 30 Stunden Akkulaufzeit | AC60: Jusqu'à 30 heures d'autonomie | AD60: 30 horas de batería
... A72: fet-badge-automatic-trueplay-tm3 | C72: Automatic Trueplay™³ | D72: Automatic Trueplay™³ | E72: Automatic Trueplay™³ | F72: Automatisk Trueplay™³ | G72: Automatisches Trueplay™³ | H72: Automatisches Trueplay™³ | I72: Trueplay™ automatique³ | J72: Trueplay™ automatique³ | K72: Trueplay™ automatique³ | L72: Réglage Trueplay™ automatique³ | M72: Ottimizzazione automatica Trueplay™³ | N72: Ottimizzazione automatica Trueplay™³ | O72: オートマティックTrueplay™³ | P72: Trueplay™ automático³ | Q72: Automatische Trueplay™³ | R72: Automatisk Trueplay™³ | S72: Trueplay™ automático³ | T72: Automatisk Trueplay™³ | U72: Automatic Trueplay™³ | V72: Automatic Trueplay™³ | W72: Automatic Trueplay™³ | X72: 自适应Trueplay™调音³ | Y72: Automatické ladění Trueplay™³ | Z72: Automaattinen Trueplay™³ | AA72: Automatyczna regulacja Trueplay™³ | AB72: Automatisches Trueplay™³ | AC72: Trueplay™ automatique³ | AD72: Trueplay™ automático³
A73: fet-feature-true-play | B73: Trueplay | C73: Trueplay | D73: Trueplay | E73: Trueplay | F73: Trueplay | G73: Trueplay | H73: Trueplay | I73: Trueplay | J73: Trueplay | K73: Trueplay | L73: Trueplay | M73: Trueplay | N73: Trueplay | O73: Trueplay | P73: Trueplay | Q73: Trueplay | R73: Trueplay | S73: Trueplay | T73: Trueplay | U73: Trueplay | V73: Trueplay | W73: Trueplay | X73: Trueplay | Y73: Trueplay | Z73: Trueplay | AA73: Trueplay | AB73: Trueplay | AC73: Trueplay | AD73: Trueplay
A74: fet-badge-waterproof-ip67 | C74: Waterproof (IP67) | D74: Waterproof (IP67) | E74: Waterproof (IP67) | F74: Vandtæt (IP67) | G74: Wasserdicht (IP67) | H74: Wasserdicht (IP67) | I74: Étanche (IP67) | J74: Étanche (IP67) | K74: Étanche (IP67) | L74: Étanche (IP67) | M74: Impermeabile (IP67) | N74: Impermeabile (IP67) | O74: 防水設計（IP67） | P74: A prueba de agua (IP67) | Q74: Waterdicht (IP67) | R74: Vanntett (IP67) | S74: Impermeable (IP67) | T74: Vattentät (IP67) | U74: Waterproof (IP67) | V74: Waterproof (IP67) | W74: Waterproof (IP67) | X74: 防水（IP67） | Y74: Vodotěsný (IP67) | Z74: Vedenpitävä (IP67) | AA74: Wodoodporny (IP67) | AB74: Wasserdicht (IP67) | AC74: Étanche (IP67) | AD74: A prueba de agua (IP67)
A75: fet-badge-waterproof-ip67-1 | C75: Waterproof (IP67)¹ | D75: Waterproof (IP67)¹ | E75: Waterproof (IP67)¹ | F75: Vandtæt (IP67)¹ | G75: Wasserdicht (IP67)¹ | H75: Wasserdicht (IP67)¹ | I75: Étanche (IP67)¹ | J75: Étanche (IP67)¹ | K75: Étanche (IP67)¹ | L75: Étanche (IP67)¹ | M75: Impermeabile (IP67)¹ | N75: Impermeabile (IP67)¹ | O75: 防水設計（IP67）¹ | P75: A prueba de agua (IP67)¹ | Q75: Waterdicht (IP67)¹ | R75: Vanntett (IP67)¹ | S75: Impermeable (IP67)¹ | T75: Vattentät (IP67)¹ | U75: Waterproof (IP67)¹ | V75: Waterproof (IP67)¹ | W75: Waterproof (IP67)¹ | X75: 防水（IP67）¹ | Y75: Vodotěsný (IP67)¹ | Z75: Vedenpitävä (IP67)¹ | AA75: Wodoodporny (IP67)¹ | AB75: Wasserdicht (IP67)¹ | AC75: Étanche (IP67)¹ | AD75: A prueba de agua (IP67)¹
A76: fet-badge-button-controls | C76: Button controls | D76: Button controls | E76: Button controls | F76: Knapbetjening | G76: Tastensteuerungen | H76: Tastensteuerungen | I76: Commandes physiques | J76: Commandes physiques | K76: Commandes physiques | L76: Boutons de commande | M76: Pulsanti | N76: Pulsanti | O76: ボタン操作 | P76: Botones de control | Q76: Knopbediening | R76: Knappekontroller | S76: Botones de control | T76: Kontrollknappar | U76: Button controls | V76: Button controls | W76: Button controls | X76: 按钮控件 | Y76: Tlačítkové ovládací prvky | Z76: Painikesäädöt | AA76: Sterowanie za pomocą przycisków | AB76: Tastensteuerungen | AC76: Commandes physiques | AD76: Botones de control
A77: fet-badge-ethernet | C77: Ethernet | D77: Ethernet | E77: Ethernet | F77: Ethernet | G77: Ethernet | H77: Ethernet | I77: Ethernet | J77: Ethernet | K77: Ethernet | L77: Ethernet | M77: Ethernet | N77: Ethernet | O77: イーサネット | P77: Ethernet | Q77: Ethernet | R77: Ethernet | S77: Ethernet | T77: Ethernet | U77: Ethernet | V77: Ethernet | W77: Ethernet | X77: 以太网 | Y77: Ethernet | Z77: Ethernet | AA77: Ethernet | AB77: Ethernet | AC77: Ethernet | AD77: Ethernet
A78: fet-badge-usbc | C78: USB-C | D78: USB-C | E78: USB-C | F78: USB-C | G78: USB-C | H78: USB-C | I78: USB-C | J78: USB-C | K78: USB-C | L78: USB-C | M78: Porta USB-C | N78: Porta USB-C | O78: USB-C | P78: USB-C | Q78: USB-C | R78: USB-C | S78: USB-C | T78: USB-C | U78: USB-C | V78: USB-C | W78: USB-C | X78: USB-C | Y78: USB-C | Z78: USB-C | AA78: USB-C | AB78: USB-C | AC78: USB-C | AD78: USB-C
A79: fet-badge-usbc-port | C79: USB-C Port | D79: USB-C Port | E79: USB-C Port | F79: USB-C-port | G79: USB-C-Port | H79: USB-C-Port | I79: Port USB-C | J79: Port USB-C | K79: Port USB-C | L79: Port USB-C | M79: Porta USB-C | N79: Porta USB-C | O79: USB-Cポート | P79: Puerto USB-C | Q79: USB-C-poort | R79: USB-C-port | S79: Puerto USB-C | T79: USB-C-port | U79: USB-C Port | V79: USB-C Port | W79: USB-C Port | X79: USB-C端口 | Y79: USB-C port | Z79: USB-C-portti | AA79: Port USB-C | AB79: USB-C-Port | AC79: Port USB-C | AD79: Puerto USB-C
A80: fet-feature-audio | C80: Audio | D80: Audio | E80: Audio | F80: Lyd | G80: Audio | H80: Audio | I80: Audio | J80: Audio | K80: Audio | L80: Audio | M80: Audio | N80: Audio | O80: オーディオ | P80: Audio | Q80: Geluid | R80: Lyd | S80: Sonido | T80: Ljud | U80: Audio | V80: Audio | W80: Audio | X80: 音频 | Y80: Audio | Z80: Ääni | AA80: Dźwięk | AB80: Audio | AC80: Audio | AD80: Audio
A81: fet-feature-acoustic-ports | C81: Acoustic ports | D81: Acoustic ports | E81: Acoustic ports | F81: Akustiske porte | G81: Akustikports | H81: Akustikports | I81: Évents acoustiques | J81: Évents acoustiques | K81: Évents acoustiques | L81: Ports acoustiques | M81: Porte audio | N81: Porte audio | O81: アコースティックポート | P81: Puertos acústicos | Q81: Akoestische poorten | R81: Akustiske porter | S81: Puertos acústicos | T81: Akustiska portar | U81: Acoustic ports | V81: Acoustic ports | W81: Acoustic ports | X81: 声学端口 | Y81: Zvukové porty | Z81: Akustiset portit | AA81: Wejścia akustyczne | AB81: Akustikports | AC81: Évents acoustiques | AD81: Puertos acústicos
A82: fet-feature-amplifiers | B82: Amplifiers | C82: Amplifiers | D82: Amplifiers | E82: Amplifiers | F82: Forstærkere | G82: Verstärker | H82: Verstärker | I82: Amplificateurs | J82: Amplificateurs | K82: Amplificateurs | L82: Amplificateurs | M82: Amplificatori | N82: Amplificatori | O82: アンプ | P82: Amplificadores | Q82: Versterkers | R82: Forsterkere | S82: Amplificadores | T82: Förstärkare | U82: Amplifiers | V82: Amplifiers | W82: Amplifiers | X82: 放大器 | Y82: Zesilovače | Z82: Vahvistimet | AA82: Wzmacniacze | AB82: Verstärker | AC82: Amplificateurs | AD82: Amplificadores
A83: fet-feature-class-d-digital-amplifier | C83: Class-D digital amplifier | D83: Class-D digital amplifier | E83: Class-D digital amplifier | F83: Digital klasse D-forstærker | G83: Digitaler Verstärker der Klasse D | H83: Digitaler Verstärker der Klasse D | I83: Amplificateur numérique de classe D | J83: Amplificateur numérique de classe D | K83: Amplificateur numérique de classe D | L83: Amplificateur numérique de classe D | M83: Amplificatore digitale classe D | N83: Amplificatore digitale classe D | O83: クラスDデジタルアンプ | P83: Amplificador digital de clase D | Q83: D-klasse digitale versterker | R83: Digitalforsterker i klasse D | S83: Amplificador digital de clase D | T83: Digital klass D-förstärkare | U83: Class-D digital amplifier | V83: Class-D digital amplifier | W83: Class-D digital amplifier | X83: D类数字功放 | Y83: Digitální zesilovač třídy D | Z83: D-luokan digitaalivahvistin | AA83: Cyfrowy wzmacniacz impulsowy | AB83: Digitaler Verstärker der Klasse D | AC83: Amplificateur numérique de classe D | AD83: Amplificador digital de clase D
A84: fet-feature-class-d-digital-amplifiers | C84: Class-D digital amplifiers | D84: Class-D digital amplifiers | E84: Class-D digital amplifiers | F84: Digitale klasse D-forstærkere | G84: Digitale Verstärker der Klasse D | H84: Digitale Verstärker der Klasse D | I84: Amplificateurs numériques de classe D | J84: Amplificateurs numériques de classe D | K84: Amplificateurs numériques de classe D | L84: Amplificateurs numériques de classe D | M84: Amplificatori digitali classe D | N84: Amplificatori digitali classe D | O84: クラスDデジタルアンプ | P84: Amplificadores digitales de clase D | Q84: D-klasse digitale versterkers | R84: Digitalforsterkere i klasse D | S84: Amplificadores digitales de clase D | T84: Digitala klass D-förstärkare | U84: Class-D digital amplifiers | V84: Class-D digital amplifiers | W84: Class-D digital amplifiers | X84: D类数字放大器 | Y84: Digitální zesilovače třídy D | Z84: D-luokan digitaalivahvistimet | AA84: Cyfrowe wzmacniacze impulsowe | AB84: Digitale Verstärker der Klasse D | AC84: Amplificateurs numériques de classe D | AD84: Amplificadores digitales de clase D
A85: fet-feature-class-h-digital-amplifier | C85: Class-H digital amplifier | D85: Class-H digital amplifier | E85: Class-H digital amplifier | F85: Digital klasse H-forstærker | G85: Digitaler Verstärker der Klasse H | H85: Digitaler Verstärker der Klasse H | I85: Amplificateur numérique de classe H | J85: Amplificateur numérique de classe H | K85: Amplificateur numérique de classe H | L85: Amplificateur numérique de classe H | M85: Amplificatore digitale classe H | N85: Amplificatore digitale classe H | O85: クラスHデジタルアンプ | P85: Amplificador digital de clase H | Q85: H-klasse digitale versterker | R85: Digitalforsterker i klasse H | S85: Amplificador digital de clase H | T85: Digital klass H-förstärkare | U85: Class-H digital amplifier | V85: Class-H digital amplifier | W85: Class-H digital amplifier | X85: H类数字放大器 | Y85: Digitální zesilovač třídy H | Z85: H-luokan digitaalivahvistin | AA85: Cyfrowy wzmacniacz klasy H | AB85: Digitaler Verstärker der Klasse H | AC85: Amplificateur numérique de classe H | AD85: Amplificador digital de clase H
A86: fet-feature-class-h-digital-amplifiers | C86: Class-H digital amplifiers | D86: Class-H digital amplifiers | E86: Class-H digital amplifiers | F86: Digitale klasse H-forstærkere | G86: Digitale Verstärker der Klasse H | H86: Digitale Verstärker der Klasse H | I86: Amplificateurs numériques de classe H | J86: Amplificateurs numériques de classe H | K86: Amplificateurs numériques de classe H | L86: Amplificateurs numériques de classe H | M86: Amplificatori digitali classe H | N86: Amplificatori digitali classe H | O86: クラスHデジタルアンプ | P86: Amplificadores digitales de clase H | Q86: H-klasse digitale versterkers | R86: Digitalforsterkere i klasse H | S86: Amplificadores digitales de clase H | T86: Digitala klass H-förstärkare | U86: Class-H digital amplifiers | V86: Class-H digital amplifiers | W86: Class-H digital amplifiers | X86: H类数字放大器 | Y86: Digitální zesilovače třídy H | Z86: H-luokan digitaalivahvistimet | AA86: Cyfrowe wzmacniacze klasy H | AB86: Digitale Verstärker der Klasse H | AC86: Amplificateurs numériques de classe H | AD86: Amplificadores digitales de clase H
A87: fet-feature-tweeter | C87: Tweeter | D87: Tweeter | E87: Tweeter | F87: Tweeter | G87: Hochtöner | H87: Hochtöner | I87: Tweeter | J87: Tweeter | K87: Tweeter | L87: Haut-parleur d’aigus | M87: Tweeter | N87: Tweeter | O87: ツイーター | P87: Tweeter | Q87: Tweeter | R87: Diskanthøyttaler | S87: Tweeter | T87: Diskant | U87: Tweeter | V87: Tweeter | W87: Tweeter | X87: 高音扬声器 | Y87: Tweeter | Z87: Diskanttikaiutin | AA87: Głośnik wysokotonowy | AB87: Hochtöner | AC87: Tweeter | AD87: Tweeter
A88: fet-feature-tweeters | C88: Tweeters | D88: Tweeters | E88: Tweeters | F88: Tweetere | G88: Hochtöner | H88: Hochtöner | I88: Tweeters | J88: Tweeters | K88: Tweeters | L88: Haut-parleurs d’aigus | M88: Tweeter | N88: Tweeter | O88: ツイーター | P88: Tweeters | Q88: Tweeters | R88: Diskanthøyttalere | S88: Tweeters | T88: Diskanter | U88: Tweeters | V88: Tweeters | W88: Tweeters | X88: 高音扬声器 | Y88: Tweetery | Z88: Diskanttikaiuttimet | AA88: Głośniki wysokotonowe | AB88: Hochtöner | AC88: Tweeters | AD88: Tweeters
A89: fet-feature-precisely-angled-silk-dome-tweeters | C89: Precisely angled silk-dome tweeters | D89: Precisely angled silk-dome tweeters | E89: Precisely angled silk-dome tweeters | F89: Præcist vinklede tweetere med silkekuppel | G89: Präzise ausgerichtete Seidenkalotten-Hochtöner | H89: Präzise ausgerichtete Seidenkalotten-Hochtöner | I89: Tweeters équipés d'un dôme en soie et orientés avec précision | J89: Tweeters équipés d'un dôme en soie et orientés avec précision | K89: Tweeters équipés d'un dôme en soie et orientés avec précision | L89: Haut-parleurs d’aigus à membrane en soie précisément inclinés | M89: Tweeter con cupola in seta appositamente calibrati | N89: Tweeter con cupola in seta appositamente calibrati | O89: 正確な角度で設置されたシルクドームツイーター | P89: Tweeters con cono de seda inclinados con precisión | Q89: Nauwkeurig gerichte silk-dome tweeters | R89: Presist vinklede diskanthøyttalere med silkekupler | S89: Tweeters con cúpula de seda inclinados con total precisión | T89: Exakt vinklade diskanter med sidenkupoler | U89: Precisely angled silk-dome tweeters | V89: Precisely angled silk-dome tweeters | W89: Precisely angled silk-dome tweeters | X89: 角度精确的丝膜半球高音扬声器 | Y89: Přesně nakloněné tweetery s hedvábnou kopulí | Z89: Tarkasti suunnatut silkkikupumalliset diskanttikaiuttimet | AA89: Głośniki wysokotonowe z jedwabną kopułką, ustawioną pod precyzyjnie dobranym kątem | AB89: Präzise ausgerichtete Seidenkalotten-Hochtöner | AC89: Tweeters équipés d'un dôme en soie et orientés avec précision | AD89: Tweeters con cono de seda inclinados con precisión
A90: fet-feature-angled-tweeters | C90: Angled tweeters | D90: Angled tweeters | E90: Angled tweeters | F90: Vinklede tweetere | G90: Abgewinkelte Hochtöner | H90: Abgewinkelte Hochtöner | I90: Tweeters orientés | J90: Tweeters orientés | K90: Tweeters orientés | L90: Haut-parleurs d’aigus inclinés | M90: Tweeter laterali inclinati | N90: Tweeter laterali inclinati | O90: 緻密に計算された角度で搭載されたツイーター | P90: Tweeters inclinados | Q90: Gerichte tweeters | R90: Vinklede diskanthøyttalere | S90: Tweeters inclinados | T90: Vinklade diskanter | U90: Angled tweeters | V90: Angled tweeters | W90: Angled tweeters | X90: 成角度的高音扬声器 | Y90: Nakloněné tweetery | Z90: Suunnatut diskanttikaiuttimet | AA90: Ustawione pod kątem głośniki wysokotonowe | AB90: Abgewinkelte Hochtöner | AC90: Tweeters orientés | AD90: Tweeters inclinados
A91: fet-feature-woofers | B91: Woofers | C91: Woofers | D91: Woofers | E91: Woofers | F91: Woofere | G91: Tieftöner | H91: Tieftöner | I91: Woofers | J91: Woofers | K91: Woofers | L91: Caissons de basses | M91: Woofer | N91: Woofer | O91: ウーファー | P91: Woofers | Q91: Woofers | R91: Woofere | S91: Woofers | T91: Woofers | U91: Woofers | V91: Woofers | W91: Woofers | X91: 低音扬声器 | Y91: Basové měniče | Z91: Bassokaiuttimet | AA91: Głośniki niskotonowe | AB91: Tieftöner | AC91: Woofers | AD91: Woofers
A92: fet-feature-woofer | C92: Woofer | D92: Woofer | E92: Woofer | F92: Woofer | G92: Tieftöner | H92: Tieftöner | I92: Woofer | J92: Woofer | K92: Woofer | L92: Caisson de basses | M92: Woofer | N92: Woofer | O92: ウーファー | P92: Woofer | Q92: Woofer | R92: Woofer | S92: Woofer | T92: Woofer | U92: Woofer | V92: Woofer | W92: Woofer | X92: 低音扬声器 | Y92: Basový měnič | Z92: Bassokaiutin | AA92: Głośnik niskotonowy | AB92: Tieftöner | AC92: Woofer | AD92: Woofer
A93: fet-feature-midwoofer | C93: Midwoofer | D93: Midwoofer | E93: Mid-woofer | F93: Midwoofer | G93: Mitteltöner | H93: Mitteltöner | I93: Mid-woofers | J93: Mid-woofers | K93: Mid-woofers | L93: Haut-parleur de graves médians | M93: Mid-woofer | N93: Mid-woofer | O93: ミッドウーファー | P93: Woofer de rango medio | Q93: Midwoofer | R93: Mellom-woofer | S93: Altavoz de medios | T93: Mid-woofer | U93: Mid-woofer | V93: Mid-woofer | W93: Mid-woofer | X93: 中低音扬声器 | Y93: Středobasový měnič | Z93: Midwoofer | AA93: Głośnik średniotonowy | AB93: Mitteltöner | AC93: Mid-woofers | AD93: Woofer de rango medio
A94: fet-feature-midwoofers | C94: Midwoofers | D94: Midwoofers | E94: Mid-woofers | F94: Midwoofere | G94: Mitteltöner | H94: Mitteltöner | I94: Mid-woofers | J94: Mid-woofers | K94: Mid-woofers | L94: Haut-parleurs de graves médians | M94: Midwoofer | N94: Midwoofer | O94: ミッドウーファー | P94: Woofers de rango medio | Q94: Midwoofers | R94: Mellom-woofere | S94: Altavoces de medios | T94: Mid-woofers | U94: Mid-woofers | V94: Mid-woofers | W94: Mid-woofers | X94: 中低音扬声器 | Y94: Středobasové měniče | Z94: Midwooferit | AA94: Głośniki średniotonowe | AB94: Mitteltöner | AC94: Mid-woofers | AD94: Woofers de rango medio
A95: fet-feature-high-efficiency-midwoofers | C95: High-efficiency midwoofers | D95: High-efficiency midwoofers | E95: High-efficiency midwoofers | F95: Højeffektive midwoofere | G95: Hocheffiziente Mitteltöner | H95: Hocheffiziente Mitteltöner | I95: Mid-woofers hautes performances | J95: Mid-woofers hautes performances | K95: Mid-woofers hautes performances | L95: Haut-parleurs de graves médians à haut rendement | M95: Mid-woofer ad alta efficienza | N95: Mid-woofer ad alta efficienza | O95: 高性能ミッドウーファー | P95: Woofers de rango medio de alta eficiencia | Q95: Extra efficiënte midwoofers | R95: Høyeffektive mellom-woofere | S95: Altavoces de medios de alta eficiencia | T95: Mid-woofers med hög effekt | U95: High-efficiency midwoofers | V95: High-efficiency midwoofers | W95: High-efficiency midwoofers | X95: 高性能中低音扬声器 | Y95: Vysoce účinné středobasové měniče | Z95: Tehokkaat midwoofer-kaiuttimet | AA95: Wysokowydajne głośniki średniotonowe | AB95: Hocheffiziente Mitteltöner | AC95: Mid-woofers hautes performances | AD95: Woofers de rango medio de alta eficiencia
A96: fet-feature-6-inch-woofers | C96: 6" woofers | D96: 6" woofers | E96: 6" woofers | F96: 6″-woofere | G96: 6" Tieftöner | H96: 6" Tieftöner | I96: woofers de 6 pouces | J96: woofers de 6 pouces | K96: woofers de 6 pouces | L96: Caissons de basses de 6 po | M96: Woofer da 6 pollici | N96: Woofer da 6 pollici | O96: 6インチウーファー | P96: Woofers de 6" | Q96: 6-inch woofers | R96: 6" woofere | S96: Woofers de 6" | T96: 6-tums woofers | U96: 6" woofers | V96: 6" woofers | W96: 6" woofers | X96: 6英寸低音扬声器 | Y96: 6palcové basové měniče | Z96: 6 tuuman bassokaiuttimet | AA96: Głośniki niskotonowe o średnicy 152 mm | AB96: 6" Tieftöner | AC96: woofers de 6 pouces | AD96: Woofers de 6"
A97: fet-feature-elliptical-midwoofer | C97: Elliptical midwoofer | D97: Elliptical midwoofer | E97: Elliptical mid-woofer | F97: Elliptisk midwoofer | G97: Elliptischer Mitteltöner | H97: Elliptischer Mitteltöner | I97: Mid-woofer elliptique | J97: Mid-woofer elliptique | K97: Mid-woofer elliptique | L97: Haut-parleur de graves médians elliptique | M97: Mid-woofer ellittico | N97: Mid-woofer ellittico | O97: 楕円形ミッドウーファー | P97: Woofer elíptico de rango medio | Q97: Elliptische midwoofer | R97: Elliptisk mellom-woofer | S97: Altavoz de medios elíptico | T97: Elliptisk mid-woofer | U97: Elliptical mid-woofer | V97: Elliptical mid-woofer | W97: Elliptical mid-woofer | X97: 椭圆形中低音扬声器 | Y97: Eliptický středobasový měnič | Z97: Elliptinen bassokaiutin | AA97: Eliptyczny głośnik średniotonowy | AB97: Elliptischer Mitteltöner | AC97: Mid-woofer elliptique | AD97: Woofer elíptico de rango medio
A98: fet-feature-elliptical-midwoofers | C98: Elliptical midwoofers | D98: Elliptical midwoofers | E98: Elliptical mid-woofers | F98: Elliptiske midwoofere | G98: Elliptische Mitteltöner | H98: Elliptische Mitteltöner | I98: Mid-woofers elliptiques | J98: Mid-woofers elliptiques | K98: Mid-woofers elliptiques | L98: Haut-parleurs de graves médians elliptiques | M98: Mid-woofer ellittici | N98: Mid-woofer ellittici | O98: 楕円形ミッドウーファー | P98: Woofers elípticos de rango medio | Q98: Elliptische midwoofers | R98: Elliptiske mellom-woofere | S98: Altavoces de medios elípticos | T98: Elliptiska mid-woofers | U98: Elliptical mid-woofers | V98: Elliptical mid-woofers | W98: Elliptical mid-woofers | X98: 椭圆形中低音扬声器 | Y98: Eliptické středobasové měniče | Z98: Elliptiset bassokaiuttimet | AA98: Eliptyczne głośniki średniotonowe | AB98: Elliptische Mitteltöner | AC98: Mid-woofers elliptiques | AD98: Woofers elípticos de rango medio
A99: fet-feature-custom-40mm-dynamice-drivers | C99: Custom-designed 40mm dynamic drivers | D99: Custom-designed 40 mm dynamic drivers | E99: Custom-designed 40 mm dynamic drivers | F99: Specialudviklede dynamiske drivere på 40 mm | G99: Spezielle dynamische 40-mm-Treiber | H99: Spezielle dynamische 40-mm-Treiber | I99: Haut-parleurs dynamiques de 40 mm conçus sur mesure | J99: Haut-parleurs dynamiques de 40 mm conçus sur mesure | K99: Haut-parleurs dynamiques de 40 mm conçus sur mesure | L99: Haut-parleurs dynamiques de 40 mm conçus sur mesure | M99: Driver dinamici da 40 mm progettati su misura | N99: Driver dinamici da 40 mm progettati su misura | O99: カスタム設計の40mmダイナミックドライバー | P99: Diafragmas dinámicos de diseño exclusivo de 40 mm | Q99: Speciaal ontworpen 40 mm dynamische drivers | R99: Spesialkonstruerte 40 mm dynamiske drivere | S99: Altavoces dinámicos de 40 mm diseñados a medida | T99: Specialdesignade, dynamiska högtalarelement på 40 mm | U99: Custom-designed 40 mm dynamic drivers | V99: Custom-designed 40 mm dynamic drivers | W99: Custom-designed 40 mm dynamic drivers | X99: 定制设计40毫米动态驱动器 | Y99: Na míru vytvořené 40mm dynamické ovladače | Z99: Kustomoidut 40 mm:n dynaamiset ohjaimet | AA99: Specjalnie zaprojektowane przetworniki dynamiczne o średnicy 40 mm | AB99: Spezielle dynamische 40-mm-Treiber | AC99: Haut-parleurs dynamiques de 40 mm conçus sur mesure | AD99: Diafragmas dinámicos de diseño exclusivo de 40 mm
A100: fet-feature-active-noise-cancellation-capitalized | C100: Active Noise Cancellation | D100: Active Noise Cancellation | E100: Active Noise Cancellation | F100: Aktiv støjreduktion | G100: Aktive Geräuschunterdrückung | H100: Aktive Geräuschunterdrückung | I100: Réduction active du bruit | J100: Réduction active du bruit | K100: Réduction active du bruit | L100: Élimination active des bruits | M100: Cancellazione attiva del rumore | N100: Cancellazione attiva del rumore | O100: ノイズキャンセリング機能 | P100: Cancelación activa de ruido | Q100: Actieve ruisonderdrukking | R100: Aktiv støykansellering | S100: Cancelación activa de ruido | T100: Aktiv brusreducering | U100: Active Noise Cancellation | V100: Active Noise Cancellation | W100: Active Noise Cancellation | X100: 主动消噪 | Y100: Aktivní potlačení hluku | Z100: Aktiivinen melunvaimennus | AA100: Aktywne tłumienie hałasu | AB100: Aktive Geräuschunterdrückung | AC100: Réduction active du bruit | AD100: Cancelación activa de ruido
A101: fet-feature-aware-mode | C101: Aware mode | D101: Aware mode | E101: Aware mode | F101: Aware mode | G101: Aware Modus | H101: Aware Modus | I101: Mode Aware | J101: Mode Aware | K101: Mode Aware | L101: Mode conscient | M101: Modalità Trasparenza | N101: Modalità Trasparenza | O101: アウェアモード | P101: Modo Ambiente | Q101: Aware-modus | R101: Bevisst modus | S101: Modo Aware | T101: Transparensläge | U101: Aware mode | V101: Aware mode | W101: Aware mode | X101: 感知模式 | Y101: Režim pozornosti | Z101: Valppaustila | AA101: Tryb kontaktu | AB101: Aware Modus | AC101: Mode Aware | AD101: Modo Ambiente
A102: fet-feature-microphones | B102: Microphones | C102: Microphones | D102: Microphones | E102: Microphones | F102: Mikrofoner | G102: Mikrofone | H102: Mikrofone | I102: Microphones | J102: Microphones | K102: Microphones | L102: Microphones | M102: Microfoni | N102: Microfoni | O102: マイク | P102: Micrófonos | Q102: Microfoons | R102: Mikrofoner | S102: Micrófonos | T102: Mikrofoner | U102: Microphones | V102: Microphones | W102: Microphones | X102: 麦克风 | Y102: Mikrofony | Z102: Mikrofonit | AA102: Mikrofony | AB102: Mikrofone | AC102: Microphones | AD102: Micrófonos
A103: fet-feature-microphones-arc-beam | B103: The far-field microphone array uses advanced beamforming and multi-channel echo cancellation for quick and accurate voice control. | C103: The far-field microphone array uses advanced beamforming and multi-channel echo cancellation for quick and accurate voice control. | D103: The far-field microphone array uses advanced beamforming and multi-channel echo cancellation for quick and accurate voice control. | E103: The far-field microphone array uses advanced beamforming and multi-channel echo cancellation for quick and accurate voice control. | F103: Fjernfeltsmikrofonen med avanceret stråleformning og multikanals ekkodæmpning giver hurtig og præcis aktivering af stemmeassistent. | G103: Fernfeldmikrofone ermöglichen eine präzise Positionsbestimmung von Audioquellen und hervorragende Mehrkanal-Echounterdrückung für eine schnelle und präzise Sprachsteuerung. | H103: Fernfeldmikrofone ermöglichen eine präzise Positionsbestimmung von Audioquellen und hervorragende Mehrkanal-Echounterdrückung für eine schnelle und präzise Sprachsteuerung. | I103: Le réseau de micros longue portée utilise des technologies avancées de formation de faisceaux et d’annulation de l’écho sur tous les canaux, pour un contrôle vocal rapide et précis. | J103: Le réseau de micros longue portée utilise des technologies avancées de formation de faisceaux et d’annulation de l’écho sur tous les canaux, pour un contrôle vocal rapide et précis. | K103: Le réseau de micros longue portée utilise des technologies avancées de formation de faisceaux et d’annulation de l’écho sur tous les canaux, pour un contrôle vocal rapide et précis. | L103: L’ensemble de microphones à grande portée assure la formation avancée de faisceaux et la suppression active de l’écho sur plusieurs canaux pour utiliser le contrôle vocal avec rapidité et précision. | M103: L’assetto far-field dei microfoni con beamforming avanzato e cancellazione dell’eco multicanale consente un controllo vocale rapido e preciso. | N103: L’assetto far-field dei microfoni con beamforming avanzato e cancellazione dell’eco multicanale consente un controllo vocale rapido e preciso. | O103: 遠距離対応マイクロホンアレイが高度なビームフォーミングとマルチチャンネルのエコー除去機能を利用して、音声操作をすばやく正確に起動。 | P103: La matriz de micrófonos de largo alcance utiliza detección avanzada de fuentes de sonido y cancelación multicanal de ecos para un control por voz rápido y preciso. | Q103: De far field-microfoons maken gebruik van geavanceerde beamforming en meerkanaals echo-onderdrukking voor snelle en nauwkeurige stembediening. | R103: Mikrofonsettet bruker avansert stråleforming og flerkanals ekkokansellering for rask og nøyaktig stemmestyring. | S103: Una matriz de micrófonos de largo alcance se encarga de formar haces avanzados y evitar el eco multicanal para que el control por voz se active de forma rápida y precisa. | T103: Fjärrfältsmikrofonerna använder avancerad strålformning och flerkanalig ekoreducering för att ge snabb och korrekt röststyrning. | U103: The far-field microphone array uses advanced beamforming and multi-channel echo cancellation for quick and accurate voice control. | V103: The far-field microphone array uses advanced beamforming and multi-channel echo cancellation for quick and accurate voice control. | W103: The far-field microphone array uses advanced beamforming and multi-channel echo cancellation for quick and accurate voice control. | X103: 远场麦克风阵列使用高级波束赋形技术和多通道回波消除技术，可实现快速精确的语音控制。 | Y103: Sada mikrofonů s dalekým dosahem využívá pokročilou technologii Beamforming a vícekanálové rušení ozvěny pro rychlé a přesné ovládání hlasu. | Z103: Kaukokenttämikrofoniryhmä käyttää edistynyttä äänikeilaa ja monikanavaista kaiunpoistoa, mikä mahdollistaa nopean puheohjauksen*. *Puheohjaus ei saatavilla Suomessa. | AA103: Układ dalekosiężnych mikrofonów wykorzystuje zaawansowane kształtowanie wiązki i wielokanałową eliminację pogłosu, co umożliwia szybką i precyzyjną aktywację sterowania głosowego. | AB103: Fernfeldmikrofone ermöglichen eine präzise Positionsbestimmung von Audioquellen und hervorragende Mehrkanal-Echounterdrückung für eine schnelle und präzise Sprachsteuerung. | AC103: Le réseau de micros longue portée utilise des technologies avancées de formation de faisceaux et d’annulation de l’écho sur tous les canaux, pour un contrôle vocal rapide et précis. | AD103: La matriz de micrófonos de largo alcance utiliza detección avanzada de fuentes de sonido y cancelación multicanal de ecos para un control por voz rápido y preciso.
A104: fet-feature-microphones-era100-move2 | B104: The far-field microphone array uses advanced beamforming and multichannel echo cancellation for quick and accurate voice control and Trueplay tuning. Disconnect by toggling off the mic switch. | C104: The far-field microphone array uses advanced beamforming and multi-channel echo cancellation for quick and accurate voice control and automatic Trueplay tuning. | D104: The far-field microphone array uses advanced beamforming and multi-channel echo cancellation for quick and accurate voice control and automatic Trueplay tuning. | E104: The far-field microphone array uses advanced beamforming and multi-channel echo cancellation for quick and accurate voice control and automatic Trueplay tuning. | F104: Fjernfeltsmikrofonen med avanceret stråleformning og multikanals ekkodæmpning giver hurtig og præcis aktivering af stemmeassistent og automatisk Trueplay-tuning. | G104: Fernfeldmikrofone ermöglichen eine präzise Positionsbestimmung von Audioquellen und eine hervorragende Mehrkanal-Echounterdrückung für eine schnelle und präzise Sprachsteuerung und automatisches Trueplay Tuning. | H104: Fernfeldmikrofone ermöglichen eine präzise Positionsbestimmung von Audioquellen und eine hervorragende Mehrkanal-Echounterdrückung für eine schnelle und präzise Sprachsteuerung und automatisches Trueplay Tuning. | I104: Le réseau de micros à longue portée utilise les technologies avancées de formation de faisceaux et d’annulation de l’écho sur tous les canaux, pour un contrôle vocal rapide et précis. Il permet de profiter du calibrage Trueplay automatique. | J104: Le réseau de micros à longue portée utilise les technologies avancées de formation de faisceaux et d’annulation de l’écho sur tous les canaux, pour un contrôle vocal rapide et précis. Il permet de profiter du calibrage Trueplay automatique. | K104: Le réseau de micros à longue portée utilise les technologies avancées de formation de faisceaux et d’annulation de l’écho sur tous les canaux, pour un contrôle vocal rapide et précis. Il permet de profiter du calibrage Trueplay automatique. | L104: L’ensemble de microphones à grande portée assure la formation avancée de faisceaux et la suppression active de l’écho sur plusieurs canaux pour utiliser le contrôle vocal et le réglage automatique Trueplay avec rapidité et précision. | M104: L’assetto far-field dei microfoni con beamforming avanzato e cancellazione dell’eco multicanale consente di attivare rapidamente l’assistente vocale e di ottimizzare l’audio automaticamente con Trueplay. | N104: L’assetto far-field dei microfoni con beamforming avanzato e cancellazione dell’eco multicanale consente di attivare rapidamente l’assistente vocale e di ottimizzare l’audio automaticamente con Trueplay. | O104: 遠距離対応マイクロホンアレイが高度なビームフォーミングとマルチチャンネルのエコー除去機能を利用して、音声操作とオートマティックTrueplayチューニングをすばやく正確に起動。 | P104: La matriz de micrófonos de largo alcance utiliza detección avanzada de fuentes de sonido y cancelación multicanal de ecos para ofrecer control por voz rápido y preciso, y ajuste Trueplay automático. | Q104: De far field-microfoons maken gebruik van geavanceerde beamforming en meerkanaals echo-onderdrukking voor snelle en nauwkeurige stembediening en automatische Trueplay™-tuning. | R104: Mikrofonsettet bruker avansert stråleforming og flerkanals ekkokansellering for rask og nøyaktig stemmestyring og automatisk Trueplay-justering. | S104: Una matriz de micrófonos de largo alcance se encarga de formar haces avanzados y evitar el eco multicanal para que el control por voz y el ajuste Trueplay automático se activen de forma rápida y precisa. | T104: Fjärrfältsmikrofonen använder avancerad strålformning och flerkanalig ekoreducering för att ge snabb och korrekt röststyrning och automatisk Trueplay™-justering. | U104: The far-field microphone array uses advanced beamforming and multi-channel echo cancellation for quick and accurate voice control and automatic Trueplay tuning. | V104: The far-field microphone array uses advanced beamforming and multi-channel echo cancellation for quick and accurate voice control and automatic Trueplay tuning. | W104: The far-field microphone array uses advanced beamforming and multi-channel echo cancellation for quick and accurate voice control and automatic Trueplay tuning. | X104: 远场麦克风阵列使用高级波束赋形技术和多通道回波消除技术，可实现快速精确的语音控制和自适应Trueplay调音功能。 | Y104: Sada mikrofonů s dalekým dosahem využívá pokročilou technologii Beamforming a vícekanálové rušení ozvěny pro rychlé a přesné ovládání hlasu a automatické ladění Trueplay. | Z104: Kaukokenttämikrofoniryhmä käyttää edistynyttä äänikeilaa ja monikanavaista kaiunpoistoa, mikä mahdollistaa nopean ääniavustajan* aktivoinnin ja automaattisen Trueplay™-virityksen. *Puheohjaus ei saatavilla Suomessa. | AA104: Układ dalekosiężnych mikrofonów wykorzystuje zaawansowane kształtowanie wiązki i wielokanałową eliminację pogłosu, co umożliwia szybką i precyzyjną aktywację sterowania głosowego oraz automatyczną regulację Trueplay. | AB104: Fernfeldmikrofone ermöglichen eine präzise Positionsbestimmung von Audioquellen und eine hervorragende Mehrkanal-Echounterdrückung für eine schnelle und präzise Sprachsteuerung und automatisches Trueplay Tuning. | AC104: Le réseau de micros à longue portée utilise les technologies avancées de formation de faisceaux et d’annulation de l’écho sur tous les canaux, pour un contrôle vocal rapide et précis. Il permet de profiter du calibrage Trueplay automatique. | AD104: La matriz de micrófonos de largo alcance utiliza detección avanzada de fuentes de sonido y cancelación multicanal de ecos para ofrecer control por voz rápido y preciso, y ajuste Trueplay automático.
A105: fet-feature-microphones-roam2 | B105: The beamforming microphone system uses multichannel echo cancellation for quick and accurate voice control plus automatic Trueplay tuning. | C105: The beamforming microphone system uses multichannel echo cancellation for quick and accurate voice control plus automatic Trueplay tuning. | D105: The beamforming microphone system uses multichannel echo cancellation for quick and accurate voice control plus automatic Trueplay tuning. | E105: The beamforming microphone system uses multichannel echo cancellation for quick and accurate voice control plus automatic Trueplay tuning. | F105: Det stråleformende mikrofonsystem bruger multikanals ekkodæmpning til hurtig og præcis stemmestyring og automatisk Trueplay-tuning. | G105: Das Mikrofonsystem mit präziser Positionsbestimmung nutzt eine hervorragende Mehrkanal-Echounterdrückung für eine schnelle und präzise Sprachsteuerung und automatisches Trueplay Tuning. | H105: Das Mikrofonsystem mit präziser Positionsbestimmung nutzt eine hervorragende Mehrkanal-Echounterdrückung für eine schnelle und präzise Sprachsteuerung und automatisches Trueplay Tuning. | I105: Le système de micros à formation de faisceau utilise des technologies d’annulation de l’écho sur tous les canaux pour un contrôle vocal rapide et précis, et permet de profiter du calibrage Trueplay automatique. | J105: Le système de micros à formation de faisceau utilise des technologies d’annulation de l’écho sur tous les canaux pour un contrôle vocal rapide et précis, et permet de profiter du calibrage Trueplay automatique. | K105: Le système de micros à formation de faisceau utilise des technologies d’annulation de l’écho sur tous les canaux pour un contrôle vocal rapide et précis, et permet de profiter du calibrage Trueplay automatique. | L105: L’ensemble de microphones à grande portée assure la suppression active de l’écho sur plusieurs canaux pour l’utilisation du contrôle vocal et le réglage automatique Trueplay avec rapidité et précision. | M105: L’assetto dei microfoni con beamforming avanzato e cancellazione dell’eco multicanale consente un controllo vocale rapido e preciso e l’ottimizzazione automatica Trueplay. | N105: L’assetto dei microfoni con beamforming avanzato e cancellazione dell’eco multicanale consente un controllo vocale rapido e preciso e l’ottimizzazione automatica Trueplay. | O105: ビームフォーミングマイクシステムが、マルチチャンネルのエコー除去を使用して、迅速かつ正確な音声操作とオートマティックTrueplayチューニングを実現。 | P105: El sistema de micrófonos con detección de fuentes de sonido utiliza cancelación multicanal de ecos para ofrecer control por voz rápido y preciso, y ajuste Trueplay automático. | Q105: Het microfoonsysteem met beamforming-technologie maakt gebruik van multichannel echo-onderdrukking. Dat zorgt voor snelle en nauwkeurige stembediening en automatische Trueplay-tuning. | R105: Det stråleformede mikrofonsystemet bruker flerkanals ekkokansellering for rask og nøyaktig stemmestyring og automatisk Trueplay-justering. | S105: Una matriz de micrófonos se encarga de formar haces avanzados y evitar el eco multicanal para que el control por voz y el ajuste Trueplay automático se activen de forma rápida y precisa. | T105: Mikrofonsystemet med strålformning använder flerkanalig ekoreducering för att ge snabb och korrekt röststyrning och automatisk Trueplayjustering. | U105: The beamforming microphone system uses multichannel echo cancellation for quick and accurate voice control plus automatic Trueplay tuning. | V105: The beamforming microphone system uses multichannel echo cancellation for quick and accurate voice control plus automatic Trueplay tuning. | W105: The beamforming microphone system uses multichannel echo cancellation for quick and accurate voice control plus automatic Trueplay tuning. | X105: 波束赋形麦克风系统使用多通道回波消除技术，可实现快速精确的语音控制和自适应Trueplay调音功能。 | Y105: Systém mikrofonu s technologií Beamforming používá vícekanálové rušení ozvěny pro rychlé a přesné hlasové ovládání a automatické ladění Trueplay. | Z105: Säteenmuodostusmikrofonijärjestelmä käyttää monikanavaista kaiunpoistoa, mikä mahdollistaa nopean puheavustajan hallinnan ja automaattisen Trueplay-virityksen. | AA105: Układ mikrofonów kształtujących wiązkę dźwięku wykorzystuje wielokanałową eliminację pogłosu, co umożliwia szybką precyzyjną aktywację sterowania głosowego oraz automatyczną regulację Trueplay. | AB105: Das Mikrofonsystem mit präziser Positionsbestimmung nutzt eine hervorragende Mehrkanal-Echounterdrückung für eine schnelle und präzise Sprachsteuerung und automatisches Trueplay Tuning. | AC105: Le système de micros à formation de faisceau utilise des technologies d’annulation de l’écho sur tous les canaux pour un contrôle vocal rapide et précis, et permet de profiter du calibrage Trueplay automatique. | AD105: El sistema de micrófonos con detección de fuentes de sonido utiliza cancelación multicanal de ecos para ofrecer control por voz rápido y preciso, y ajuste Trueplay automático.
A106: fet-feature-microphones-ace | C106: Eight microphones for Active Noise Cancellation, voice targeting, and background noise suppression. | D106: Eight microphones for Active Noise Cancellation, voice targeting, and background noise suppression. | E106: Eight microphones for Active Noise Cancellation, voice targeting and background noise suppression. | F106: Otte mikrofoner giver aktiv støjreduktion, stemmefokus og dæmpning af baggrundsstøj. | G106: Acht Mikrofone sorgen für aktive Geräuschunterdrückung, die deine Stimme hervorheben und Hintergrundgeräusche ausblenden. | H106: Acht Mikrofone sorgen für aktive Geräuschunterdrückung, die deine Stimme hervorheben und Hintergrundgeräusche ausblenden. | I106: Huit micros dédiés à la réduction active du bruit, au ciblage vocal et la suppression des bruits parasites. | J106: Huit micros dédiés à la réduction active du bruit, au ciblage vocal et la suppression des bruits parasites. | K106: Huit micros dédiés à la réduction active du bruit, au ciblage vocal et la suppression des bruits parasites. | L106: Huit microphones pour l’annulation active du bruit, le ciblage vocal et la suppression des bruits de fond. | M106: Otto microfoni consentono la cancellazione attiva del rumore, l’amplificazione della voce e l’eliminazione del rumore di sottofondo. | N106: Otto microfoni consentono la cancellazione attiva del rumore, l’amplificazione della voce e l’eliminazione del rumore di sottofondo. | O106: 8つのマイクでノイズキャンセリング機能、ボイスターゲティング、バックグラウンドノイズ除去を実現。 | P106: Ocho micrófonos para cancelación activa de ruido, focalización de la voz y supresión de ruido de fondo. | Q106: Acht microfoons voor actieve ruisonderdrukking, Voice Targeting en onderdrukking van achtergrondgeluiden. | R106: Åtte mikrofoner for aktiv støykansellering, stemmemålretting og demping av bakgrunnsstøy. | S106: Los ocho micrófonos permiten la cancelación activa del ruido, la optimización de la voz y la eliminación del ruido de fondo. | T106: Åtta mikrofoner ger aktiv brusreducering, talfokusering och dämpning av bakgrundsljud. | U106: Eight microphones for Active Noise Cancellation, voice targeting and background noise suppression. | V106: Eight microphones for Active Noise Cancellation, voice targeting and background noise suppression. | W106: Eight microphones for Active Noise Cancellation, voice targeting and background noise suppression. | X106: 八个麦克风，用于主动消噪、语音定位和背景噪声抑制。 | Y106: Osm mikrofonů pro aktivní potlačení hluku, cílení hlasu a potlačení hluku v pozadí. | Z106: Kahdeksan mikrofonia aktiivista melunvaimennusta, äänen kohdennusta ja taustamelun vaimennusta varten. | AA106: Osiem mikrofonów wykorzystywanych do aktywnego tłumienia hałasu, wykrywania głosu i wygłuszania szumów w tle. | AB106: Acht Mikrofone sorgen für aktive Geräuschunterdrückung, die deine Stimme hervorheben und Hintergrundgeräusche ausblenden. | AC106: Huit micros dédiés à la réduction active du bruit, au ciblage vocal et la suppression des bruits parasites. | AD106: Ocho micrófonos para cancelación activa de ruido, focalización de la voz y supresión de ruido de fondo.
A107: fet-feature-full-on-immersion | B107: Immersion like you've never felt | C107: Immersion like you've never felt | D107: Immersion like you've never felt | E107: Immersion like you've never felt | F107: Omsluttende lyd, som du aldrig har oplevet det før | G107: Eine unvergleichliche Sound Experience | H107: Eine unvergleichliche Sound Experience | I107: Une immersion sonore incomparable | J107: Une immersion sonore incomparable | K107: Une immersion sonore incomparable | L107: Une immersion comme vous n’en avez jamais entendue | M107: Un’esperienza coinvolgente unica nel suo genere | N107: Un’esperienza coinvolgente unica nel suo genere | O107: かつてない臨場感を体験 | P107: Inmersión como nunca has sentido | Q107: Meeslepender dan je ooit hebt meegemaakt | R107: Innlevelse slik du aldri har følt det før | S107: Sumérgete en el sonido como nunca | T107: Omslutande på en helt ny nivå | U107: Immersion like you've never felt | V107: Immersion like you've never felt | W107: Immersion like you've never felt | X107: 从未有过的沉浸体验 | Y107: Pohlcující poslech, jaký jste dosud nezažili | Z107: Ennenkokematonta mukaansatempaavuutta | AA107: Głębia dźwięku, jak nigdy dotąd | AB107: Eine unvergleichliche Sound Experience | AC107: Une immersion sonore incomparable | AD107: Inmersión como nunca has sentido
A108: fet-feature-full-on-immersion-ace | B108: Meticulously engineered and tuned by the most discerning ears in the industry, Sonos Ace creates the deepest connection to sound. Each custom-designed component combines with our advanced software to surround you in the highest-fidelity audio. From crystal clear highs to powerful lows, every note feels more profound. | C108: Meticulously engineered and tuned by the most discerning ears in the industry, Sonos Ace creates the deepest connection to sound. Each custom-designed component combines with our advanced software to surround you in the highest-fidelity audio. From crystal clear highs to powerful lows, every note feels more profound. | D108: Meticulously engineered and tuned by the most discerning ears in the industry, Sonos Ace creates the deepest connection to sound. Each custom-designed component combines with our advanced software to surround you in the highest-fidelity audio. From crystal-clear highs to powerful lows, every note feels more profound. | E108: Meticulously engineered and tuned by the most discerning ears in the industry, Sonos Ace creates the deepest connection to sound. Each custom-designed component combines with our advanced software to surround you with the highest-fidelity audio. From crystal-clear highs to powerful lows, every note feels more profound. | F108: Sonos Ace er omhyggeligt designet og tunet af branchens mest kræsne ører, så du kan føle dig dybt forbundet med din musik. Hver specialdesignet komponent arbejder sammen med vores avancerede software for at omslutte dig med lyd af allerhøjeste kvalitet. Fra krystalklare højder til kraftfuld bas – hver tone føles rig og autentisk. | G108: Der präzise entwickelte und von Branchenexpert:innen abgestimmte Sonos Ace verbindet dich noch intensiver mit Sound. Maßgefertigte Komponenten sorgen gemeinsam mit unserer fortschrittlichen Software für einzigartiges HiFi Audio. Von kristallklaren Höhen bis hin zu kraftvollen Tiefen klingt jeder einzelne Ton noch mitreißender. | H108: Der präzise entwickelte und von Branchenexpert:innen abgestimmte Sonos Ace verbindet dich noch intensiver mit Sound. Massgefertigte Komponenten sorgen gemeinsam mit unserer fortschrittlichen Software für einzigartiges HiFi Audio. Von kristallklaren Höhen bis hin zu kraftvollen Tiefen klingt jeder einzelne Ton noch mitreissender. | I108: Conçu avec un soin infini par les meilleurs ingénieurs du son, le Sonos Ace crée une immersion sonore totale. Chaque composant conçu sur mesure s'associe à notre logiciel avancé pour vous immerger dans un son ultra haute fidélité. Aigus cristallins, basses puissantes: chaque note gagne en profondeur. | J108: Conçu avec un soin infini par les meilleurs ingénieurs du son, le Sonos Ace crée une immersion sonore totale. Chaque composant conçu sur mesure s'associe à notre logiciel avancé pour vous immerger dans un son ultra haute fidélité. Aigus cristallins, basses puissantes: chaque note gagne en profondeur. | K108: Conçu avec un soin infini par les meilleurs ingénieurs du son, le Sonos Ace crée une immersion sonore totale. Chaque composant conçu sur mesure s'associe à notre logiciel avancé pour vous immerger dans un son ultra haute fidélité. Aigus cristallins, basses puissantes: chaque note gagne en profondeur. | L108: Méticuleusement conçu et ajusté par les oreilles les plus exigeantes de l’industrie musicale, Sonos Ace permet de vivre une expérience sonore des plus profondes. Chaque composant conçu sur mesure s’associe à nos logiciels évolués pour vous entourer d’un son de la plus haute fidélité. Des aigus cristallins aux graves puissants, chaque note semble plus profonde. | M108: Progettato meticolosamente e ottimizzato dai migliori esperti del settore, Sonos Ace stabilisce la connessione più profonda in assoluto tra te e il suono. Ogni componente è stato progettato su misura per integrarsi con il nostro software avanzato e offrirti un audio ad alta fedeltà estremamente definito. Grazie ad alti cristallini e a bassi potenti, sentirai l’intensità di ogni nota. | N108: Progettato meticolosamente e ottimizzato dai migliori esperti del settore, Sonos Ace stabilisce la connessione più profonda in assoluto tra te e il suono. Ogni componente è stato progettato su misura per integrarsi con il nostro software avanzato e offrirti un audio ad alta fedeltà estremamente definito. Grazie ad alti cristallini e a bassi potenti, sentirai l’intensità di ogni nota. | O108: 音楽業界のプロによって精緻に設計・チューニングされたSonos Aceは、サウンドとリスナーの間に深いつながりを生み出します。カスタム設計された各コンポーネントとSonosの高度なソフトウェアの組み合わせにより、最高のHi-Fiサウンドで聴く人を包み込みます。驚くほどクリアな高音からパワフルな低音まで、すべての音に深みを感じられます。 | P108: Meticulosamente diseñado y calibrado por los oídos más exigentes de la industria, Sonos Ace crea la más profunda conexión con el sonido. Cada componente de diseño exclusivo se combina con nuestro software avanzado para envolverte en audio de la más alta fidelidad. Desde agudos increíblemente nítidos hasta graves potentes, cada nota se siente más profunda. | Q108: Zorgvuldig ontworpen en getuned met behulp van de meest kundige oren uit de muziekindustrie. Sonos Ace zorgt voor een nog diepere verbinding met geluid. Elk speciaal ontworpen onderdeel wordt gecombineerd met onze geavanceerde software zodat je wordt omringd door audio van de hoogste kwaliteit. Van kristalheldere hoge tonen tot krachtig laag: elke noot komt binnen. | R108: Sonos Ace er omhyggelig konstruert og justert av de mest finstilte ørene i bransjen, og skaper den dypeste forbindelsen til lyd. Hver spesialkonstruerte komponent kombineres med den avanserte programvaren vår for å omslutte deg med lyd av høyeste kvalitet. Hver tone, fra krystallklare diskanttoner til kraftig bass, føles dypere. | S108: Sonos Ace ha sido diseñado y ajustado meticulosamente por los expertos con el oído más fino de la industria para que disfrutes y conectes con tu contenido favorito como nunca. Todos los componentes diseñados a medida funcionan con nuestro software avanzado para que puedas sumergirte en el mejor sonido posible. Siente cada nota con una profundidad sin igual, ya sean agudos nítidos o graves potentes. | T108: Sonos Ace är minutiöst konstruerad och finjusterad av branschens bästa ljudtekniker för att ge en riktigt omslutande ljudupplevelse. När de specialdesignade komponenterna kombineras med vår avancerade programvara skapas hifi-ljud i världsklass. Varje ton känns mer framträdande, från kristallklara höga till kraftfulla låga frekvenser. | U108: Meticulously engineered and tuned by the most discerning ears in the industry, Sonos Ace creates the deepest connection to sound. Each custom-designed component combines with our advanced software to surround you with the highest-fidelity audio. From crystal-clear highs to powerful lows, every note feels more profound. | V108: Meticulously engineered and tuned by the most discerning ears in the industry, Sonos Ace creates the deepest connection to sound. Each custom-designed component combines with our advanced software to surround you with the highest-fidelity audio. From crystal-clear highs to powerful lows, every note feels more profound. | W108: Meticulously engineered and tuned by the most discerning ears in the industry, Sonos Ace creates the deepest connection to sound. Each custom-designed component combines with our advanced software to surround you with the highest-fidelity audio. From crystal-clear highs to powerful lows, every note feels more profound. | X108: Sonos Ace由业内耳朵最挑剔的工程师精心设计和调校，可为听众创造沉浸感十足的音效体验。每个定制设计的组件都与我们先进的软件相结合，为您呈现最高保真度的音频。从水晶般清晰的高音到强劲澎湃的低音，每个音符都更加扣人心弦。 | Y108: Sonos Ace pečlivě navrhli a vyladili mistři zvuku pro co nejhlubší zvukový zážitek. Každá na míru navržená komponenta v kombinaci s naším pokročilým softwarem vás obklopí zvukem s nejvyšší věrností. Každý tón, od křišťálově čistých výšek až po silné hloubky, je pronikavější. | Z108: Sonos Ace on alan tarkimpien korvien suunnittelema ja virittämä, ja se luo syvääkin syvemmän yhteyden ääneen. Jokainen kustomoitu komponentti ja edistynyt ohjelmisto luovat korkean toistotarkkuuden äänen, joka ympäröi kuuntelijan. Jokainen sävel kuuluu tarkasti aina kristallinkirkkaista ylä-äänistä voimakkaisiin alaääniin. | AA108: Skrupulatnie opracowane i dostrojone przez najbardziej wymagających specjalistów w branży, Sonos Ace tworzą głęboką więź z muzyką. Wszystkie specjalnie zaprojektowany komponenty współpracują z naszym zaawansowanym oprogramowaniem, by otoczyć słuchacza dźwiękiem o najwyższej wierności. Od krystalicznie czystych tonów wysokich po potężne tony niskie — każdy dźwięk jest bardziej intensywny. | AB108: Der präzise entwickelte und von Branchenexpert:innen abgestimmte Sonos Ace verbindet dich noch intensiver mit Sound. Maßgefertigte Komponenten sorgen gemeinsam mit unserer fortschrittlichen Software für einzigartiges HiFi Audio. Von kristallklaren Höhen bis hin zu kraftvollen Tiefen klingt jeder einzelne Ton noch mitreißender. | AC108: Conçu avec un soin infini par les meilleurs ingénieurs du son, le Sonos Ace crée une immersion sonore totale. Chaque composant conçu sur mesure s'associe à notre logiciel avancé pour vous immerger dans un son ultra haute fidélité. Aigus cristallins, basses puissantes: chaque note gagne en profondeur. | AD108: Meticulosamente diseñado y calibrado por los oídos más exigentes de la industria, Sonos Ace crea la más profunda conexión con el sonido. Cada componente de diseño exclusivo se combina con nuestro software avanzado para envolverte en audio de la más alta fidelidad. Desde agudos increíblemente nítidos hasta graves potentes, cada nota se siente más profunda.
A109: fet-feature-extreme-clarity | B109: Extreme clarity | C109: Extreme clarity | D109: Extreme clarity | E109: Extreme clarity | F109: Ekstrem klarhed | G109: Unglaublich klar | H109: Unglaublich klar | I109: Une clarté extraordinaire | J109: Une clarté extraordinaire | K109: Une clarté extraordinaire | L109: Extrême clarté | M109: Nitidezza straordinaria | N109: Nitidezza straordinaria | O109: 究極にクリアなサウンド | P109: Nitidez extrema | Q109: Extreem zuiver | R109: Ekstrem klarhet | S109: Percibe cada matiz | T109: Exceptionell klarhet | U109: Extreme clarity | V109: Extreme clarity | W109: Extreme clarity | X109: 极致清晰度 | Y109: Extrémní jasnost | Z109: Äärimmäistä selkeyttä | AA109: Nadzwyczajnie wyraźny dźwięk | AB109: Unglaublich klar | AC109: Une clarté extraordinaire | AD109: Nitidez extrema
A110: fet-feature-extreme-clarity-ace | B110: Positioned to deliver the most balanced sound profile and distortionless playback, the dynamic driver produces each frequency with impeccable precision and accuracy. | C110: Positioned to deliver the most balanced sound profile and distortionless playback, the dynamic driver produces each frequency with impeccable precision and accuracy. | D110: Positioned to deliver the most balanced sound profile and distortionless playback, the dynamic driver produces each frequency with impeccable precision and accuracy. | E110: Positioned to deliver the most balanced sound profile and distortionless playback, the dynamic driver produces each frequency with impeccable precision and accuracy. | F110: Den dynamiske driver sidder sådan, at den gengiver den mest afbalancerede lydprofil uden forvrængning og frembringer hver frekvens med uovertruffen præcision. | G110: Der dynamische Treiber ist so positioniert, dass er ein vollständig ausgewogenes Soundprofil und eine verzerrungsfreie Wiedergabe liefert, und jede Frequenz mit unglaublicher Präzision und Genauigkeit wiedergibt. | H110: Der dynamische Treiber ist so positioniert, dass er ein vollständig ausgewogenes Soundprofil und eine verzerrungsfreie Wiedergabe liefert, und jede Frequenz mit unglaublicher Präzision und Genauigkeit wiedergibt. | I110: Orienté pour offrir le profil sonore le plus équilibré possible et une lecture du son sans distorsion, le haut-parleur dynamique reproduit chaque fréquence avec une netteté et une précision impeccables. | J110: Orienté pour offrir le profil sonore le plus équilibré possible et une lecture du son sans distorsion, le haut-parleur dynamique reproduit chaque fréquence avec une netteté et une précision impeccables. | K110: Orienté pour offrir le profil sonore le plus équilibré possible et une lecture du son sans distorsion, le haut-parleur dynamique reproduit chaque fréquence avec une netteté et une précision impeccables. | L110: Positionné pour offrir le profil sonore le plus équilibré et une lecture sans distorsion, le haut-parleur dynamique reproduit chaque fréquence avec une précision et une exactitude irréprochables. | M110: Posizionato per garantire un profilo sonoro estremamente bilanciato e una riproduzione senza distorsioni, il driver dinamico rende ogni frequenza con una precisione impeccabile. | N110: Posizionato per garantire un profilo sonoro estremamente bilanciato e una riproduzione senza distorsioni, il driver dinamico rende ogni frequenza con una precisione impeccabile. | O110: 最もバランスの取れたサウンドプロファイルで歪みのないサウンドを再生するように設置されたダイナミックドライバーが、各周波数を完璧かつ正確に再生します。 | P110: Ubicado para ofrecer el perfil sonoro más equilibrado y reproducción sin distorsiones, el diafragma dinámico genera cada frecuencia con un nivel impecable de precisión y exactitud. | Q110: De dynamische driver zorgt voor het meest uitgebalanceerde geluidsprofiel en is optimaal gepositioneerd voor een geluidsweergave zonder vervorming. Zo hoor je elke frequentie accuraat en met precisie. | R110: Den dynamiske driveren er plassert for å gi den mest balanserte lydprofilen og avspilling uten forvrenging. Den produserer hver frekvens med plettfri presisjon og nøyaktighet. | S110: El altavoz dinámico está estratégicamente colocado para ofrecer el sonido más equilibrado, eliminar las distorsiones y reproducir cada frecuencia con una precisión y una exactitud impecables. | T110: Det dynamiska högtalarelementet återger alla frekvenser med oslagbar precision och har positionerats för att ge en perfekt balanserad ljudprofil och uppspelning utan förvrängningar. | U110: Positioned to deliver the most balanced sound profile and distortionless playback, the dynamic driver produces each frequency with impeccable precision and accuracy. | V110: Positioned to deliver the most balanced sound profile and distortionless playback, the dynamic driver produces each frequency with impeccable precision and accuracy. | W110: Positioned to deliver the most balanced sound profile and distortionless playback, the dynamic driver produces each frequency with impeccable precision and accuracy. | X110: 动态驱动器经精准定位，旨在呈现最平衡的声音特征和无失真播放，能够以无可挑剔的精度和准度呈现每个频段。 | Y110: Dynamický ovladač, který je umístěn tak, aby poskytoval co nejvyváženější zvukový profil a přehrávání bez zkreslení, produkuje každou frekvenci s dokonalou přesností a precizností. | Z110: Dynaaminen ohjain on sijoitettu tuottamaan erittäin tasapainoisen ääniprofiilin ja häiriöttömän toiston. Lisäksi se tuottaa joka taajuuden pettämättömällä tarkkuudella. | AA110: Każdy dźwięk bez względu na częstotliwość jest emitowany z niezrównaną precyzją i dokładnością dzięki dynamicznemu sterownikowi ustawionemu pod kątem, który zapewnia najbardziej zrównoważony profil dźwięku i odtwarzanie bez zniekształceń. | AB110: Der dynamische Treiber ist so positioniert, dass er ein vollständig ausgewogenes Soundprofil und eine verzerrungsfreie Wiedergabe liefert, und jede Frequenz mit unglaublicher Präzision und Genauigkeit wiedergibt. | AC110: Orienté pour offrir le profil sonore le plus équilibré possible et une lecture du son sans distorsion, le haut-parleur dynamique reproduit chaque fréquence avec une netteté et une précision impeccables. | AD110: Ubicado para ofrecer el perfil sonoro más equilibrado y reproducción sin distorsiones, el diafragma dinámico genera cada frecuencia con un nivel impecable de precisión y exactitud.
A111: fet-feature-superior-bass | B111: Superior bass | C111: Superior bass | D111: Superior bass | E111: Superior bass | F111: Suveræn bas | G111: Überragender Bass | H111: Überragender Bass | I111: Des basses puissantes | J111: Des basses puissantes | K111: Des basses puissantes | L111: Basses supérieures | M111: Bassi di altissima qualità | N111: Bassi di altissima qualità | O111: 優れた低音 | P111: Graves superiores | Q111: Superieure bass | R111: Overlegen bass | S111: Déjate asombrar por los graves | T111: Överlägsen bas | U111: Superior bass | V111: Superior bass | W111: Superior bass | X111: 超凡低音 | Y111: Špičkové basy | Z111: Erinomainen basso | AA111: Niezrównany bas | AB111: Überragender Bass | AC111: Des basses puissantes | AD111: Graves superiores
...

Sheet Translation_Lasso_Release
A1: Key | B1: Description | C1: en-US | D1: en-CA | E1: en-GB | F1: da-DK | G1: de-DE | H1: de-CH | I1: fr-FR | J1: fr-CH | K1: fr-BE | L1: fr-CA | M1: it-IT | N1: it-CH | O1: ja-JP | P1: es-MX | Q1: nl-NL | R1: nb-NO | S1: es-ES | T1: sv-SE | U1: en-AU | V1: en-NZ | W1: en-RW | X1: zh-CN | Y1: cs-CZ | Z1: fi-FI | AA1: pl-PL | AB1: de-LU | AC1: fr-LU | AD1: es-CO
A2: LASSO
A3: fet-badge-6x | C3: 6x
A4: fet-badge-7x | C4: 7x
A5: fet-badge-15x | C5: 15x
A6: LOTUS
A7: fet-feature-trueplay-sub4 | C7: This software measures the acoustics of the room then fine-tunes your Sonos system.
A8: MISSING & DIFFERENCE

Sheet DIFF
A1: FIGMA | B1: SHEETS | C1: KEY | D1: TRANSLATION
A2: $179 | C2: {=IFERROR(INDEX('Duke release copy DEV'!A:A, MATCH(B2, 'Duke release copy DEV'!C:C, 0)), "")} | D2: {=IFERROR(INDEX('Duke release copy DEV'!X:X, MATCH(C2, 'Duke release copy DEV'!A:A, 0)), "")}
A3: $249 | C3: {=IFERROR(INDEX('Duke release copy DEV'!A:A, MATCH(B3, 'Duke release copy DEV'!C:C, 0)), "")} | D3: {=IFERROR(INDEX('Duke release copy DEV'!X:X, MATCH(C3, 'Duke release copy DEV'!A:A, 0)), "")}
A4: $279 | C4: {=IFERROR(INDEX('Duke release copy DEV'!A:A, MATCH(B4, 'Duke release copy DEV'!C:C, 0)), "")} | D4: {=IFERROR(INDEX('Duke release copy DEV'!X:X, MATCH(C4, 'Duke release copy DEV'!A:A, 0)), "")} | E4: In one, but not the other
A5: $429 | C5: {=IFERROR(INDEX('Duke release copy DEV'!A:A, MATCH(B5, 'Duke release copy DEV'!C:C, 0)), "")} | D5: {=IFERROR(INDEX('Duke release copy DEV'!X:X, MATCH(C5, 'Duke release copy DEV'!A:A, 0)), "")} | E5: In both Figma and Sheet
A6: $449 | C6: {=IFERROR(INDEX('Duke release copy DEV'!A:A, MATCH(B6, 'Duke release copy DEV'!C:C, 0)), "")} | D6: {=IFERROR(INDEX('Duke release copy DEV'!X:X, MATCH(C6, 'Duke release copy DEV'!A:A, 0)), "")} | E6: Missing
A7: $499 | C7: {=IFERROR(INDEX('Duke release copy DEV'!A:A, MATCH(B7, 'Duke release copy DEV'!C:C, 0)), "")} | D7: {=IFERROR(INDEX('Duke release copy DEV'!X:X, MATCH(C7, 'Duke release copy DEV'!A:A, 0)), "")}
A8: $549 | C8: {=IFERROR(INDEX('Duke release copy DEV'!A:A, MATCH(B8, 'Duke release copy DEV'!C:C, 0)), "")} | D8: {=IFERROR(INDEX('Duke release copy DEV'!X:X, MATCH(C8, 'Duke release copy DEV'!A:A, 0)), "")}
A9: $799 | C9: {=IFERROR(INDEX('Duke release copy DEV'!A:A, MATCH(B9, 'Duke release copy DEV'!C:C, 0)), "")} | D9: {=IFERROR(INDEX('Duke release copy DEV'!X:X, MATCH(C9, 'Duke release copy DEV'!A:A, 0)), "")}
A10: $899.99 | C10: {=IFERROR(INDEX('Duke release copy DEV'!A:A, MATCH(B10, 'Duke release copy DEV'!C:C, 0)), "")} | D10: {=IFERROR(INDEX('Duke release copy DEV'!X:X, MATCH(C10, 'Duke release copy DEV'!A:A, 0)), "")}
B11: *HDMI eARC connection required. **This is not an indication of a licensed decoder. | C11: {=IFERROR(INDEX('Duke release copy DEV'!A:A, MATCH(B11, 'Duke release copy DEV'!C:C, 0)), "")} | D11: {=IFERROR(INDEX('Duke release copy DEV'!X:X, MATCH(C11, 'Duke release copy DEV'!A:A, 0)), "")}
A12: 0.95 lb (0.43 kg) | B12: 0.95 lb (0.43 kg) | C12: {=IFERROR(INDEX('Duke release copy DEV'!A:A, MATCH(B12, 'Duke release copy DEV'!C:C, 0)), "")} | D12: {=IFERROR(INDEX('Duke release copy DEV'!X:X, MATCH(C12, 'Duke release copy DEV'!A:A, 0)), "")}
A13: 01 | C13: {=IFERROR(INDEX('Duke release copy DEV'!A:A, MATCH(B13, 'Duke release copy DEV'!C:C, 0)), "")} | D13: {=IFERROR(INDEX('Duke release copy DEV'!X:X, MATCH(C13, 'Duke release copy DEV'!A:A, 0)), "")}
A14: 02 | C14: {=IFERROR(INDEX('Duke release copy DEV'!A:A, MATCH(B14, 'Duke release copy DEV'!C:C, 0)), "")} | D14: {=IFERROR(INDEX('Duke release copy DEV'!X:X, MATCH(C14, 'Duke release copy DEV'!A:A, 0)), "")}
A15: 03 | C15: {=IFERROR(INDEX('Duke release copy DEV'!A:A, MATCH(B15, 'Duke release copy DEV'!C:C, 0)), "")} | D15: {=IFERROR(INDEX('Duke release copy DEV'!X:X, MATCH(C15, 'Duke release copy DEV'!A:A, 0)), "")}
A16: 04 | C16: {=IFERROR(INDEX('Duke release copy DEV'!A:A, MATCH(B16, 'Duke release copy DEV'!C:C, 0)), "")} | D16: {=IFERROR(INDEX('Duke release copy DEV'!X:X, MATCH(C16, 'Duke release copy DEV'!A:A, 0)), "")}
A17: 05 | C17: {=IFERROR(INDEX('Duke release copy DEV'!A:A, MATCH(B17, 'Duke release copy DEV'!C:C, 0)), "")} | D17: {=IFERROR(INDEX('Duke release copy DEV'!X:X, MATCH(C17, 'Duke release copy DEV'!A:A, 0)), "")}
A18: 06 | C18: {=IFERROR(INDEX('Duke release copy DEV'!A:A, MATCH(B18, 'Duke release copy DEV'!C:C, 0)), "")} | D18: {=IFERROR(INDEX('Duke release copy DEV'!X:X, MATCH(C18, 'Duke release copy DEV'!A:A, 0)), "")}
A19: 1 GB SDRAM8 GB NV | B19: 1 GB SDRAM8 GB NV | C19: {=IFERROR(INDEX('Duke release copy DEV'!A:A, MATCH(B19, 'Duke release copy DEV'!C:C, 0)), "")} | D19: {=IFERROR(INDEX('Duke release copy DEV'!X:X, MATCH(C19, 'Duke release copy DEV'!A:A, 0)), "")}
A20: 10+ hour battery life | B20: 10+ hour battery life | C20: {=IFERROR(INDEX('Duke release copy DEV'!A:A, MATCH(B20, 'Duke release copy DEV'!C:C, 0)), "")} | D20: {=IFERROR(INDEX('Duke release copy DEV'!X:X, MATCH(C20, 'Duke release copy DEV'!A:A, 0)), "")}
A21: 100-240V 50/60Hz internal power supply | B21: 100-240V 50/60Hz internal power supply | C21: {=IFERROR(INDEX('Duke release copy DEV'!A:A, MATCH(B21, 'Duke release copy DEV'!C:C, 0)), "")} -> fet-feature-voltage-100-240V-50-60Hz | D21: {=IFERROR(INDEX('Duke release copy DEV'!X:X, MATCH(C21, 'Duke release copy DEV'!A:A, 0)), "")} -> 100-240V 50/60Hz内部电源
A22: 11.11 oz (315 g) | B22: 11.11 oz (315 g) | C22: {=IFERROR(INDEX('Duke release copy DEV'!A:A, MATCH(B22, 'Duke release copy DEV'!C:C, 0)), "")} -> fet-feature-weight-duke | D22: {=IFERROR(INDEX('Duke release copy DEV'!X:X, MATCH(C22, 'Duke release copy DEV'!A:A, 0)), "")} -> 315克（11.11盎司）
A23: 13 lb (5.9 kg) | B23: 13 lb (5.9 kg) | C23: {=IFERROR(INDEX('Duke release copy DEV'!A:A, MATCH(B23, 'Duke release copy DEV'!C:C, 0)), "")} | D23: {=IFERROR(INDEX('Duke release copy DEV'!X:X, MATCH(C23, 'Duke release copy DEV'!A:A, 0)), "")}
B24: 13.78 lb (6.25 kg) | C24: {=IFERROR(INDEX('Duke release copy DEV'!A:A, MATCH(B24, 'Duke release copy DEV'!C:C, 0)), "")} | D24: {=IFERROR(INDEX('Duke release copy DEV'!X:X, MATCH(C24, 'Duke release copy DEV'!A:A, 0)), "")}
A25: 14 lb (6.35 kg) | B25: 14 lb (6.35 kg) | C25: {=IFERROR(INDEX('Duke release copy DEV'!A:A, MATCH(B25, 'Duke release copy DEV'!C:C, 0)), "")} | D25: {=IFERROR(INDEX('Duke release copy DEV'!X:X, MATCH(C25, 'Duke release copy DEV'!A:A, 0)), "")}
A26: 14 lb (6.36 kg) | B26: 14 lb (6.36 kg) | C26: {=IFERROR(INDEX('Duke release copy DEV'!A:A, MATCH(B26, 'Duke release copy DEV'!C:C, 0)), "")} | D26: {=IFERROR(INDEX('Duke release copy DEV'!X:X, MATCH(C26, 'Duke release copy DEV'!A:A, 0)), "")}
A27: 14°F to 130°F (-10°C to 55°C) | B27: 14°F to 130°F (-10°C to 55°C) | C27: {=IFERROR(INDEX('Duke release copy DEV'!A:A, MATCH(B27, 'Duke release copy DEV'!C:C, 0)), "")} -> fet-feature-operating-temperature-prima | D27: {=IFERROR(INDEX('Duke release copy DEV'!X:X, MATCH(C27, 'Duke release copy DEV'!A:A, 0)), "")} -> -10°C到55°C （14°F到130°F）
A28: 15x | C28: {=IFERROR(INDEX('Duke release copy DEV'!A:A, MATCH(B28, 'Duke release copy DEV'!C:C, 0)), "")} | D28: {=IFERROR(INDEX('Duke release copy DEV'!X:X, MATCH(C28, 'Duke release copy DEV'!A:A, 0)), "")}
B29: 16 GB SDRAM 8GB NV | C29: {=IFERROR(INDEX('Duke release copy DEV'!A:A, MATCH(B29, 'Duke release copy DEV'!C:C, 0)), "")} -> fet-feature-memory-16-gb-sdram-8gb-nv | D29: {=IFERROR(INDEX('Duke release copy DEV'!X:X, MATCH(C29, 'Duke release copy DEV'!A:A, 0)), "")} -> 16 GB SDRAM 8GB NV
A30: 16 GB SDRAM 8GB NV | C30: {=IFERROR(INDEX('Duke release copy DEV'!A:A, MATCH(B30, 'Duke release copy DEV'!C:C, 0)), "")} | D30: {=IFERROR(INDEX('Duke release copy DEV'!X:X, MATCH(C30, 'Duke release copy DEV'!A:A, 0)), "")}
B31: 18Wh battery provides up to 10 hours of continuous playback on a single charge at moderate volumes. | C31: {=IFERROR(INDEX('Duke release copy DEV'!A:A, MATCH(B31, 'Duke release copy DEV'!C:C, 0)), "")} -> fet-feature-battery-roam2 | D31: {=IFERROR(INDEX('Duke release copy DEV'!X:X, MATCH(C31, 'Duke release copy DEV'!A:A, 0)), "")} -> 18Wh电池在中等音量下一次充电即可享受长达10小时连续播放。
A32: 18Wh battery provides up to 10 hours of continuous playback on a single charge. | B32: 18Wh battery provides up to 10 hours of continuous playback on a single charge. | C32: {=IFERROR(INDEX('Duke release copy DEV'!A:A, MATCH(B32, 'Duke release copy DEV'!C:C, 0)), "")} | D32: {=IFERROR(INDEX('Duke release copy DEV'!X:X, MATCH(C32, 'Duke release copy DEV'!A:A, 0)), "")}
A33: 1GB SDRAM 4GB NV | B33: 1GB SDRAM 4GB NV | C33: {=IFERROR(INDEX('Duke release copy DEV'!A:A, MATCH(B33, 'Duke release copy DEV'!C:C, 0)), "")} -> fet-feature-memory-1gb-sdram-4gb-nv | D33: {=IFERROR(INDEX('Duke release copy DEV'!X:X, MATCH(C33, 'Duke release copy DEV'!A:A, 0)), "")} -> 1GB SDRAM 4GB NV
A34: 1x | C34: {=IFERROR(INDEX('Duke release copy DEV'!A:A, MATCH(B34, 'Duke release copy DEV'!C:C, 0)), "")} | D34: {=IFERROR(INDEX('Duke release copy DEV'!X:X, MATCH(C34, 'Duke release copy DEV'!A:A, 0)), "")}
A35: 24 hour battery life | B35: 24 hour battery life | C35: {=IFERROR(INDEX('Duke release copy DEV'!A:A, MATCH(B35, 'Duke release copy DEV'!C:C, 0)), "")} -> fet-badge-battery-life-24 | D35: {=IFERROR(INDEX('Duke release copy DEV'!X:X, MATCH(C35, 'Duke release copy DEV'!A:A, 0)), "")} -> 24小时电池续航时间
A36: 256 MB SDRAM 256 MB NAND Flash | B36: 256 MB SDRAM 256 MB NAND Flash | C36: {=IFERROR(INDEX('Duke release copy DEV'!A:A, MATCH(B36, 'Duke release copy DEV'!C:C, 0)), "")} -> fet-feature-memory-256-mb-sdram-256-mb-nand-flash | D36: {=IFERROR(INDEX('Duke release copy DEV'!X:X, MATCH(C36, 'Duke release copy DEV'!A:A, 0)), "")} -> 256 MB SDRAM 256 MB NAND Flash
A37: 26 lb (11.79 kg) | B37: 26 lb (11.79 kg) | C37: {=IFERROR(INDEX('Duke release copy DEV'!A:A, MATCH(B37, 'Duke release copy DEV'!C:C, 0)), "")} | D37: {=IFERROR(INDEX('Duke release copy DEV'!X:X, MATCH(C37, 'Duke release copy DEV'!A:A, 0)), "")}
A38: 29 lb (13.15 kg) | B38: 29 lb (13.15 kg) | C38: {=IFERROR(INDEX('Duke release copy DEV'!A:A, MATCH(B38, 'Duke release copy DEV'!C:C, 0)), "")} | D38: {=IFERROR(INDEX('Duke release copy DEV'!X:X, MATCH(C38, 'Duke release copy DEV'!A:A, 0)), "")}
A39: 2x | C39: {=IFERROR(INDEX('Duke release copy DEV'!A:A, MATCH(B39, 'Duke release copy DEV'!C:C, 0)), "")} | D39: {=IFERROR(INDEX('Duke release copy DEV'!X:X, MATCH(C39, 'Duke release copy DEV'!A:A, 0)), "")}
A40: 30 hour battery life | B40: 30 hour battery life | C40: {=IFERROR(INDEX('Duke release copy DEV'!A:A, MATCH(B40, 'Duke release copy DEV'!C:C, 0)), "")} -> fet-badge-battery-life-30 | D40: {=IFERROR(INDEX('Duke release copy DEV'!X:X, MATCH(C40, 'Duke release copy DEV'!A:A, 0)), "")} -> 30小时电池续航时间
A41: 32°F to 104°F (0°C to 40°C) | B41: 32°F to 104°F (0°C to 40°C) | C41: {=IFERROR(INDEX('Duke release copy DEV'!A:A, MATCH(B41, 'Duke release copy DEV'!C:C, 0)), "")} -> fet-feature-operating-temperature-32f-104f-0c-40c | D41: {=IFERROR(INDEX('Duke release copy DEV'!X:X, MATCH(C41, 'Duke release copy DEV'!A:A, 0)), "")} -> 0°C到40°C （32°F到104°F）
A42: 32°F to 113°F (0°C to 45°C) | B42: 32°F to 113°F (0°C to 45°C) | C42: {=IFERROR(INDEX('Duke release copy DEV'!A:A, MATCH(B42, 'Duke release copy DEV'!C:C, 0)), "")} -> fet-feature-charging-temperature-32f-113f-0c-45c | D42: {=IFERROR(INDEX('Duke release copy DEV'!X:X, MATCH(C42, 'Duke release copy DEV'!A:A, 0)), "")} -> 0°C到45°C （32°F到113°F）
A43: 36Wh battery provides up to 11 hours of continuous playback on a single charge at moderate volumes. | B43: 36Wh battery provides up to 11 hours of continuous playback on a single charge at moderate volumes. | C43: {=IFERROR(INDEX('Duke release copy DEV'!A:A, MATCH(B43, 'Duke release copy DEV'!C:C, 0)), "")} | D43: {=IFERROR(INDEX('Duke release copy DEV'!X:X, MATCH(C43, 'Duke release copy DEV'!A:A, 0)), "")}
A44: 3x | C44: {=IFERROR(INDEX('Duke release copy DEV'!A:A, MATCH(B44, 'Duke release copy DEV'!C:C, 0)), "")} | D44: {=IFERROR(INDEX('Duke release copy DEV'!X:X, MATCH(C44, 'Duke release copy DEV'!A:A, 0)), "")}
A45: 4.29 lb (1.95 kg) | B45: 4.29 lb (1.95 kg) | C45: {=IFERROR(INDEX('Duke release copy DEV'!A:A, MATCH(B45, 'Duke release copy DEV'!C:C, 0)), "")} | D45: {=IFERROR(INDEX('Duke release copy DEV'!X:X, MATCH(C45, 'Duke release copy DEV'!A:A, 0)), "")}
A46: 4.44 lb (2.02 kg) | B46: 4.44 lb (2.02 kg) | C46: {=IFERROR(INDEX('Duke release copy DEV'!A:A, MATCH(B46, 'Duke release copy DEV'!C:C, 0)), "")} | D46: {=IFERROR(INDEX('Duke release copy DEV'!X:X, MATCH(C46, 'Duke release copy DEV'!A:A, 0)), "")}
A47: 41°F to 95°F (5°C to 35°C) | B47: 41°F to 95°F (5°C to 35°C) | C47: {=IFERROR(INDEX('Duke release copy DEV'!A:A, MATCH(B47, 'Duke release copy DEV'!C:C, 0)), "")} -> fet-feature-operating-temperature-roam2 | D47: {=IFERROR(INDEX('Duke release copy DEV'!X:X, MATCH(C47, 'Duke release copy DEV'!A:A, 0)), "")} -> 5°C到35°C （41°F到95°F）
A48: 4x | C48: {=IFERROR(INDEX('Duke release copy DEV'!A:A, MATCH(B48, 'Duke release copy DEV'!C:C, 0)), "")} | D48: {=IFERROR(INDEX('Duke release copy DEV'!X:X, MATCH(C48, 'Duke release copy DEV'!A:A, 0)), "")}
A49: 5" x 8" elliptical woofers | C49: {=IFERROR(INDEX('Duke release copy DEV'!A:A, MATCH(B49, 'Duke release copy DEV'!C:C, 0)), "")} | D49: {=IFERROR(INDEX('Duke release copy DEV'!X:X, MATCH(C49, 'Duke release copy DEV'!A:A, 0)), "")}
A50: 512 MB DDR4 4GB eMMC | B50: 512 MB DDR4 4GB eMMC | C50: {=IFERROR(INDEX('Duke release copy DEV'!A:A, MATCH(B50, 'Duke release copy DEV'!C:C, 0)), "")} -> fet-feature-memory-sub4 | D50: {=IFERROR(INDEX('Duke release copy DEV'!X:X, MATCH(C50, 'Duke release copy DEV'!A:A, 0)), "")} -> 512 MB DDR4 4GB eMMC
A51: 512 MB SDRAM 512 MB NAND Flash | B51: 512 MB SDRAM 512 MB NAND Flash | C51: {=IFERROR(INDEX('Duke release copy DEV'!A:A, MATCH(B51, 'Duke release copy DEV'!C:C, 0)), "")} -> fet-feature-memory-512-mb-sdram-512-mb-nand-flash | D51: {=IFERROR(INDEX('Duke release copy DEV'!X:X, MATCH(C51, 'Duke release copy DEV'!A:A, 0)), "")} -> 512 MB SDRAM 512 MB NAND Flash
A52: 5x | C52: {=IFERROR(INDEX('Duke release copy DEV'!A:A, MATCH(B52, 'Duke release copy DEV'!C:C, 0)), "")} | D52: {=IFERROR(INDEX('Duke release copy DEV'!X:X, MATCH(C52, 'Duke release copy DEV'!A:A, 0)), "")}
B53: 6" woofer | C53: {=IFERROR(INDEX('Duke release copy DEV'!A:A, MATCH(B53, 'Duke release copy DEV'!C:C, 0)), "")} | D53: {=IFERROR(INDEX('Duke release copy DEV'!X:X, MATCH(C53, 'Duke release copy DEV'!A:A, 0)), "")}
A54: 6" woofers | B54: 6" woofers | C54: {=IFERROR(INDEX('Duke release copy DEV'!A:A, MATCH(B54, 'Duke release copy DEV'!C:C, 0)), "")} -> fet-feature-6-inch-woofers | D54: {=IFERROR(INDEX('Duke release copy DEV'!X:X, MATCH(C54, 'Duke release copy DEV'!A:A, 0)), "")} -> 6英寸低音扬声器
B55: 6.2 lb (2.8 kg) | C55: {=IFERROR(INDEX('Duke release copy DEV'!A:A, MATCH(B55, 'Duke release copy DEV'!C:C, 0)), "")} | D55: {=IFERROR(INDEX('Duke release copy DEV'!X:X, MATCH(C55, 'Duke release copy DEV'!A:A, 0)), "")}
A56: 6.2 lb (2.8kg) | B56: 6.2 lb (2.8kg) | C56: {=IFERROR(INDEX('Duke release copy DEV'!A:A, MATCH(B56, 'Duke release copy DEV'!C:C, 0)), "")} | D56: {=IFERROR(INDEX('Duke release copy DEV'!X:X, MATCH(C56, 'Duke release copy DEV'!A:A, 0)), "")}
A57: 6.61 lb (3 kg) | B57: 6.61 lb (3 kg) | C57: {=IFERROR(INDEX('Duke release copy DEV'!A:A, MATCH(B57, 'Duke release copy DEV'!C:C, 0)), "")} | D57: {=IFERROR(INDEX('Duke release copy DEV'!X:X, MATCH(C57, 'Duke release copy DEV'!A:A, 0)), "")}
A58: 6.61 lbs (3 kg) | C58: {=IFERROR(INDEX('Duke release copy DEV'!A:A, MATCH(B58, 'Duke release copy DEV'!C:C, 0)), "")} | D58: {=IFERROR(INDEX('Duke release copy DEV'!X:X, MATCH(C58, 'Duke release copy DEV'!A:A, 0)), "")}
A59: 6x | C59: {=IFERROR(INDEX('Duke release copy DEV'!A:A, MATCH(B59, 'Duke release copy DEV'!C:C, 0)), "")} | D59: {=IFERROR(INDEX('Duke release copy DEV'!X:X, MATCH(C59, 'Duke release copy DEV'!A:A, 0)), "")}
A60: 6” woofers | C60: {=IFERROR(INDEX('Duke release copy DEV'!A:A, MATCH(B60, 'Duke release copy DEV'!C:C, 0)), "")} | D60: {=IFERROR(INDEX('Duke release copy DEV'!X:X, MATCH(C60, 'Duke release copy DEV'!A:A, 0)), "")}
A61: 7x | C61: {=IFERROR(INDEX('Duke release copy DEV'!A:A, MATCH(B61, 'Duke release copy DEV'!C:C, 0)), "")} | D61: {=IFERROR(INDEX('Duke release copy DEV'!X:X, MATCH(C61, 'Duke release copy DEV'!A:A, 0)), "")}
A62: 8 GB DDR4 8 GB NAND | B62: 8 GB DDR4 8 GB NAND | C62: {=IFERROR(INDEX('Duke release copy DEV'!A:A, MATCH(B62, 'Duke release copy DEV'!C:C, 0)), "")} -> fet-feature-memory-8-gb-ddr4-8-gb-nand | D62: {=IFERROR(INDEX('Duke release copy DEV'!X:X, MATCH(C62, 'Duke release copy DEV'!A:A, 0)), "")} -> 8 GB DDR4 8 GB NAND
B63: 80 pounds to go. | C63: {=IFERROR(INDEX('Duke release copy DEV'!A:A, MATCH(B63, 'Duke release copy DEV'!C:C, 0)), "")} -> subtitles.nature.8 | D63: {=IFERROR(INDEX('Duke release copy DEV'!X:X, MATCH(C63, 'Duke release copy DEV'!A:A, 0)), "")} -> 还差36公斤。
A64: 9.85 lb (4.47 kg) | B64: 9.85 lb (4.47 kg) | C64: {=IFERROR(INDEX('Duke release copy DEV'!A:A, MATCH(B64, 'Duke release copy DEV'!C:C, 0)), "")} | D64: {=IFERROR(INDEX('Duke release copy DEV'!X:X, MATCH(C64, 'Duke release copy DEV'!A:A, 0)), "")}
A65: About Sonos | B65: About Sonos | C65: {=IFERROR(INDEX('Duke release copy DEV'!A:A, MATCH(B65, 'Duke release copy DEV'!C:C, 0)), "")} -> fet-nav-about-sonos | D65: {=IFERROR(INDEX('Duke release copy DEV'!X:X, MATCH(C65, 'Duke release copy DEV'!A:A, 0)), "")} -> Sonos简介
B66: Acoustic port | C66: {=IFERROR(INDEX('Duke release copy DEV'!A:A, MATCH(B66, 'Duke release copy DEV'!C:C, 0)), "")} | D66: {=IFERROR(INDEX('Duke release copy DEV'!X:X, MATCH(C66, 'Duke release copy DEV'!A:A, 0)), "")}
A67: Acoustic ports | B67: Acoustic ports | C67: {=IFERROR(INDEX('Duke release copy DEV'!A:A, MATCH(B67, 'Duke release copy DEV'!C:C, 0)), "")} -> fet-feature-acoustic-ports | D67: {=IFERROR(INDEX('Duke release copy DEV'!X:X, MATCH(C67, 'Duke release copy DEV'!A:A, 0)), "")} -> 声学端口
A68: Active Noise Cancellation | B68: Active Noise Cancellation | C68: {=IFERROR(INDEX('Duke release copy DEV'!A:A, MATCH(B68, 'Duke release copy DEV'!C:C, 0)), "")} -> fet-badge-active-noise-cancellation-capitalized | D68: {=IFERROR(INDEX('Duke release copy DEV'!X:X, MATCH(C68, 'Duke release copy DEV'!A:A, 0)), "")} -> 主动消噪
A69: Active noise cancellation | B69: Active noise cancellation | C69: {=IFERROR(INDEX('Duke release copy DEV'!A:A, MATCH(B69, 'Duke release copy DEV'!C:C, 0)), "")} -> fet-badge-active-noise-cancellation-capitalized | D69: {=IFERROR(INDEX('Duke release copy DEV'!X:X, MATCH(C69, 'Duke release copy DEV'!A:A, 0)), "")} -> 主动消噪
A70: Active noise cancellation | C70: {=IFERROR(INDEX('Duke release copy DEV'!A:A, MATCH(B70, 'Duke release copy DEV'!C:C, 0)), "")} | D70: {=IFERROR(INDEX('Duke release copy DEV'!X:X, MATCH(C70, 'Duke release copy DEV'!A:A, 0)), "")}
A71: Adjustable EQ | B71: Adjustable EQ | C71: {=IFERROR(INDEX('Duke release copy DEV'!A:A, MATCH(B71, 'Duke release copy DEV'!C:C, 0)), "")} -> fet-badge-adjustable-eq | D71: {=IFERROR(INDEX('Duke release copy DEV'!X:X, MATCH(C71, 'Duke release copy DEV'!A:A, 0)), "")} -> 可调整EQ
B72: Ah, takes it away! | C72: {=IFERROR(INDEX('Duke release copy DEV'!A:A, MATCH(B72, 'Duke release copy DEV'!C:C, 0)), "")} -> subtitles.sports.8 | D72: {=IFERROR(INDEX('Duke release copy DEV'!X:X, MATCH(C72, 'Duke release copy DEV'!A:A, 0)), "")}
B73: Alexa built-in | C73: {=IFERROR(INDEX('Duke release copy DEV'!A:A, MATCH(B73, 'Duke release copy DEV'!C:C, 0)), "")} | D73: {=IFERROR(INDEX('Duke release copy DEV'!X:X, MATCH(C73, 'Duke release copy DEV'!A:A, 0)), "")}
A74: All the sounds you want, none of the noise you don't | B74: All the sounds you want, none of the noise you don't | C74: {=IFERROR(INDEX('Duke release copy DEV'!A:A, MATCH(B74, 'Duke release copy DEV'!C:C, 0)), "")} -> fet-slide-3-headline-duke | D74: {=IFERROR(INDEX('Duke release copy DEV'!X:X, MATCH(C74, 'Duke release copy DEV'!A:A, 0)), "")} -> 消除喧嚣噪声，唯有动人佳音
B75: All the way home. | C75: {=IFERROR(INDEX('Duke release copy DEV'!A:A, MATCH(B75, 'Duke release copy DEV'!C:C, 0)), "")} -> subtitles.sports.15 | D75: {=IFERROR(INDEX('Duke release copy DEV'!X:X, MATCH(C75, 'Duke release copy DEV'!A:A, 0)), "")}
B76: Amp | C76: {=IFERROR(INDEX('Duke release copy DEV'!A:A, MATCH(B76, 'Duke release copy DEV'!C:C, 0)), "")} -> fet-name-amp | D76: {=IFERROR(INDEX('Duke release copy DEV'!X:X, MATCH(C76, 'Duke release copy DEV'!A:A, 0)), "")} -> Amp
A77: Amplifiers | B77: Amplifiers | C77: {=IFERROR(INDEX('Duke release copy DEV'!A:A, MATCH(B77, 'Duke release copy DEV'!C:C, 0)), "")} -> fet-feature-amplifiers | D77: {=IFERROR(INDEX('Duke release copy DEV'!X:X, MATCH(C77, 'Duke release copy DEV'!A:A, 0)), "")} -> 放大器
B78: And score! | C78: {=IFERROR(INDEX('Duke release copy DEV'!A:A, MATCH(B78, 'Duke release copy DEV'!C:C, 0)), "")} -> subtitles.sports.16 | D78: {=IFERROR(INDEX('Duke release copy DEV'!X:X, MATCH(C78, 'Duke release copy DEV'!A:A, 0)), "")}
B79: And the fans going wild. | C79: {=IFERROR(INDEX('Duke release copy DEV'!A:A, MATCH(B79, 'Duke release copy DEV'!C:C, 0)), "")} -> subtitles.sports.17 | D79: {=IFERROR(INDEX('Duke release copy DEV'!X:X, MATCH(C79, 'Duke release copy DEV'!A:A, 0)), "")}
A80: Angled Tweeters | C80: {=IFERROR(INDEX('Duke release copy DEV'!A:A, MATCH(B80, 'Duke release copy DEV'!C:C, 0)), "")} | D80: {=IFERROR(INDEX('Duke release copy DEV'!X:X, MATCH(C80, 'Duke release copy DEV'!A:A, 0)), "")}
B81: Angled tweeter | C81: {=IFERROR(INDEX('Duke release copy DEV'!A:A, MATCH(B81, 'Duke release copy DEV'!C:C, 0)), "")} | D81: {=IFERROR(INDEX('Duke release copy DEV'!X:X, MATCH(C81, 'Duke release copy DEV'!A:A, 0)), "")}
A82: Angled tweeters | B82: Angled tweeters | C82: {=IFERROR(INDEX('Duke release copy DEV'!A:A, MATCH(B82, 'Duke release copy DEV'!C:C, 0)), "")} -> fet-feature-angled-tweeters | D82: {=IFERROR(INDEX('Duke release copy DEV'!X:X, MATCH(C82, 'Duke release copy DEV'!A:A, 0)), "")} -> 成角度的高音扬声器
A83: Apple AirPlay 2 | B83: Apple AirPlay 2 | C83: {=IFERROR(INDEX('Duke release copy DEV'!A:A, MATCH(B83, 'Duke release copy DEV'!C:C, 0)), "")} -> fet-badge-apple-airplay2 | D83: {=IFERROR(INDEX('Duke release copy DEV'!X:X, MATCH(C83, 'Duke release copy DEV'!A:A, 0)), "")} -> Apple AirPlay 2
A84: Apple AirPlay 2 | C84: {=IFERROR(INDEX('Duke release copy DEV'!A:A, MATCH(B84, 'Duke release copy DEV'!C:C, 0)), "")} | D84: {=IFERROR(INDEX('Duke release copy DEV'!X:X, MATCH(C84, 'Duke release copy DEV'!A:A, 0)), "")}
A85: Apple AirPlay 2³ | C85: {=IFERROR(INDEX('Duke release copy DEV'!A:A, MATCH(B85, 'Duke release copy DEV'!C:C, 0)), "")} | D85: {=IFERROR(INDEX('Duke release copy DEV'!X:X, MATCH(C85, 'Duke release copy DEV'!A:A, 0)), "")}
A86: Arc | B86: Arc | C86: {=IFERROR(INDEX('Duke release copy DEV'!A:A, MATCH(B86, 'Duke release copy DEV'!C:C, 0)), "")} -> fet-name-arc | D86: {=IFERROR(INDEX('Duke release copy DEV'!X:X, MATCH(C86, 'Duke release copy DEV'!A:A, 0)), "")} -> Arc
A87: Arc Ultra | B87: Arc Ultra | C87: {=IFERROR(INDEX('Duke release copy DEV'!A:A, MATCH(B87, 'Duke release copy DEV'!C:C, 0)), "")} -> fet-name-arcultra | D87: {=IFERROR(INDEX('Duke release copy DEV'!X:X, MATCH(C87, 'Duke release copy DEV'!A:A, 0)), "")} -> Arc Ultra
A88: Arc Ultra brings your entertainment to life like no other soundbar. Experience unprecedentedly clear, deep, and balanced sound that precisely surrounds you from every direction — all with an unbelievably sleek design made possible by breakthrough Sound Motion technology. | B88: Arc Ultra brings your entertainment to life like no other soundbar. Experience unprecedentedly clear, deep, and balanced sound that precisely surrounds you from every direction — all with an unbelievably sleek design made possible by breakthrough Sound Motion technology. | C88: {=IFERROR(INDEX('Duke release copy DEV'!A:A, MATCH(B88, 'Duke release copy DEV'!C:C, 0)), "")} | D88: {=IFERROR(INDEX('Duke release copy DEV'!X:X, MATCH(C88, 'Duke release copy DEV'!A:A, 0)), "")}
A89: Architecture | B89: Architecture | C89: {=IFERROR(INDEX('Duke release copy DEV'!A:A, MATCH(B89, 'Duke release copy DEV'!C:C, 0)), "")} -> fet-feature-architecture | D89: {=IFERROR(INDEX('Duke release copy DEV'!X:X, MATCH(C89, 'Duke release copy DEV'!A:A, 0)), "")} -> 架构
A90: Artist Name | C90: {=IFERROR(INDEX('Duke release copy DEV'!A:A, MATCH(B90, 'Duke release copy DEV'!C:C, 0)), "")} | D90: {=IFERROR(INDEX('Duke release copy DEV'!X:X, MATCH(C90, 'Duke release copy DEV'!A:A, 0)), "")}
A91: As low as 25 Hz | B91: As low as 25 Hz | C91: {=IFERROR(INDEX('Duke release copy DEV'!A:A, MATCH(B91, 'Duke release copy DEV'!C:C, 0)), "")} -> fet-feature-frequency-response-25Hz | D91: {=IFERROR(INDEX('Duke release copy DEV'!X:X, MATCH(C91, 'Duke release copy DEV'!A:A, 0)), "")} -> 低至25 Hz
A92: Astonishingly lightweight, durable, and powerful, Roam 2 makes it easy to enjoy Sonos sound everywhere life takes you. Just pair, play, and go. Enjoy up to 10 hours of size-defying clarity and bass. Fully IP67 waterproof and dustproof, Roam 2 is ready for the outdoors. Plus, it doubles as a smart speaker at home. | B92: Astonishingly lightweight, durable, and powerful, Roam 2 makes it easy to enjoy Sonos sound everywhere life takes you. Just pair, play, and go. Enjoy up to 10 hours of size-defying clarity and bass. Fully IP67 waterproof and dustproof, Roam 2 is ready for the outdoors. Plus, it doubles as a smart speaker at home. | C92: {=IFERROR(INDEX('Duke release copy DEV'!A:A, MATCH(B92, 'Duke release copy DEV'!C:C, 0)), "")} | D92: {=IFERROR(INDEX('Duke release copy DEV'!X:X, MATCH(C92, 'Duke release copy DEV'!A:A, 0)), "")}
A93: Audio | B93: Audio | C93: {=IFERROR(INDEX('Duke release copy DEV'!A:A, MATCH(B93, 'Duke release copy DEV'!C:C, 0)), "")} -> fet-feature-audio | D93: {=IFERROR(INDEX('Duke release copy DEV'!X:X, MATCH(C93, 'Duke release copy DEV'!A:A, 0)), "")} -> 音频
A94: Audio settings automatically equalize to balance Sub 4 and the paired Sonos speaker(s). Use the Sonos app to adjust bass, treble, and loudness. | B94: Audio settings automatically equalize to balance Sub 4 and the paired Sonos speaker(s). Use the Sonos app to adjust bass, treble, and loudness. | C94: {=IFERROR(INDEX('Duke release copy DEV'!A:A, MATCH(B94, 'Duke release copy DEV'!C:C, 0)), "")} | D94: {=IFERROR(INDEX('Duke release copy DEV'!X:X, MATCH(C94, 'Duke release copy DEV'!A:A, 0)), "")}
A95: Audio settings automatically equalize to balance Sub Mini and the paired Sonos product(s). Use the Sonos app to adjust bass, treble, and loudness. | B95: Audio settings automatically equalize to balance Sub Mini and the paired Sonos product(s). Use the Sonos app to adjust bass, treble, and loudness. | C95: {=IFERROR(INDEX('Duke release copy DEV'!A:A, MATCH(B95, 'Duke release copy DEV'!C:C, 0)), "")} -> fet-feature-eq-gravity | D95: {=IFERROR(INDEX('Duke release copy DEV'!X:X, MATCH(C95, 'Duke release copy DEV'!A:A, 0)), "")} -> 音频设置自动均衡以平衡Sub Mini和配对的Sonos产品。使用Sonos App调节低音、高音和响度。
B96: Audio settings automatically equalize to balance Sub and the paired Sonos speaker(s) or component. Use the Sonos app to adjust bass, treble, and loudness. | C96: {=IFERROR(INDEX('Duke release copy DEV'!A:A, MATCH(B96, 'Duke release copy DEV'!C:C, 0)), "")} -> fet-feature-eq-sub | D96: {=IFERROR(INDEX('Duke release copy DEV'!X:X, MATCH(C96, 'Duke release copy DEV'!A:A, 0)), "")} -> 音频设置自动均衡以平衡Sub和配对的Sonos音响或组件。使用Sonos App调节低音、高音和响度。
A97: Auto-switching 100-240V 50/60Hz AC universal input | B97: Auto-switching 100-240V 50/60Hz AC universal input | C97: {=IFERROR(INDEX('Duke release copy DEV'!A:A, MATCH(B97, 'Duke release copy DEV'!C:C, 0)), "")} -> fet-feature-voltage-auto-switching-100-240V-50-60hc-ac | D97: {=IFERROR(INDEX('Duke release copy DEV'!X:X, MATCH(C97, 'Duke release copy DEV'!A:A, 0)), "")} -> 自动切换100-240V 50/60Hz AC通用输入
A98: Automatic Trueplay | B98: Automatic Trueplay | C98: {=IFERROR(INDEX('Duke release copy DEV'!A:A, MATCH(B98, 'Duke release copy DEV'!C:C, 0)), "")} -> fet-badge-automatic-trueplay | D98: {=IFERROR(INDEX('Duke release copy DEV'!X:X, MATCH(C98, 'Duke release copy DEV'!A:A, 0)), "")} -> 自适应Trueplay调音
A99: Automatic Trueplay™ | B99: Automatic Trueplay™ | C99: {=IFERROR(INDEX('Duke release copy DEV'!A:A, MATCH(B99, 'Duke release copy DEV'!C:C, 0)), "")} -> fet-badge-automatic-trueplay-tm | D99: {=IFERROR(INDEX('Duke release copy DEV'!X:X, MATCH(C99, 'Duke release copy DEV'!A:A, 0)), "")} -> 自适应Trueplay™调音
A100: Automatic Trueplay™³ | B100: Automatic Trueplay™³ | C100: {=IFERROR(INDEX('Duke release copy DEV'!A:A, MATCH(B100, 'Duke release copy DEV'!C:C, 0)), "")} -> fet-badge-automatic-trueplay-tm3 | D100: {=IFERROR(INDEX('Duke release copy DEV'!X:X, MATCH(C100, 'Duke release copy DEV'!A:A, 0)), "")} -> 自适应Trueplay™调音³
...

Sheet VARIABLES
A1: fet-10HourBatteryLife | B1: 10+ hour battery life
A2: fet-24HourBatteryLife | B2: 24 hour battery life
A3: fet-30HourBatteryLife | B3: 30 hour battery life
A4: fet-30HourBatteryLifeUpTo | B4: Battery life up to 30 hours³
A5: fet-40mmDrivers | B5: Custom-designed 40mm dynamic drivers
A6: fet-6InchWoofers | B6: 6” woofers
A7: fet-about-slide1-description | B7: Each speaker is thoughtfully designed from the inside out then fine-tuned by award-winning creators.
A8: fet-about-slide1-title | B8: Hear how sound should sound
A9: fet-about-slide2-description | B9: Stream music and more from all your favorite services and get incredible sound for TV or even vinyl.
A10: fet-about-slide2-title | B10: Play everything you love
A11: fet-about-slide3-description | B11: Mix and match speakers to build the system you want over time. Everything works together over WiFi.
A12: fet-about-slide3-title | B12: Customize your system
... A191: fet-worksWithAppleAndAndroid | B191: Works with Apple and Android

Sheet Mojave and Bambino - 1213
A1: Key | B1: Description | C1: en-US | D1: en-CA | E1: en-GB | F1: da-DK | G1: de-DE | H1: de-CH | I1: fr-FR | J1: fr-CH | K1: fr-BE | L1: fr-CA | M1: it-IT | N1: it-CH | O1: ja-JP | P1: es-MX | Q1: nl-NL | R1: nb-NO | S1: es-ES | T1: sv-SE | U1: en-AU | V1: en-NZ | W1: en-RW | X1: zh-CN | Y1: cs-CZ | Z1: fi-FI | AA1: pl-PL | AB1: de-LU | AC1: fr-LU | AD1: es-CO
A2: fet-header-intro-system-story | C2: Discover how Sonos brings your home together with seamless sound, room to room and beyond.
A3: fet-slide-1-headline-system-story | C3: The power of the Sonos system
A5: fet-feature-dimensions | B5: Learn More / Details & Dimensions | C5: Dimensions | D5: Dimensions | E5: Dimensions | F5: Mål | G5: Abmessungen | H5: Abmessungen | I5: Dimensions | J5: Dimensions | K5: Dimensions | L5: Dimensions | M5: Dimensioni | N5: Dimensioni | O5: 寸法 | P5: Dimensiones | Q5: Afmetingen | R5: Mål | S5: Dimensiones | T5: Mått | U5: Dimensions | V5: Dimensions | W5: Dimensions | X5: 尺寸 | Y5: Rozměry | Z5: Mitat | AA5: Wymiary | AB5: Abmessungen | AC5: Dimensions | AD5: Dimensiones
A6: fet-feature-weight | B6: Learn More / Details & Dimensions | C6: Weight | D6: Weight | E6: Weight | F6: Vægt | G6: Gewicht | H6: Gewicht | I6: Poids | J6: Poids | K6: Poids | L6: Poids | M6: Peso | N6: Peso | O6: 重量 | P6: Peso | Q6: Gewicht | R6: Vekt | S6: Peso | T6: Vikt | U6: Weight | V6: Weight | W6: Weight | X6: 重量 | Y6: Hmotnost | Z6: Paino | AA6: Waga | AB6: Gewicht | AC6: Poids | AD6: Peso
A7: fet-feature-weight-arc | B7: Learn More / Details & Dimensions / Arc | C7: 13.78 lb (6.25 kg) | D7: 13.78 lb (6.25 kg) | E7: 13.78 lb (6.25 kg) | F7: 6,25 kg | G7: 6,25 kg | H7: 6,25 kg | I7: 6,25 kg | J7: 6,25 kg | K7: 6,25 kg | L7: 6,25 kg (13,78 lb) | M7: 6,25 kg (13,78 lb) | N7: 6,25 kg (13,78 lb) | O7: 6.25 kg | P7: 6.25 kg (13.78 lb) | Q7: 6,25 kg | R7: 6,25 kg | S7: 6,25 kg (13,78 lb) | T7: 6,25 kg | U7: 6.25 kg | V7: 6.25 kg | W7: 13.78 lb (6.25 kg) | X7: 6.25千克（13.78磅） | Y7: 13,78 libry (6,25 kg) | Z7: 6,25 kg | AA7: 6,25 kg | AB7: 6,25 kg | AC7: 6,25 kg | AD7: 6,25 kg (13,78 lb)
A8: fet-feature-weight-beam | B8: Learn More / Details & Dimensions / Beam | C8: 6.2 lb (2.8 kg) | D8: 6.2 lb (2.8 kg) | E8: 6.2 lb (2.8 kg) | F8: 2,8 kg | G8: 2,8 kg | H8: 2,8 kg | I8: 2,8 kg | J8: 2,8 kg | K8: 2,8 kg | L8: 2,8 kg (6,2 lb) | M8: 2,8 kg (6,2 lb) | N8: 2,8 kg (6,2 lb) | O8: 2.8 kg | P8: 2.8 kg (6.2 lb) | Q8: 2,8 kg | R8: 2,8 kg | S8: 2,8 kg (6,2 lb) | T8: 2,8 kg | U8: 2.8 kg | V8: 2.8 kg | W8: 6.2 lb (2.8 kg) | X8: 2.8千克（6.2磅） | Y8: 6,2 libry (2,8 kg) | Z8: 2,8 kg | AA8: 2,8 kg | AB8: 2,8 kg | AC8: 2,8 kg | AD8: 2,8 kg (6,2 lb)
A9: fet-feature-weight-ray | B9: Learn More / Details & Dimensions / Ray | C9: 4.29 lb (1.95 kg) | D9: 4.29 lb (1.95 kg) | E9: 4.29 lb (1.95 kg) | F9: 1,95 kg | G9: 1,95 kg | H9: 1,95 kg | I9: 1,95 kg | J9: 1,95 kg | K9: 1,95 kg | L9: 1,95 kg (4,29 lb) | M9: 1,95 kg (4,29 lb) | N9: 1,95 kg (4,29 lb) | O9: 1.95 kg | P9: 1.95 kg (4.29 lb) | Q9: 1,95 kg | R9: 1,95 kg | S9: 1,95 kg (4,29 lb) | T9: 1,95 kg | U9: 1.95 kg | V9: 1.95 kg | W9: 4.29 lb (1.95 kg) | X9: 1.95千克（4.29磅） | Y9: 4,29 libry (1,95 kg) | Z9: 1,95 kg | AA9: 1,95 kg | AB9: 1,95 kg | AC9: 1,95 kg | AD9: 1,95 kg (4,29 lb)
A10: fet-feature-weight-sub | B10: Learn More / Details & Dimensions / Sub | C10: 29 lb (13.15 kg) | D10: 29 lb (13.15 kg) | E10: 29 lb (13.15 kg) | F10: 13,15 kg | G10: 13,15 kg | H10: 13,15 kg | I10: 13,15 kg | J10: 13,15 kg | K10: 13,15 kg | L10: 13,15 kg (29 lb) | M10: 13,15 kg (29 lb) | N10: 13,15 kg (29 lb) | O10: 13.15 kg | P10: 13.15 kg (29 lb) | Q10: 13,15 kg | R10: 13,15 kg | S10: 13,15 kg (29 lb) | T10: 13,15 kg | U10: 13.15 kg | V10: 13.15 kg | W10: 29 lb (13.15 kg) | X10: 13.15千克（29磅） | Y10: 29 liber (13,15 kg) | Z10: 13,15 kg | AA10: 13,15 kg | AB10: 13,15 kg | AC10: 13,15 kg | AD10: 13,15 kg (29 lb)
A11: fet-feature-weight-gravity | B11: Learn More / Tech Specs / Details & Dimensions tab | C11: 14 lb (6.35 kg) | D11: 14 lbs (6.35 kg) | E11: 14 lb (6.35 kg) | F11: 6,35 kg | G11: 6,35 kg | H11: 6,35 kg | I11: 6,35 kg | J11: 6,35 kg | K11: 6,35 kg | L11: 6,35 kg (14 lb) | M11: 6,35 kg (14 lb) | N11: 6,35 kg (14 lb) | O11: 6.35 kg | P11: 6.35 kg (14 lb) | Q11: 6,35 kg | R11: 6,35 kg | S11: 6,35 kg (14 lb) | T11: 6,35 kg | U11: 6.35 kg | V11: 6.35 kg | W11: 14 lb (6.35 kg) | X11: 6.35千克（14磅） | Y11: 14 liber (6,35 kg) | Z11: 6,35 kg | AA11: 6,35 kg | AB11: 6,35 kg | AC11: 6,35 kg | AD11: 6.35 kg (14 lb)
A12: fet-feature-weight-optimo1 | B12: Learn More / Details & Dimensions / Optimo 1 | C12: 4.44 lb (2.02 kg) | D12: 4.44 lb (2.02 kg) | E12: 4.44 lb (2.02 kg) | F12: 2,02 kg | G12: 2,02 kg | H12: 2,02 kg | I12: 2,02 kg | J12: 2,02 kg | K12: 2,02 kg | L12: 2,02 kg (4,44 lb) | M12: 2,02 kg (4,44 lb) | N12: 2,02 kg (4,44 lb) | O12: 2.02 kg | P12: 2.02 kg (4.44 lb) | Q12: 2,02 kg | R12: 2,02 kg | S12: 2,02 kg (4,44 lb) | T12: 2,02 kg | U12: 2.02 kg | V12: 2.02 kg | W12: 4.44 lb (2.02 kg) | X12: 2.02千克（4.44磅） | Y12: 4,44 libry (2,02 kg) | Z12: 2,02 kg | AA12: 2,02 kg | AB12: 2,02 kg | AC12: 2,02 kg | AD12: 2,02 kg (4,44 lb)
A13: fet-feature-weight-optimo2 | B13: Learn More / Details & Dimensions / Optimo 2 | C13: 9.85 lb (4.47 kg) | D13: 9.85 lb (4.47 kg) | E13: 9.85 lb (4.47 kg) | F13: 4,47 kg | G13: 4,47 kg | H13: 4,47 kg | I13: 4,47 kg | J13: 4,47 kg | K13: 4,47 kg | L13: 4,47 kg (9,85 lb) | M13: 4,47 kg (9,85 lb) | N13: 4,47 kg (9,85 lb) | O13: 4.47 kg | P13: 4.47 kg (9.85 lb) | Q13: 4,47 kg | R13: 4,47 kg | S13: 4,47 kg (9,85 lb) | T13: 4,47 kg | U13: 4.47 kg | V13: 4.47 kg | W13: 9.85 lb (4.47 kg) | X13: 4.47千克（9.85磅） | Y13: 9,85 libry (4,47 kg) | Z13: 4,47 kg | AA13: 4,47 kg | AB13: 4,47 kg | AC13: 4,47 kg | AD13: 4,47 kg (9,85 lb)
A14: fet-feature-weight-five | B14: Learn More / Details & Dimensions / Five | C14: 14 lb (6.36 kg) | D14: 14 lb (6.36 kg) | E14: 14 lb (6.36 kg) | F14: 6,36 kg | G14: 6,36 kg | H14: 6,36 kg | I14: 6,36 kg | J14: 6,36 kg | K14: 6,36 kg | L14: 6,36 kg (14 lb) | M14: 6,36 kg (14 lb) | N14: 6,36 kg (14 lb) | O14: 6.36 kg | P14: 6.36 kg (14 lb) | Q14: 6,36 kg | R14: 6,36 kg | S14: 6,36 kg (14 lb) | T14: 6,36 kg | U14: 6.36 kg | V14: 6.36 kg | W14: 14 lb (6.36 kg) | X14: 6.36千克（14磅） | Y14: 14 liber (6,36 kg) | Z14: 6,36 kg | AA14: 6,36 kg | AB14: 6,36 kg | AC14: 6,36 kg | AD14: 6,36 kg (14 lb)
A15: fet-feature-weight-move | B15: Learn More / Details & Dimensions / Move | C15: 14 lb (6.36 kg) | D15: 14 lb (6.36 kg) | E15: 14 lb (6.36 kg) | F15: 6,36 kg | G15: 6,36 kg | H15: 6,36 kg | I15: 6,36 kg | J15: 6,36 kg | K15: 6,36 kg | L15: 6,36 kg (14 lb) | M15: 6,36 kg (14 lb) | N15: 6,36 kg (14 lb) | O15: 6.36 kg | P15: 6.36 kg (14 lb) | Q15: 6,36 kg | R15: 6,36 kg | S15: 6,36 kg (14 lb) | T15: 6,36 kg | U15: 6.36 kg | V15: 6.36 kg | W15: 14 lb (6.36 kg) | X15: 6.36千克（14磅） | Y15: 14 liber (6,36 kg) | Z15: 6,36 kg | AA15: 6,36 kg | AB15: 6,36 kg | AC15: 6,36 kg | AD15: 6,36 kg (14 lb)
A16: fet-feature-weight-prima | B16: Learn More / Details & Dimensions / Prima | C16: 6.61 lb (3 kg) | D16: 6.61 lb (3 kg) | E16: 6.61 lb (3 kg) | F16: 3 kg | G16: 3 kg | H16: 3 kg | I16: 3,0 kg | J16: 3,0 kg | K16: 3,0 kg | L16: 3 kg (6,61 lb) | M16: 3 kg (6,61 lb) | N16: 3 kg (6,61 lb) | O16: 3 kg | P16: 3 kg (6.61 lb) | Q16: 3 kg | R16: 3 kg | S16: 3 kg (6,61 lb) | T16: 3 kg | U16: 3 kg | V16: 3 kg | W16: 6.61 lb (3 kg) | X16: 3千克（6.61磅） | Y16: 6,61 libry (3 kg) | Z16: 3 kg | AA16: 3 kg | AB16: 3 kg | AC16: 3,0 kg | AD16: 3 kg (6,61 lb)
... A18: fet-feature-weight-roamsl | B18: Learn More / Details & Dimensions / RoamSL | C18: 0.95 lb (0.43 kg) | D18: 0.95 lb (0.43 kg) | E18: 0.95 lb (0.43 kg) | F18: 0,43 kg | G18: 0,43 kg | H18: 0,43 kg | I18: 0,43 kg | J18: 0,43 kg | K18: 0,43 kg | L18: 0,43 kg (0,95 lb) | M18: 0,43 kg (0,95 lb) | N18: 0,43 kg (0,95 lb) | O18: 0.43 kg | P18: 0.43 kg (0.95 lb) | Q18: 0,43 kg | R18: 0,43 kg | S18: 0,43 kg (0,95 lb) | T18: 0,43 kg | U18: 0.43 kg | V18: 0.43 kg | W18: 0.95 lb (0.43 kg) | X18: 0.43千克（0.95磅） | Y18: 0,95 libry (0,43 kg) | Z18: 0,43 kg | AA18: 0,43 kg | AB18: 0,43 kg | AC18: 0,43 kg | AD18: 0,43 kg (0,95 lb)
A19: fet-feature-weight-roam2 | C19: 0.95 lb (0.43 kg) | D19: 0.95 lb (0.43 kg) | E19: 0.95 lb (0.43 kg) | F19: 0,43 kg | G19: 0,43 kg | H19: 0,43 kg | I19: 0,43 kg | J19: 0,43 kg | K19: 0,43 kg | L19: 0,43 kg (0,95 lb) | M19: 0,43 kg (0,95 lb) | N19: 0,43 kg (0,95 lb) | O19: 0.43 kg | P19: 0.43 kg (0.95 lb) | Q19: 0,43 kg | R19: 0,43 kg | S19: 0,43 kg (0,95 lb) | T19: 0,43 kg | U19: 0.43 kg | V19: 0.43 kg | W19: 0.95 lb (0.43 kg) | X19: 0.43千克（0.95磅） | Y19: 0,95 libry (0,43 kg) | Z19: 0,43 kg | AA19: 0,43 kg | AB19: 0,43 kg | AC19: 0,43 kg | AD19: 0,43 kg (0,95 lb)
A20: fet-feature-weight-duke | C20: 11.11 oz (315 g) | D20: 11.11 oz (315 g) | E20: 11.11 oz (315 g) | F20: 315 g | G20: 315 g | H20: 315 g | I20: 315 g | J20: 315 g | K20: 315 g | L20: 315 g (11,11 oz) | M20: 315 g (11,11 oz) | N20: 315 g (11,11 oz) | O20: 315 g | P20: 315 g (11.11 oz) | Q20: 315 g | R20: 315 g | S20: 315 g (11,11 oz) | T20: 315 g | U20: 315 g | V20: 315 g | W20: 11.11 oz (315 g) | X20: 315克（11.11盎司） | Y20: 11,11 libry (315 g) | Z20: 315 g | AA20: 315 g | AB20: 315 g | AC20: 315 g | AD20: 315 g (11,11 oz)
A21: fet-feature-weight-amp | B21: Learn More / Details & Dimensions / Amp | C21: 4.63 lbs (2.1 kg) | D21: 4.63 lbs (2.1 kg) | E21: 4.63 lbs (2.1 kg) | F21: 2.1 kg | G21: 2.1 kg | H21: 2.1 kg | I21: 2,1 kg | J21: 2,1 kg | K21: 2,1 kg | L21: 2.1 kg (4,63 lb) | M21: 2.1 kg (4,63 lb) | N21: 2.1 kg (4,63 lb) | O21: 2.1 kg | P21: 2.1 kg (4.63 lb) | Q21: 2.1 kg | R21: 2.1 kg | S21: 2.1 kg (4.63 lb) | T21: 2.1 kg | U21: 2.1 kg | V21: 2.1 kg | W21: 4.63 lbs (2.1 kg) | X21: 2.1千克（4.63磅） | Y21: 4,63 libry (2.1 kg) | Z21: 2.1 kg | AA21: 2.1 kg | AB21: 2.1 kg | AC21: 2,1 kg | AD21: 2.1 kg (4.63 lb)
A22: fet-name-arc | B22: Learn More / Compare & Features | C22: Arc | D22: Arc | E22: Arc | F22: Arc | G22: Arc | H22: Arc | I22: Sonos Arc | J22: Sonos Arc | K22: Sonos Arc | L22: Arc | M22: Arc | N22: Arc | O22: Sonos Arc | P22: Arc | Q22: Arc | R22: Arc | S22: Arc | T22: Arc | U22: Arc | V22: Arc | W22: Arc | X22: Arc | Y22: Arc | Z22: Arc | AA22: Arc | AB22: Arc | AC22: Sonos Arc | AD22: Arc
A23: fet-name-beam | B23: Learn More / Compare & Features | C23: Beam | D23: Beam | E23: Beam | F23: Beam | G23: Beam | H23: Beam | I23: Sonos Beam | J23: Sonos Beam | K23: Sonos Beam | L23: Beam | M23: Beam | N23: Beam | O23: Sonos Beam | P23: Beam | Q23: Beam | R23: Beam | S23: Beam | T23: Beam | U23: Beam | V23: Beam | W23: Beam | X23: Beam | Y23: Beam | Z23: Beam | AA23: Beam | AB23: Beam | AC23: Sonos Beam | AD23: Beam
A24: fet-name-ray | B24: Learn More / Compare & Features | C24: Ray | D24: Ray | E24: Ray | F24: Ray | G24: Ray | H24: Ray | I24: Sonos Ray | J24: Sonos Ray | K24: Sonos Ray | L24: Ray | M24: Ray | N24: Ray | O24: Sonos Ray | P24: Ray | Q24: Ray | R24: Ray | S24: Ray | T24: Ray | U24: Ray | V24: Ray | W24: Ray | X24: Ray | Y24: Ray | Z24: Ray | AA24: Ray | AB24: Ray | AC24: Sonos Ray | AD24: Ray
A25: fet-name-sub | B25: Learn More / Compare & Features | C25: Sub | D25: Sub | E25: Sub | F25: Sub | G25: Sub | H25: Sub | I25: Sonos Sub | J25: Sonos Sub | K25: Sonos Sub | L25: Sub | M25: Sub | N25: Sub | O25: Sonos Sub | P25: Sub | Q25: Sub | R25: Sub | S25: Sub | T25: Sub | U25: Sub | V25: Sub | W25: Sub | X25: Sub | Y25: Sub | Z25: Sub | AA25: Sub | AB25: Sub | AC25: Sonos Sub | AD25: Sub
A26: fet-name-gravity | B26: Learn More / Compare & Features | C26: Sub Mini | D26: Sub Mini | E26: Sub Mini | F26: Sub Mini | G26: Sub Mini | H26: Sub Mini | I26: Sonos Sub Mini | J26: Sonos Sub Mini | K26: Sonos Sub Mini | L26: Sub Mini | M26: Sub Mini | N26: Sub Mini | O26: Sonos Sub Mini | P26: Sub Mini | Q26: Sub Mini | R26: Sub Mini | S26: Sub Mini | T26: Sub Mini | U26: Sub Mini | V26: Sub Mini | W26: Sub Mini | X26: Sub Mini | Y26: Sub Mini | Z26: Sub Mini | AA26: Sub Mini | AB26: Sub Mini | AC26: Sonos Sub Mini | AD26: Sub Mini
A27: fet-name-optimo1 | B27: Learn More / Compare & Features | C27: Era 100 | D27: Era 100 | E27: Era 100 | F27: Era 100 | G27: Era 100 | H27: Era 100 | I27: Sonos Era 100 | J27: Sonos Era 100 | K27: Sonos Era 100 | L27: Era 100 | M27: Era 100 | N27: Era 100 | O27: Sonos Era 100 | P27: Era 100 | Q27: Era 100 | R27: Era 100 | S27: Era 100 | T27: Era 100 | U27: Era 100 | V27: Era 100 | W27: Era 100 | X27: Era 100 | Y27: Era 100 | Z27: Era 100 | AA27: Era 100 | AB27: Era 100 | AC27: Sonos Era 100 | AD27: Era 100
A28: fet-name-optimo2 | B28: Learn More / Compare & Features | C28: Era 300 | D28: Era 300 | E28: Era 300 | F28: Era 300 | G28: Era 300 | H28: Era 300 | I28: Sonos Era 300 | J28: Sonos Era 300 | K28: Sonos Era 300 | L28: Era 300 | M28: Era 300 | N28: Era 300 | O28: Sonos Era 300 | P28: Era 300 | Q28: Era 300 | R28: Era 300 | S28: Era 300 | T28: Era 300 | U28: Era 300 | V28: Era 300 | W28: Era 300 | X28: Era 300 | Y28: Era 300 | Z28: Era 300 | AA28: Era 300 | AB28: Era 300 | AC28: Sonos Era 300 | AD28: Era 300
A29: fet-name-five | B29: Learn More / Compare & Features | C29: Five | D29: Five | E29: Five | F29: Five | G29: Five | H29: Five | I29: Sonos Five | J29: Sonos Five | K29: Sonos Five | L29: Five | M29: Five | N29: Five | O29: Sonos Five | P29: Five | Q29: Five | R29: Five | S29: Five | T29: Five | U29: Five | V29: Five | W29: Five | X29: Five | Y29: Five | Z29: Five | AA29: Five | AB29: Five | AC29: Sonos Five | AD29: Five
A30: fet-name-roam | B30: Learn More / Compare & Features | C30: Roam | D30: Roam | E30: Roam | F30: Roam | G30: Roam | H30: Roam | I30: Sonos Roam | J30: Sonos Roam | K30: Sonos Roam | L30: Roam | M30: Roam | N30: Roam | O30: Sonos Roam | P30: Roam | Q30: Roam | R30: Roam | S30: Roam | T30: Roam | U30: Roam | V30: Roam | W30: Roam | X30: Roam | Y30: Roam | Z30: Roam | AA30: Roam | AB30: Roam | AC30: Sonos Roam | AD30: Roam
A31: fet-name-roam2 | C31: Roam 2 | D31: Roam 2 | E31: Roam 2 | F31: Roam 2 | G31: Roam 2 | H31: Roam 2 | I31: Sonos Roam 2 | J31: Sonos Roam 2 | K31: Sonos Roam 2 | L31: Roam 2 | M31: Roam 2 | N31: Roam 2 | O31: Sonos Roam 2 | P31: Roam 2 | Q31: Roam 2 | R31: Roam 2 | S31: Roam 2 | T31: Roam 2 | U31: Roam 2 | V31: Roam 2 | W31: Roam 2 | X31: Roam 2 | Y31: Roam 2 | Z31: Roam 2 | AA31: Roam 2 | AB31: Roam 2 | AC31: Sonos Roam 2 | AD31: Roam 2
A32: fet-name-roamsl | B32: Learn More / Compare & Features | C32: Roam SL | D32: Roam SL | E32: Roam SL | F32: Roam SL | G32: Roam SL | H32: Roam SL | I32: Sonos Roam SL | J32: Sonos Roam SL | K32: Sonos Roam SL | L32: Roam SL | M32: Roam SL | N32: Roam SL | O32: Sonos Roam SL | P32: Roam SL | Q32: Roam SL | R32: Roam SL | S32: Roam SL | T32: Roam SL | U32: Roam SL | V32: Roam SL | W32: Roam SL | X32: Roam SL | Y32: Roam SL | Z32: Roam SL | AA32: Roam SL | AB32: Roam SL | AC32: Sonos Roam SL | AD32: Roam SL
A33: fet-name-duke | C33: Sonos Ace | D33: Sonos Ace | E33: Sonos Ace | F33: Sonos Ace | G33: Sonos Ace | H33: Sonos Ace | I33: Sonos Ace | J33: Sonos Ace | K33: Sonos Ace | L33: Sonos Ace | M33: Sonos Ace | N33: Sonos Ace | O33: Sonos Ace | P33: Sonos Ace | Q33: Sonos Ace | R33: Sonos Ace | S33: Sonos Ace | T33: Sonos Ace | U33: Sonos Ace | V33: Sonos Ace | W33: Sonos Ace | X33: Sonos Ace | Y33: Sonos Ace | Z33: Sonos Ace | AA33: Sonos Ace | AB33: Sonos Ace | AC33: Sonos Ace | AD33: Sonos Ace
A34: fet-name-move | B34: Learn More / Compare & Features | C34: Move | D34: Move | E34: Move | F34: Move | G34: Move | H34: Move | I34: Sonos Move | J34: Sonos Move | K34: Sonos Move | L34: Move | M34: Move | N34: Move | O34: Sonos Move | P34: Move | Q34: Move | R34: Move | S34: Move | T34: Move | U34: Move | V34: Move | W34: Move | X34: Move | Y34: Move | Z34: Move | AA34: Move | AB34: Move | AC34: Sonos Move | AD34: Move
A35: fet-name-prima | B35: Learn More / Compare & Features | C35: Move 2 | D35: Move 2 | E35: Move 2 | F35: Move 2 | G35: Move 2 | H35: Move 2 | I35: Sonos Move 2 | J35: Sonos Move 2 | K35: Sonos Move 2 | L35: Move 2 | M35: Move 2 | N35: Move 2 | O35: Sonos Move 2 | P35: Move 2 | Q35: Move 2 | R35: Move 2 | S35: Move 2 | T35: Move 2 | U35: Move 2 | V35: Move 2 | W35: Move 2 | X35: Move 2 | Y35: Move 2 | Z35: Move 2 | AA35: Move 2 | AB35: Move 2 | AC35: Sonos Move 2 | AD35: Move 2
A36: fet-name-amp | C36: Amp | D36: Amp | E36: Amp | F36: Amp | G36: Amp | H36: Amp | I36: Sonos Amp | J36: Sonos Amp | K36: Sonos Amp | L36: Amp | M36: Amp | N36: Amp | O36: Sonos Amp | P36: Amp | Q36: Amp | R36: Amp | S36: Amp | T36: Amp | U36: Amp | V36: Amp | W36: Amp | X36: Amp | Y36: Amp | Z36: Amp | AA36: Amp | AB36: Amp | AC36: Sonos Amp | AD36: Amp
A37: fet-badge-dolby-atmos | B37: Lean More / Icons under descritpion | C37: Dolby Atmos | D37: Dolby Atmos | E37: Dolby Atmos | F37: Dolby Atmos | G37: Dolby Atmos | H37: Dolby Atmos | I37: Dolby Atmos | J37: Dolby Atmos | K37: Dolby Atmos | L37: Dolby Atmos | M37: Dolby Atmos | N37: Dolby Atmos | O37: Dolby Atmos（ドルビーアトモス） | P37: Dolby Atmos | Q37: Dolby Atmos | R37: Dolby Atmos | S37: Dolby Atmos | T37: Dolby Atmos | U37: Dolby Atmos | V37: Dolby Atmos | W37: Dolby Atmos | X37: 杜比全景声 | Y37: Dolby Atmos | Z37: Dolby Atmos | AA37: Dolby Atmos | AB37: Dolby Atmos | AC37: Dolby Atmos | AD37: Dolby Atmos
A38: fet-badge-dolby-head-tracking | C38: Dolby head tracking | D38: Dolby head tracking | E38: Dolby head tracking | F38: Dynamisk hovedsporing | G38: Dolby Head Tracking | H38: Dolby Head Tracking | I38: Suivi dynamique des mouvements de la tête | J38: Suivi dynamique des mouvements de la tête | K38: Suivi dynamique des mouvements de la tête | L38: Suivi dynamique de la tête | M38: Rilevamento dinamico della posizione della testa | N38: Rilevamento dinamico della posizione della testa | O38: Dolbyヘッドトラッキング | P38: Rastreo de cabeza Dolby | Q38: Dolby Head Tracking | R38: Dynamisk hodesporing | S38: Seguimiento de la cabeza Dolby | T38: Dynamisk huvudspårning | U38: Dolby head tracking | V38: Dolby head tracking | W38: Dolby head tracking | X38: 杜比头部追踪 | Y38: Dynamické sledování hlavy | Z38: Dolbyn pään asennon seuranta | AA38: Dynamiczne śledzenie ruchu głowy | AB38: Dolby Head Tracking | AC38: Suivi dynamique des mouvements de la tête | AD38: Rastreo de cabeza Dolby
A39: fet-badge-spatial-audio-with-dynamic-head-tracking-1 | C39: Spatial audio with dynamic head tracking¹ | D39: Spatial audio with dynamic head tracking¹ | E39: Spatial audio with dynamic head tracking¹ | F39: Rumlig lyd med dynamisk hovedsporing¹ | G39: 3D-Audio mit dynamischem Head Tracking¹ | H39: 3D-Audio mit dynamischem Head Tracking¹ | I39: Audio spatial avec suivi dynamique des mouvements de la tête¹ | J39: Audio spatial avec suivi dynamique des mouvements de la tête¹ | K39: Audio spatial avec suivi dynamique des mouvements de la tête¹ | L39: Audio spatial avec suivi dynamique de la tête¹ | M39: Audio spaziale con rilevamento dinamico della posizione della testa¹ | N39: Audio spaziale con rilevamento dinamico della posizione della testa¹ | O39: 空間オーディオとダイナミックヘッドトラッキング¹ | P39: Audio espacial con seguimiento dinámico de la cabeza¹ | Q39: Ruimtelijke audio met dynamische hoofdtracking | R39: Romtilpasset lyd med dynamisk hodesporing¹ | S39: Audio espacial con seguimiento dinámico de la cabeza¹ | T39: Rymligt ljud med dynamisk huvudspårning¹ | U39: Spatial audio with dynamic head tracking¹ | V39: Spatial audio with dynamic head tracking¹ | W39: Spatial audio with dynamic head tracking¹ | X39: 支持动态头部追踪的空间音频¹ | Y39: Prostorový zvuk s dynamickým sledováním hlavy¹ | Z39: Tilaääni dynaamisella pään asennon seurannalla¹ | AA39: Dźwięk przestrzenny z dynamicznym śledzeniem ruchu głowy¹ | AB39: 3D-Audio mit dynamischem Head Tracking¹ | AC39: Audio spatial avec suivi dynamique des mouvements de la tête¹ | AD39: Audio espacial con seguimiento dinámico de la cabeza1
A40: fet-badge-lossless-audio-2 | C40: Lossless audio² | D40: Lossless audio² | E40: Lossless audio² | F40: Tabsfri lyd² | G40: Verlustfreies Audio² | H40: Verlustfreies Audio² | I40: Contenus audio sans perte² | J40: Contenus audio sans perte² | K40: Contenus audio sans perte² | L40: Audio sans perte² | M40: Audio lossless² | N40: Audio lossless² | O40: ロスレスオーディオ² | P40: Audio lossless² | Q40: Lossless audio² | R40: Tapsfri lyd² | S40: Sonido sin pérdidas² | T40: Losslessljud² | U40: Lossless audio² | V40: Lossless audio² | W40: Lossless audio² | X40: 无损音频² | Y40: Bezztrátový zvuk² | Z40: Häviötön ääni² | AA40: Dźwięk bezstratny² | AB40: Verlustfreies Audio² | AC40: Contenus audio sans perte² | AD40: Audio lossless²
A41: fet-badge-enhanced-call-clarity | C41: Enhanced call clarity | D41: Enhanced call clarity | E41: Enhanced call clarity | F41: Tydeligere opkald | G41: Verbesserte Sprachqualität | H41: Verbesserte Sprachqualität | I41: Un son encore plus clair pour les appels | J41: Un son encore plus clair pour les appels | K41: Un son encore plus clair pour les appels | L41: Clarté accrue des appels | M41: Ottimizzazione della nitidezza delle chiamate | N41: Ottimizzazione della nitidezza delle chiamate | O41: より明瞭な音声 | P41: Nitidez de llamada mejorada | Q41: Duidelijkere telefoongesprekken | R41: Økt anropsklarhet | S41: Mejor calidad de las llamadas | T41: Ökad klarhet för samtal | U41: Enhanced call clarity | V41: Enhanced call clarity | W41: Enhanced call clarity | X41: 增强通话清晰度 | Y41: Zvýšená srozumitelnost hovorů | Z41: Kehittyneempi puhelun selkeys | AA41: Większa wyrazistość połączeń telefonicznych | AB41: Verbesserte Sprachqualität | AC41: Un son encore plus clair pour les appels | AD41: Nitidez de llamada mejorada
A42: badges.wearDetection | C42: Wear detection | D42: Wear detection | E42: Wear detection | F42: Registrering af brug | G42: Trageerkennung | H42: Trageerkennung | I42: Détection d'usure | J42: Détection d'usure | K42: Détection d'usure | L42: Détection lors du port | M42: Rilevamento automatico quando il prodotto viene indossato | N42: Rilevamento automatico quando il prodotto viene indossato | O42: 装着検出 | P42: Detección de desgaste | Q42: Draagdetectie | R42: Bruksdeteksjon | S42: Detección de desgaste | T42: Användningsavkänning | U42: Wear detection | V42: Wear detection | W42: Wear detection | X42: 佩戴检测 | Y42: Detekce nošení | Z42: Kulumisen havaitseminen | AA42: Wykrywanie noszenia | AB42: Trageerkennung | AC42: Détection d'usure | AD42: Detección de desgaste
A43: fet-badge-active-noise-cancellation-capitalized | C43: Active Noise Cancellation | D43: Active Noise Cancellation | E43: Active Noise Cancellation | F43: Aktiv støjreduktion | G43: Aktive Geräuschunterdrückung | H43: Aktive Geräuschunterdrückung | I43: Réduction active du bruit | J43: Réduction active du bruit | K43: Réduction active du bruit | L43: Annulation active des bruits | M43: Cancellazione attiva del rumore | N43: Cancellazione attiva del rumore | O43: ノイズキャンセリング機能 | P43: Cancelación activa de ruido | Q43: Actieve ruisonderdrukking | R43: Aktiv støykansellering | S43: Cancelación activa de ruido | T43: Aktiv brusreducering | U43: Active Noise Cancellation | V43: Active Noise Cancellation | W43: Active Noise Cancellation | X43: 主动消噪 | Y43: Aktivní potlačení hluku | Z43: Aktiivinen melunvaimennus | AA43: Aktywne tłumienie hałasu | AB43: Aktive Geräuschunterdrückung | AC43: Réduction active du bruit | AD43: Cancelación activa de ruido
A44: fet-badge-active-noise-cancellation | C44: Active Noise Cancellation | D44: Active Noise Cancellation | E44: Active Noise Cancellation | F44: Aktiv støjreduktion | G44: Aktive Geräuschunterdrückung | H44: Aktive Geräuschunterdrückung | I44: Réduction active du bruit | J44: Réduction active du bruit | K44: Réduction active du bruit | L44: Annulation active des bruits | M44: Cancellazione attiva del rumore | N44: Cancellazione attiva del rumore | O44: ノイズキャンセリング機能 | P44: Cancelación activa de ruido | Q44: Actieve ruisonderdrukking | R44: Aktiv støykansellering | S44: Cancelación activa de ruido | T44: Aktiv brusreducering | U44: Active Noise Cancellation | V44: Active Noise Cancellation | W44: Active Noise Cancellation | X44: 主动消噪 | Y44: Aktivní potlačení hluku | Z44: Aktiivinen melunvaimennus | AA44: Aktywne tłumienie hałasu | AB44: Aktive Geräuschunterdrückung | AC44: Réduction active du bruit | AD44: Cancelación activa de ruido
A45: fet-badge-aware-mode | C45: Aware mode | D45: Aware mode | E45: Aware mode | F45: Aware mode | G45: Aware Modus | H45: Aware Modus | I45: Mode Aware | J45: Mode Aware | K45: Mode Aware | L45: Mode conscient | M45: Modalità Trasparenza | N45: Modalità Trasparenza | O45: アウェアモード | P45: Modo Ambiente | Q45: Aware-modus | R45: Bevisst modus | S45: Modo Aware | T45: Transparensläge | U45: Aware mode | V45: Aware mode | W45: Aware mode | X45: 感知模式 | Y45: Režim pozornosti | Z45: Valppaustila | AA45: Tryb kontaktu | AB45: Aware Modus | AC45: Mode Aware | AD45: Modo Ambiente
A46: fet-badge-crafted-for-comfort | C46: Crafted for comfort | D46: Crafted for comfort | E46: Crafted for comfort | F46: Designet til komfort | G46: Maximaler Tragekomfort | H46: Maximaler Tragekomfort | I46: Conçu pour un maximum de confort | J46: Conçu pour un maximum de confort | K46: Conçu pour un maximum de confort | L46: Conçu pour le confort | M46: Per la massima comodità | N46: Per la massima comodità | O46: 快適さを求めたデザイン | P46: Diseñados para tu comodidad | Q46: Gemaakt voor comfort | R46: Designet for komfort | S46: Comodidad total | T46: Utformade för bekvämlighet | U46: Crafted for comfort | V46: Crafted for comfort | W46: Crafted for comfort | X46: 精心打造舒适体验 | Y46: Vytvořeno pro pohodlí | Z46: Muotoiltu mukavaksi | AA46: Stworzony z myślą o wygodzie | AB46: Maximaler Tragekomfort | AC46: Conçu pour un maximum de confort | AD46: Diseñados para tu comodidad
A47: fet-badge-badges-dynamic-head-tracking | C47: Dynamic head tracking | D47: Dynamic head tracking | E47: Dynamic head tracking | F47: Dynamisk hovedsporing | G47: Dynamisches Head Tracking | H47: Dynamisches Head Tracking | I47: Suivi dynamique des mouvements de la tête | J47: Suivi dynamique des mouvements de la tête | K47: Suivi dynamique des mouvements de la tête | L47: Suivi dynamique de la tête | M47: Rilevamento dinamico della posizione della testa | N47: Rilevamento dinamico della posizione della testa | O47: ダイナミックヘッドトラッキング | P47: Seguimiento dinámico de la cabeza | Q47: Dynamische hoofdtracking | R47: Dynamisk hodesporing | S47: Seguimiento dinámico de la cabeza | T47: Dynamisk huvudspårning | U47: Dynamic head tracking | V47: Dynamic head tracking | W47: Dynamic head tracking | X47: 动态头部追踪 | Y47: Dynamické sledování hlavy | Z47: Dynaaminen pään asennon seuranta | AA47: Dynamiczne śledzenie ruchu głowy | AB47: Dynamisches Head Tracking | AC47: Suivi dynamique des mouvements de la tête | AD47: Seguimiento dinámico de la cabeza
A48: fet-badge-custom-designed-40mm-dynamic-drivers | B48: Lean More / Compare / Audio & Features / Audio | C48: Custom-designed 40mm dynamic drivers | D48: Custom-designed 40 mm dynamic drivers | E48: Custom-designed 40 mm dynamic drivers | F48: Specialudviklede dynamiske drivere på 40 mm | G48: Spezielle dynamische 40-mm-Treiber | H48: Spezielle dynamische 40-mm-Treiber | I48: Haut-parleurs dynamiques de 40 mm conçus sur mesure | J48: Haut-parleurs dynamiques de 40 mm conçus sur mesure | K48: Haut-parleurs dynamiques de 40 mm conçus sur mesure | L48: Haut-parleurs dynamiques de 40 mm conçus sur mesure | M48: Driver dinamici da 40 mm progettati su misura | N48: Driver dinamici da 40 mm progettati su misura | O48: カスタム設計の40mmダイナミックドライバー | P48: Diafragmas dinámicos de diseño exclusivo de 40 mm | Q48: Speciaal ontworpen 40 mm dynamische drivers | R48: Spesialkonstruerte 40 mm dynamiske drivere | S48: Altavoces dinámicos de 40 mm diseñados a medida | T48: Specialdesignade, dynamiska högtalarelement på 40 mm | U48: Custom-designed 40 mm dynamic drivers | V48: Custom-designed 40 mm dynamic drivers | W48: Custom-designed 40 mm dynamic drivers | X48: 定制设计40毫米动态驱动器 | Y48: Na míru vytvořené 40mm dynamické ovladače | Z48: Kustomoidut 40 mm:n dynaamiset ohjaimet | AA48: Specjalnie zaprojektowane przetworniki dynamiczne o średnicy 40 mm | AB48: Spezielle dynamische 40-mm-Treiber | AC48: Haut-parleurs dynamiques de 40 mm conçus sur mesure | AD48: Diafragmas dinámicos de diseño exclusivo de 40 mm
A49: fet-badge-adjustable-eq | B49: Lean More / Tech Specs / Audio | C49: Adjustable EQ | D49: Adjustable EQ | E49: Adjustable EQ | F49: Justerbar equalizer | G49: Verstellbarer Equalizer | H49: Verstellbarer Equalizer | I49: Égalisation réglable | J49: Égalisation réglable | K49: Égalisation réglable | L49: EQ ajustable | M49: Equalizzazione regolabile | N49: Equalizzazione regolabile | O49: 調整可能なイコライザー | P49: Ecualización ajustable | Q49: Aanpasbare EQ | R49: Justerbar EQ | S49: Ecualización regulable | T49: Justerbar EQ | U49: Adjustable EQ | V49: Adjustable EQ | W49: Adjustable EQ | X49: 可调整EQ | Y49: Nastavitelný ekvalizér | Z49: Säädettävä äänentasaus | AA49: Korektor graficzny (EQ) z możliwością regulacji | AB49: Verstellbarer Equalizer | AC49: Égalisation réglable | AD49: Ecualización ajustable
A50: fet-badge-voice-enabled | B50: Lean More / Icons under descritpion | C50: Voice enabled | D50: Voice-enabled | E50: Voice-enabled | F50: Indbygget stemmestyring | G50: Sprachsteuerung | H50: Sprachsteuerung | I50: Contrôle vocal | J50: Contrôle vocal | K50: Contrôle vocal | L50: Compatible avec le contrôle vocal | M50: Controllo vocale | N50: Controllo vocale | O50: 音声操作対応 | P50: Control por voz | Q50: Met spraakbediening | R50: Stemmestyring er aktivert | S50: Control por voz | T50: Redo för röststyrning | U50: Voice-enabled | V50: Voice-enabled | W50: Voice-enabled | X50: 支持语音功能 | Y50: Aktivace hlasem | Z50: Puheohjaus | AA50: Funkcja sterowania głosowego | AB50: Sprachsteuerung | AC50: Contrôle vocal | AD50: Control por voz
A51: fet-badge-wifi | B51: Lean More / Icons under descritpion | C51: WiFi | D51: WiFi | E51: WiFi | F51: WiFi | G51: WLAN | H51: WLAN | I51: Wi-Fi | J51: Wi-Fi | K51: Wi-Fi | L51: Wi-Fi | M51: Wi-Fi | N51: Wi-Fi | O51: WiFi | P51: WiFi | Q51: Wifi | R51: Wi-Fi | S51: Wi-Fi | T51: Wi-Fi | U51: WiFi | V51: WiFi | W51: WiFi | X51: Wi-Fi | Y51: Wi-Fi | Z51: WiFi | AA51: Wi-Fi | AB51: WLAN | AC51: Wi-Fi | AD51: WiFi
A52: fet-badge-trueplay-tm | B52: Lean More / Icons under descritpion | C52: Trueplay™ | D52: Trueplay™ | E52: Trueplay™ | F52: Trueplay™ | G52: Trueplay™ | H52: Trueplay™ | I52: Trueplay™ | J52: Trueplay™ | K52: Trueplay™ | L52: Trueplay™ | M52: Trueplay™ | N52: Trueplay™ | O52: Trueplay™ | P52: Trueplay™ | Q52: Trueplay™ | R52: Trueplay™ | S52: Trueplay™ | T52: Trueplay™ | U52: Trueplay™ | V52: Trueplay™ | W52: Trueplay™ | X52: Trueplay™调音 | Y52: Trueplay™ | Z52: Trueplay™ | AA52: Trueplay™ | AB52: Trueplay™ | AC52: Trueplay™ | AD52: Trueplay™
A53: fet-badge-tv-remote-sync | B53: Lean More / Icons under descritpion | C53: TV remote sync | D53: TV remote sync | E53: TV remote sync | F53: Synkronisering med TV-remote | G53: Synchronisierung mit der TV-Fernbedienung | H53: Synchronisierung mit der TV-Fernbedienung | I53: Synchronisation avec la télécommande de votre TV | J53: Synchronisation avec la télécommande de votre TV | K53: Synchronisation avec la télécommande de votre TV | L53: Synchronisation de la télécommande du téléviseur | M53: Sincronizzazione del telecomando della TV | N53: Sincronizzazione del telecomando della TV | O53: テレビのリモコンと同期 | P53: Sincronización con el control de la TV | Q53: Afstandsbediening-synchronisatie | R53: Synkronisering av fjernkontroll til TV | S53: Sincronización con el mando de la tele | T53: Synkronisering med fjärrkontrollen till tv:n | U53: TV remote sync | V53: TV remote sync | W53: TV remote sync | X53: 电视遥控器同步 | Y53: Synchronní s dálkovým ovladačem televize | Z53: TV-kaukosäätimen synkronointi | AA53: Synchronizacja pilota telewizyjnego | AB53: Synchronisierung mit der TV-Fernbedienung | AC53: Synchronisation avec la télécommande de votre TV | AD53: Sincronización con el control de la TV
A54: fet-badge-hdmi-earc | B54: Lean More / Icons under descritpion | C54: HDMI eARC | D54: HDMI eARC | E54: HDMI eARC | F54: HDMI eARC | G54: HDMI eARC | H54: HDMI eARC | I54: HDMI eARC | J54: HDMI eARC | K54: HDMI eARC | L54: HDMI eARC | M54: HDMI eARC | N54: HDMI eARC | O54: HDMI eARC | P54: HDMI eARC | Q54: HDMI eARC | R54: HDMI eARC | S54: HDMI eARC | T54: HDMI eARC | U54: HDMI eARC | V54: HDMI eARC | W54: HDMI eARC | X54: HDMI eARC | Y54: HDMI eARC | Z54: HDMI eARC | AA54: HDMI eARC | AB54: HDMI eARC | AC54: HDMI eARC | AD54: HDMI eARC
A55: fet-badge-hdmi-arc | B55: Lean More / Icons under descritpion | C55: HDMI ARC | D55: HDMI ARC | E55: HDMI ARC | F55: HDMI ARC | G55: HDMI ARC | H55: HDMI ARC | I55: HDMI ARC | J55: HDMI ARC | K55: HDMI ARC | L55: HDMI ARC | M55: HDMI ARC | N55: HDMI ARC | O55: HDMI ARC | P55: HDMI ARC | Q55: HDMI ARC | R55: HDMI ARC | S55: HDMI ARC | T55: HDMI ARC | U55: HDMI ARC | V55: HDMI ARC | W55: HDMI ARC | X55: HDMI ARC | Y55: HDMI ARC | Z55: HDMI ARC | AA55: HDMI ARC | AB55: HDMI ARC | AC55: HDMI ARC | AD55: HDMI ARC
A56: fet-badge-apple-airplay2 | B56: Lean More / Icons under descritpion | C56: Apple AirPlay 2 | D56: Apple AirPlay 2 | E56: Apple AirPlay 2 | F56: Apple AirPlay 2 | G56: Apple AirPlay 2 | H56: Apple AirPlay 2 | I56: Apple AirPlay 2 | J56: Apple AirPlay 2 | K56: Apple AirPlay 2 | L56: AirPlay 2 d’Apple | M56: Apple AirPlay 2 | N56: Apple AirPlay 2 | O56: Apple AirPlay 2 | P56: Apple AirPlay 2 | Q56: Apple AirPlay 2 | R56: Apple AirPlay 2 | S56: AirPlay 2 de Apple | T56: Apple AirPlay 2 | U56: Apple AirPlay 2 | V56: Apple AirPlay 2 | W56: Apple AirPlay 2 | X56: Apple AirPlay 2 | Y56: Apple AirPlay 2 | Z56: Apple AirPlay 2 | AA56: Apple AirPlay 2 | AB56: Apple AirPlay 2 | AC56: Apple AirPlay 2 | AD56: Apple AirPlay 2
A57: fet-badge-touch-controls | B57: Lean More / Icons under descritpion | C57: Touch controls | D57: Touch controls | E57: Touch controls | F57: Touchbetjening | G57: Touch Steuerung | H57: Touch Steuerung | I57: Commandes tactiles | J57: Commandes tactiles | K57: Commandes tactiles | L57: Commandes tactiles | M57: Controlli touch | N57: Controlli touch | O57: タッチ操作 | P57: Controles táctiles | Q57: Touchtoetsen | R57: Berøringskontroller | S57: Controles táctiles | T57: Touchkontroller | U57: Touch controls | V57: Touch controls | W57: Touch controls | X57: 触摸控件 | Y57: Dotykové ovládací prvky | Z57: Kosketussäätimet | AA57: Sterowanie dotykowe | AB57: Touch Steuerung | AC57: Commandes tactiles | AD57: Controles táctiles
A58: fet-badge-optical | B58: Lean More / Icons under descritpion | C58: Optical | D58: Optical | E58: Optical | F58: Optisk | G58: Optisches Kabel | H58: Optisches Kabel | I58: Optique | J58: Optique | K58: Optique | L58: Optique | M58: Ottico | N58: Ottico | O58: 光デジタルオーディオ | P58: Conexión óptica | Q58: Optisch | R58: Optisk | S58: Óptico | T58: Optisk | U58: Optical | V58: Optical | W58: Optical | X58: 光纤 | Y58: Optický | Z58: Optinen | AA58: Optyczny | AB58: Optisches Kabel | AC58: Optique | AD58: Conexión óptica
A59: fet-badge-dual-orientation | B59: Lean More / Icons under descritpion | C59: Dual orientation | D59: Dual orientation | E59: Dual orientation | F59: To positioner | G59: Duale Ausrichtung | H59: Duale Ausrichtung | I59: Double orientation | J59: Double orientation | K59: Double orientation | L59: Deux orientations | M59: Doppio orientamento | N59: Doppio orientamento | O59: 縦横どちらでも設置可能 | P59: Orientación doble | Q59: Twee standen | R59: Flere plasseringsmuligheter | S59: Dos posiciones | T59: Dubbelriktad | U59: Dual orientation | V59: Dual orientation | W59: Dual orientation | X59: 两种摆放方向 | Y59: Dvojí umístění | Z59: Kaksisuuntainen | AA59: Możliwość ustawienia w dwóch pozycjach | AB59: Duale Ausrichtung | AC59: Double orientation | AD59: Orientación doble
... A67: fet-badge-battery-life-10-plus | B67: Lean More / Icons under descritpion | C67: 10 hour battery life | D67: 10-hour battery life | E67: 10-hour battery life | F67: 10 timers batteritid | G67: 10 Stunden Akkulaufzeit | H67: 10 Stunden Akkulaufzeit | I67: Jusqu'à 10 heures d'autonomie | J67: Jusqu'à 10 heures d'autonomie | K67: Jusqu'à 10 heures d'autonomie | L67: 10 heures d’autonomie | M67: Batteria con un’autonomia di 10 ore | N67: Batteria con un’autonomia di 10 ore | O67: 10時間駆動可能のバッテリー | P67: 10 horas de batería | Q67: 10 uur batterijduur | R67: 10 timers batteritid | S67: 10 horas de autonomía | T67: 10 timmars batteritid | U67: 10-hour battery life | V67: 10-hour battery life | W67: 10-hour battery life | X67: 10小时电池续航时间 | Y67: 10hodinová výdrž baterie | Z67: 10 tunnin akunkesto | AA67: 10 godzin pracy na akumulatorze | AB67: 10 Stunden Akkulaufzeit | AC67: Jusqu'à 10 heures d'autonomie | AD67: 10 horas de batería
A68: fet-badge-battery-life-10-up-to-2 | C68: Battery life up to 10 hours² | D68: Battery life up to 10 hours² | E68: Battery life up to 10 hours² | F68: Op til 10 timers batteritid² | G68: Mindestens 10 Stunden Akkulaufzeit² | H68: Mindestens 10 Stunden Akkulaufzeit² | I68: Jusqu'à 10 heures d'autonomie² | J68: Jusqu'à 10 heures d'autonomie² | K68: Jusqu'à 10 heures d'autonomie² | L68: Jusqu’à 10 heures d’autonomie² | M68: Batteria con un’autonomia fino a 10 ore² | N68: Batteria con un’autonomia fino a 10 ore² | O68: 最長10時間駆動可能のバッテリー² | P68: Hasta 10 horas de batería² | Q68: Tot wel 10 uur batterijduur³ | R68: Batterilevetid opptil 10 timer² | S68: Hasta 10 horas de autonomía² | T68: Upp till 10 timmars batteritid² | U68: Battery life up to 10 hours² | V68: Battery life up to 10 hours² | W68: Battery life up to 10 hours² | X68: 电池续航时间长达10小时² | Y68: Výdrž baterie až 10 hodin² | Z68: Akun kesto jopa 10 tuntia² | AA68: Do 10 godzin pracy na akumulatorze² | AB68: Mindestens 10 Stunden Akkulaufzeit² | AC68: Jusqu'à 10 heures d'autonomie² | AD68: Hasta 10 horas de batería²
A69: fet-badge-water-resistant-ip56 | B69: Lean More / Icons under descritpion | C69: Water resistant (IP56) | D69: Water resistant (IP56) | E69: Water resistant (IP56) | F69: Vandresistent (IP56) | G69: Wasserfest (IP56) | H69: Wasserfest (IP56) | I69: Résistant à l'eau (IP56) | J69: Résistant à l'eau (IP56) | K69: Résistant à l'eau (IP56) | L69: Étanche (IP56) | M69: Resistente all’acqua (IP56) | N69: Resistente all’acqua (IP56) | O69: 耐水設計（IP56） | P69: Resistente al agua (IP56) | Q69: Waterbestendig (IP56) | R69: Vannresistent (IP56) | S69: Resistente al agua (IP56) | T69: Fukttålig (IP56) | U69: Water resistant (IP56) | V69: Water resistant (IP56) | W69: Water resistant (IP56) | X69: 抗水（IP56） | Y69: Voděodolný (IP56) | Z69: Vedenkestävä (IP56) | AA69: Wodoodporny (IP56) | AB69: Wasserfest (IP56) | AC69: Résistant à l'eau (IP56) | AD69: Resistente al agua (IP56)
A70: fet-badge-rapid-charging-4 | C70: Rapid charging⁴ | D70: Rapid charging⁴ | E70: Rapid charging⁴ | F70: Hurtig opladning⁴ | G70: Schnelles Aufladen⁴ | H70: Schnelles Aufladen⁴ | I70: Charge rapide⁴ | J70: Charge rapide⁴ | K70: Charge rapide⁴ | L70: Recharge rapide⁴ | M70: Ricarica veloce⁴ | N70: Ricarica veloce⁴ | O70: 急速充電⁴ | P70: Carga rápida⁴ | Q70: Snel opladen⁴ | R70: Rask lading⁴ | S70: Carga rápida4 | T70: Snabbladdning⁴ | U70: Rapid charging⁴ | V70: Rapid charging⁴ | W70: Rapid charging⁴ | X70: 快速充电⁴ | Y70: Rychlé nabíjení⁴ | Z70: Pikalataus⁴ | AA70: Szybkie ładowanie⁴ | AB70: Schnelles Aufladen⁴ | AC70: Charge rapide⁴ | AD70: Carga rápida⁴
A71: fet-badge-rapid-charging | C71: Rapid charging | D71: Rapid charging | E71: Rapid charging | F71: Hurtig opladning | G71: Schnelles Aufladen | H71: Schnelles Aufladen | I71: Charge rapide | J71: Charge rapide | K71: Charge rapide | L71: Recharge rapide | M71: Ricarica veloce | N71: Ricarica veloce | O71: 急速充電 | P71: Carga rápida | Q71: Snel opladen | R71: Rask lading | S71: Carga rápida | T71: Snabbladdning | U71: Rapid charging | V71: Rapid charging | W71: Rapid charging | X71: 快速充电 | Y71: Rychlé nabíjení | Z71: Pikalataus | AA71: Szybkie ładowanie | AB71: Schnelles Aufladen | AC71: Charge rapide | AD71: Carga rápida
A72: fet-badge-works-with-apple-and-android | C72: Works with Apple and Android | D72: Works with Apple and Android | E72: Works with Apple and Android | F72: Fungerer med Apple og Android | G72: Kompatibel mit Apple und Android | H72: Kompatibel mit Apple und Android | I72: Fonctionne avec Apple et Android | J72: Fonctionne avec Apple et Android | K72: Fonctionne avec Apple et Android | L72: Compatibles avec les appareils Apple et Android | M72: Compatibile con Apple e Android | N72: Compatibile con Apple e Android | O72: AppleとAndroidに対応 | P72: Funciona con Apple y Android | Q72: Werkt met Apple en Android | R72: Fungerer med Apple og Android | S72: Compatible con Apple y Android | T72: Fungerar med Apple och Android | U72: Works with Apple and Android | V72: Works with Apple and Android | W72: Works with Apple and Android | X72: 支持Apple和Android | Y72: Funguje se systémy Apple a Android | Z72: Yhteensopiva Apple- ja Android-laitteiden kanssa | AA72: Współpracuje z systemami Apple i Android | AB72: Kompatibel mit Apple und Android | AC72: Fonctionne avec Apple et Android | AD72: Funciona con Apple y Android
A73: fet-badge-drop-resistant | B73: Lean More / Icons under descritpion | C73: Drop resistant | D73: Drop resistant | E73: Drop resistant | F73: Tåler fald | G73: Sturzfest | H73: Sturzfest | I73: Résistant aux chocs | J73: Résistant aux chocs | K73: Résistant aux chocs | L73: Résistant aux chutes | M73: Resistente alle cadute | N73: Resistente alle cadute | O73: 耐落下性 | P73: Resistente a caídas | Q73: Valbestendig | R73: Tåler fall | S73: Resistente a los impactos | T73: Stöttålig | U73: Drop resistant | V73: Drop resistant | W73: Drop resistant | X73: 抗跌落 | Y73: Nárazuvzdorný | Z73: Pudotuksenkestävä | AA73: Odporny na upadki | AB73: Sturzfest | AC73: Résistant aux chocs | AD73: Resistente a caídas
A74: fet-badge-automatic-trueplay | B74: Lean More / Icons under descritpion | C74: Automatic Trueplay | D74: Automatic Trueplay | E74: Automatic Trueplay | F74: Automatisk Trueplay | G74: Automatisches Trueplay | H74: Automatisches Trueplay | I74: Calibrage Trueplay automatique | J74: Calibrage Trueplay automatique | K74: Calibrage Trueplay automatique | L74: Réglage Trueplay automatique | M74: Ottimizzazione automatica Trueplay | N74: Ottimizzazione automatica Trueplay | O74: オートマティックTrueplay | P74: Trueplay automático | Q74: Automatische Trueplay | R74: Automatisk Trueplay | S74: Ajuste Trueplay automático | T74: Automatisk Trueplay | U74: Automatic Trueplay | V74: Automatic Trueplay | W74: Automatic Trueplay | X74: 自适应Trueplay调音 | Y74: Automatické ladění Trueplay | Z74: Automaattinen Trueplay | AA74: Automatyczna regulacja Trueplay | AB74: Automatisches Trueplay | AC74: Calibrage Trueplay automatique | AD74: Trueplay automático
A75: fet-badge-automatic-trueplay-tm | B75: Lean More / Icons under descritpion | C75: Automatic Trueplay™ | D75: Automatic Trueplay™ | E75: Automatic Trueplay™ | F75: Automatisk Trueplay™ | G75: Automatisches Trueplay™ | H75: Automatisches Trueplay™ | I75: Trueplay™ automatique | J75: Trueplay™ automatique | K75: Trueplay™ automatique | L75: Réglage Trueplay™ automatique | M75: Ottimizzazione automatica Trueplay™ | N75: Ottimizzazione automatica Trueplay™ | O75: オートマティックTrueplay™ | P75: Trueplay™ automático | Q75: Automatische Trueplay™ | R75: Automatisk Trueplay™ | S75: Trueplay™ automático | T75: Automatisk Trueplay™ | U75: Automatic Trueplay™ | V75: Automatic Trueplay™ | W75: Automatic Trueplay™ | X75: 自适应Trueplay™调音 | Y75: Automatické ladění Trueplay™ | Z75: Automaattinen Trueplay™ | AA75: Automatyczna regulacja Trueplay™ | AB75: Automatisches Trueplay™ | AC75: Trueplay™ automatique | AD75: Trueplay™ automático
A76: fet-badge-automatic-trueplay-tm3 | C76: Automatic Trueplay™³ | D76: Automatic Trueplay™³ | E76: Automatic Trueplay™³ | F76: Automatisk Trueplay™³ | G76: Automatisches Trueplay™³ | H76: Automatisches Trueplay™³ | I76: Trueplay™ automatique³ | J76: Trueplay™ automatique³ | K76: Trueplay™ automatique³ | L76: Réglage Trueplay™ automatique³ | M76: Ottimizzazione automatica Trueplay™³ | N76: Ottimizzazione automatica Trueplay™³ | O76: オートマティックTrueplay™³ | P76: Trueplay™ automático³ | Q76: Automatische Trueplay™³ | R76: Automatisk Trueplay™³ | S76: Trueplay™ automático³ | T76: Automatisk Trueplay™³ | U76: Automatic Trueplay™³ | V76: Automatic Trueplay™³ | W76: Automatic Trueplay™³ | X76: 自适应Trueplay™调音³ | Y76: Automatické ladění Trueplay™³ | Z76: Automaattinen Trueplay™³ | AA76: Automatyczna regulacja Trueplay™³ | AB76: Automatisches Trueplay™³ | AC76: Trueplay™ automatique³ | AD76: Trueplay™ automático³
A77: fet-feature-true-play | B77: Lean More / Tech Specs / Audio | C77: Trueplay | D77: Trueplay | E77: Trueplay | F77: Trueplay | G77: Trueplay | H77: Trueplay | I77: Trueplay | J77: Trueplay | K77: Trueplay | L77: Trueplay | M77: Trueplay | N77: Trueplay | O77: Trueplay | P77: Trueplay | Q77: Trueplay | R77: Trueplay | S77: Trueplay | T77: Trueplay | U77: Trueplay | V77: Trueplay | W77: Trueplay | X77: Trueplay | Y77: Trueplay | Z77: Trueplay | AA77: Trueplay | AB77: Trueplay | AC77: Trueplay | AD77: Trueplay
A78: fet-badge-waterproof-ip67 | B78: Lean More / Icons under descritpion | C78: Waterproof (IP67) | D78: Waterproof (IP67) | E78: Waterproof (IP67) | F78: Vandtæt (IP67) | G78: Wasserdicht (IP67) | H78: Wasserdicht (IP67) | I78: Étanche (IP67) | J78: Étanche (IP67) | K78: Étanche (IP67) | L78: Étanche (IP67) | M78: Impermeabile (IP67) | N78: Impermeabile (IP67) | O78: 防水設計（IP67） | P78: A prueba de agua (IP67) | Q78: Waterdicht (IP67) | R78: Vanntett (IP67) | S78: Impermeable (IP67) | T78: Vattentät (IP67) | U78: Waterproof (IP67) | V78: Waterproof (IP67) | W78: Waterproof (IP67) | X78: 防水（IP67） | Y78: Vodotěsný (IP67) | Z78: Vedenpitävä (IP67) | AA78: Wodoodporny (IP67) | AB78: Wasserdicht (IP67) | AC78: Étanche (IP67) | AD78: A prueba de agua (IP67)
A79: fet-badge-waterproof-ip67-1 | C79: Waterproof (IP67)¹ | D79: Waterproof (IP67)¹ | E79: Waterproof (IP67)¹ | F79: Vandtæt (IP67)¹ | G79: Wasserdicht (IP67)¹ | H79: Wasserdicht (IP67)¹ | I79: Étanche (IP67)¹ | J79: Étanche (IP67)¹ | K79: Étanche (IP67)¹ | L79: Étanche (IP67)¹ | M79: Impermeabile (IP67)¹ | N79: Impermeabile (IP67)¹ | O79: 防水設計（IP67）¹ | P79: A prueba de agua (IP67)¹ | Q79: Waterdicht (IP67)¹ | R79: Vanntett (IP67)¹ | S79: Impermeable (IP67)¹ | T79: Vattentät (IP67)¹ | U79: Waterproof (IP67)¹ | V79: Waterproof (IP67)¹ | W79: Waterproof (IP67)¹ | X79: 防水（IP67）¹ | Y79: Vodotěsný (IP67)¹ | Z79: Vedenpitävä (IP67)¹ | AA79: Wodoodporny (IP67)¹ | AB79: Wasserdicht (IP67)¹ | AC79: Étanche (IP67)¹ | AD79: A prueba de agua (IP67)¹
A80: fet-badge-button-controls | B80: Lean More / Icons under descritpion | C80: Button controls | D80: Button controls | E80: Button controls | F80: Knapbetjening | G80: Tastensteuerungen | H80: Tastensteuerungen | I80: Commandes physiques | J80: Commandes physiques | K80: Commandes physiques | L80: Boutons de commande | M80: Pulsanti | N80: Pulsanti | O80: ボタン操作 | P80: Botones de control | Q80: Knopbediening | R80: Knappekontroller | S80: Botones de control | T80: Kontrollknappar | U80: Button controls | V80: Button controls | W80: Button controls | X80: 按钮控件 | Y80: Tlačítkové ovládací prvky | Z80: Painikesäädöt | AA80: Sterowanie za pomocą przycisków | AB80: Tastensteuerungen | AC80: Commandes physiques | AD80: Botones de control
A81: fet-badge-ethernet | B81: Lean More / Icons under descritpion | C81: Ethernet | D81: Ethernet | E81: Ethernet | F81: Ethernet | G81: Ethernet | H81: Ethernet | I81: Ethernet | J81: Ethernet | K81: Ethernet | L81: Ethernet | M81: Ethernet | N81: Ethernet | O81: イーサネット | P81: Ethernet | Q81: Ethernet | R81: Ethernet | S81: Ethernet | T81: Ethernet | U81: Ethernet | V81: Ethernet | W81: Ethernet | X81: 以太网 | Y81: Ethernet | Z81: Ethernet | AA81: Ethernet | AB81: Ethernet | AC81: Ethernet | AD81: Ethernet
A82: fet-badge-usbc | B82: Lean More / Icons under descritpion | C82: USB-C | D82: USB-C | E82: USB-C | F82: USB-C | G82: USB-C | H82: USB-C | I82: USB-C | J82: USB-C | K82: USB-C | L82: USB-C | M82: Porta USB-C | N82: Porta USB-C | O82: USB-C | P82: USB-C | Q82: USB-C | R82: USB-C | S82: USB-C | T82: USB-C | U82: USB-C | V82: USB-C | W82: USB-C | X82: USB-C | Y82: USB-C | Z82: USB-C | AA82: USB-C | AB82: USB-C | AC82: USB-C | AD82: USB-C
A83: fet-badge-usbc-port | C83: USB-C Port | D83: USB-C Port | E83: USB-C Port | F83: USB-C-port | G83: USB-C-Port | H83: USB-C-Port | I83: Port USB-C | J83: Port USB-C | K83: Port USB-C | L83: Port USB-C | M83: Porta USB-C | N83: Porta USB-C | O83: USB-Cポート | P83: Puerto USB-C | Q83: USB-C-poort | R83: USB-C-port | S83: Puerto USB-C | T83: USB-C-port | U83: USB-C Port | V83: USB-C Port | W83: USB-C Port | X83: USB-C端口 | Y83: USB-C port | Z83: USB-C-portti | AA83: Port USB-C | AB83: USB-C-Port | AC83: Port USB-C | AD83: Puerto USB-C
A84: fet-feature-audio | B84: Lean More / Compare / Audio & Features / Audio | C84: Audio | D84: Audio | E84: Audio | F84: Lyd | G84: Audio | H84: Audio | I84: Audio | J84: Audio | K84: Audio | L84: Audio | M84: Audio | N84: Audio | O84: オーディオ | P84: Audio | Q84: Geluid | R84: Lyd | S84: Sonido | T84: Ljud | U84: Audio | V84: Audio | W84: Audio | X84: 音频 | Y84: Audio | Z84: Ääni | AA84: Dźwięk | AB84: Audio | AC84: Audio | AD84: Audio
A85: audio.ports.acoustic | B85: Lean More / Compare / Audio & Features / Audio | C85: Acoustic port | D85: Acoustic port | E85: Acoustic port | F85: Akustisk port | G85: Akustikport | H85: Akustikport | I85: Évent acoustique | J85: Évent acoustique | K85: Évent acoustique | L85: Port acoustique | M85: Porta audio | N85: Porta audio | O85: アコースティックポート | P85: Puerto acústico | Q85: Akoestische poort | R85: Akustisk port | S85: Puerto acústico | T85: Akustisk port | U85: Acoustic port | V85: Acoustic port | W85: Acoustic port | X85: 声学端口 | Y85: Zvukový port | Z85: Akustinen portti | AA85: Wejście akustyczne | AB85: Akustikport | AC85: Évent acoustique | AD85: Puerto acústico
A86: fet-feature-acoustic-ports | B86: Lean More / Compare / Audio & Features / Audio | C86: Acoustic ports | D86: Acoustic ports | E86: Acoustic ports | F86: Akustiske porte | G86: Akustikports | H86: Akustikports | I86: Évents acoustiques | J86: Évents acoustiques | K86: Évents acoustiques | L86: Ports acoustiques | M86: Porte audio | N86: Porte audio | O86: アコースティックポート | P86: Puertos acústicos | Q86: Akoestische poorten | R86: Akustiske porter | S86: Puertos acústicos | T86: Akustiska portar | U86: Acoustic ports | V86: Acoustic ports | W86: Acoustic ports | X86: 声学端口 | Y86: Zvukové porty | Z86: Akustiset portit | AA86: Wejścia akustyczne | AB86: Akustikports | AC86: Évents acoustiques | AD86: Puertos acústicos
A87: audio.amplifiers.singular | B87: Lean More / Compare / Audio & Features / Audio | C87: amplifier | D87: amplifier | E87: amplifier | F87: forstærker | G87: Verstärker | H87: Verstärker | I87: amplificateur | J87: amplificateur | K87: amplificateur | L87: amplificateur | M87: amplificatore | N87: amplificatore | O87: アンプ | P87: amplificador | Q87: versterker | R87: forsterker | S87: amplificador | T87: förstärkare | U87: amplifier | V87: amplifier | W87: amplifier | X87: 放大器 | Y87: zesilovač | Z87: vahvistin | AA87: wzmacniacz | AB87: Verstärker | AC87: amplificateur | AD87: amplificador
A88: audio.amplifiers.plural | B88: Lean More / Compare / Audio & Features / Audio | C88: amplifiers | D88: amplifiers | E88: amplifiers | F88: forstærkere | G88: Verstärker | H88: Verstärker | I88: amplificateurs | J88: amplificateurs | K88: amplificateurs | L88: amplificateurs | M88: amplificatori | N88: amplificatori | O88: アンプ | P88: amplificadores | Q88: versterkers | R88: forsterkere | S88: amplificadores | T88: förstärkare | U88: amplifiers | V88: amplifiers | W88: amplifiers | X88: 放大器 | Y88: zesilovače | Z88: vahvistimet | AA88: wzmacniacze | AB88: Verstärker | AC88: amplificateurs | AD88: amplificadores
A89: fet-feature-amplifiers | B89: Lean More / Compare / Audio & Features / Audio | C89: Amplifiers | D89: Amplifiers | E89: Amplifiers | F89: Forstærkere | G89: Verstärker | H89: Verstärker | I89: Amplificateurs | J89: Amplificateurs | K89: Amplificateurs | L89: Amplificateurs | M89: Amplificatori | N89: Amplificatori | O89: アンプ | P89: Amplificadores | Q89: Versterkers | R89: Forsterkere | S89: Amplificadores | T89: Förstärkare | U89: Amplifiers | V89: Amplifiers | W89: Amplifiers | X89: 放大器 | Y89: Zesilovače | Z89: Vahvistimet | AA89: Wzmacniacze | AB89: Verstärker | AC89: Amplificateurs | AD89: Amplificadores
A90: fet-feature-class-d-digital-amplifier | B90: Lean More / Compare / Audio & Features / Audio | C90: Class-D digital amplifier | D90: Class-D digital amplifier | E90: Class-D digital amplifier | F90: Digital klasse D-forstærker | G90: Digitaler Verstärker der Klasse D | H90: Digitaler Verstärker der Klasse D | I90: Amplificateur numérique de classe D | J90: Amplificateur numérique de classe D | K90: Amplificateur numérique de classe D | L90: Amplificateur numérique de classe D | M90: Amplificatore digitale classe D | N90: Amplificatore digitale classe D | O90: クラスDデジタルアンプ | P90: Amplificador digital de clase D | Q90: D-klasse digitale versterker | R90: Digitalforsterker i klasse D | S90: Amplificador digital de clase D | T90: Digital klass D-förstärkare | U90: Class-D digital amplifier | V90: Class-D digital amplifier | W90: Class-D digital amplifier | X90: D类数字功放 | Y90: Digitální zesilovač třídy D | Z90: D-luokan digitaalivahvistin | AA90: Cyfrowy wzmacniacz impulsowy | AB90: Digitaler Verstärker der Klasse D | AC90: Amplificateur numérique de classe D | AD90: Amplificador digital de clase D
A91: fet-feature-class-d-digital-amplifiers | B91: Lean More / Compare / Audio & Features / Audio | C91: Class-D digital amplifiers | D91: Class-D digital amplifiers | E91: Class-D digital amplifiers | F91: Digitale klasse D-forstærkere | G91: Digitale Verstärker der Klasse D | H91: Digitale Verstärker der Klasse D | I91: Amplificateurs numériques de classe D | J91: Amplificateurs numériques de classe D | K91: Amplificateurs numériques de classe D | L91: Amplificateurs numériques de classe D | M91: Amplificatori digitali classe D | N91: Amplificatori digitali classe D | O91: クラスDデジタルアンプ | P91: Amplificadores digitales de clase D | Q91: D-klasse digitale versterkers | R91: Digitalforsterkere i klasse D | S91: Amplificadores digitales de clase D | T91: Digitala klass D-förstärkare | U91: Class-D digital amplifiers | V91: Class-D digital amplifiers | W91: Class-D digital amplifiers | X91: D类数字放大器 | Y91: Digitální zesilovače třídy D | Z91: D-luokan digitaalivahvistimet | AA91: Cyfrowe wzmacniacze impulsowe | AB91: Digitale Verstärker der Klasse D | AC91: Amplificateurs numériques de classe D | AD91: Amplificadores digitales de clase D
A92: fet-feature-class-h-digital-amplifier | B92: Lean More / Compare / Audio & Features / Audio | C92: Class-H digital amplifier | D92: Class-H digital amplifier | E92: Class-H digital amplifier | F92: Digital klasse H-forstærker | G92: Digitaler Verstärker der Klasse H | H92: Digitaler Verstärker der Klasse H | I92: Amplificateur numérique de classe H | J92: Amplificateur numérique de classe H | K92: Amplificateur numérique de classe H | L92: Amplificateur numérique de classe H | M92: Amplificatore digitale classe H | N92: Amplificatore digitale classe H | O92: クラスHデジタルアンプ | P92: Amplificador digital de clase H | Q92: H-klasse digitale versterker | R92: Digitalforsterker i klasse H | S92: Amplificador digital de clase H | T92: Digital klass H-förstärkare | U92: Class-H digital amplifier | V92: Class-H digital amplifier | W92: Class-H digital amplifier | X92: H类数字放大器 | Y92: Digitální zesilovač třídy H | Z92: H-luokan digitaalivahvistin | AA92: Cyfrowy wzmacniacz klasy H | AB92: Digitaler Verstärker der Klasse H | AC92: Amplificateur numérique de classe H | AD92: Amplificador digital de clase H
A93: fet-feature-class-h-digital-amplifiers | B93: Lean More / Compare / Audio & Features / Audio | C93: Class-H digital amplifiers | D93: Class-H digital amplifiers | E93: Class-H digital amplifiers | F93: Digitale klasse H-forstærkere | G93: Digitale Verstärker der Klasse H | H93: Digitale Verstärker der Klasse H | I93: Amplificateurs numériques de classe H | J93: Amplificateurs numériques de classe H | K93: Amplificateurs numériques de classe H | L93: Amplificateurs numériques de classe H | M93: Amplificatori digitali classe H | N93: Amplificatori digitali classe H | O93: クラスHデジタルアンプ | P93: Amplificadores digitales de clase H | Q93: H-klasse digitale versterkers | R93: Digitalforsterkere i klasse H | S93: Amplificadores digitales de clase H | T93: Digitala klass H-förstärkare | U93: Class-H digital amplifiers | V93: Class-H digital amplifiers | W93: Class-H digital amplifiers | X93: H类数字放大器 | Y93: Digitální zesilovače třídy H | Z93: H-luokan digitaalivahvistimet | AA93: Cyfrowe wzmacniacze klasy H | AB93: Digitale Verstärker der Klasse H | AC93: Amplificateurs numériques de classe H | AD93: Amplificadores digitales de clase H
A94: feature-audio.tweeters.singular | B94: Lean More / Compare / Audio & Features / Audio | C94: tweeter | D94: tweeter | E94: tweeter | F94: tweeter | G94: Hochtöner | H94: Hochtöner | I94: tweeter | J94: tweeter | K94: tweeter | L94: haut-parleur d’aigus | M94: tweeter | N94: tweeter | O94: ツイーター | P94: tweeter | Q94: tweeter | R94: diskanthøyttaler | S94: tweeter | T94: diskant | U94: tweeter | V94: tweeter | W94: tweeter | X94: 高音扬声器 | Y94: tweeter | Z94: diskanttikaiutin | AA94: głośnik wysokotonowy | AB94: Hochtöner | AC94: tweeter | AD94: tweeter
A95: feature-audio.tweeters.plural | B95: Lean More / Compare / Audio & Features / Audio | C95: tweeters | D95: tweeters | E95: tweeters | F95: tweetere | G95: Hochtöner | H95: Hochtöner | I95: tweeters | J95: tweeters | K95: tweeters | L95: haut-parleurs d’aigus | M95: tweeter | N95: tweeter | O95: ツイーター | P95: tweeters | Q95: tweeters | R95: diskanthøyttalere | S95: tweeters | T95: diskanter | U95: tweeters | V95: tweeters | W95: tweeters | X95: 高音扬声器 | Y95: tweetery | Z95: diskanttikaiuttimet | AA95: głośniki wysokotonowe | AB95: Hochtöner | AC95: tweeters | AD95: tweeters
... A109: fet-feature-midwoofers | B109: Lean More / Compare / Audio & Features / Audio | C109: Midwoofers | D109: Midwoofers | E109: Mid-woofers | F109: Midwoofere | G109: Mitteltöner | H109: Mitteltöner | I109: Mid-woofers | J109: Mid-woofers | K109: Mid-woofers | L109: Haut-parleurs de graves médians | M109: Midwoofer | N109: Midwoofer | O109: ミッドウーファー | P109: Woofers de rango medio | Q109: Midwoofers | R109: Mellom-woofere | S109: Altavoces de medios | T109: Mid-woofers | U109: Mid-woofers | V109: Mid-woofers | W109: Mid-woofers | X109: 中低音扬声器 | Y109: Středobasové měniče | Z109: Midwooferit | AA109: Głośniki średniotonowe | AB109: Mitteltöner | AC109: Mid-woofers | AD109: Woofers de rango medio
A110: fet-feature-high-efficiency-midwoofers | C110: High-efficiency midwoofers | D110: High-efficiency midwoofers | E110: High-efficiency midwoofers | F110: Højeffektive midwoofere | G110: Hocheffiziente Mitteltöner | H110: Hocheffiziente Mitteltöner | I110: Mid-woofers hautes performances | J110: Mid-woofers hautes performances | K110: Mid-woofers hautes performances | L110: Haut-parleurs de graves médians à haut rendement | M110: Mid-woofer ad alta efficienza | N110: Mid-woofer ad alta efficienza | O110: 高性能ミッドウーファー | P110: Woofers de rango medio de alta eficiencia | Q110: Extra efficiënte midwoofers | R110: Høyeffektive mellom-woofere | S110: Altavoces de medios de alta eficiencia | T110: Mid-woofers med hög effekt | U110: High-efficiency midwoofers | V110: High-efficiency midwoofers | W110: High-efficiency midwoofers | X110: 高性能中低音扬声器 | Y110: Vysoce účinné středobasové měniče | Z110: Tehokkaat midwoofer-kaiuttimet | AA110: Wysokowydajne głośniki średniotonowe | AB110: Hocheffiziente Mitteltöner | AC110: Mid-woofers hautes performances | AD110: Woofers de rango medio de alta eficiencia
A111: audio.woofers.sixInch | B111: Lean More / Compare / Audio & Features / Audio | C111: 6" woofer | D111: 6" woofer | E111: 6" woofer | F111: 6″-woofer | G111: 6" Tieftöner | H111: 6" Tieftöner | I111: woofer de 6 pouces | J111: woofer de 6 pouces | K111: woofer de 6 pouces | L111: Caisson de basses de 6 po | M111: Woofer da 6 pollici | N111: Woofer da 6 pollici | O111: 6インチウーファー | P111: Woofer de 6" | Q111: 6-inch woofer | R111: 6" woofer | S111: Woofer de 6" | T111: 6-tums woofer | U111: 6" woofer | V111: 6" woofer | W111: 6" woofer | X111: 6英寸低音扬声器 | Y111: 6palcový basový měnič | Z111: 6 tuuman bassokaiutin | AA111: Głośnik niskotonowy o średnicy 152 mm | AB111: 6" Tieftöner | AC111: woofer de 6 pouces | AD111: Woofer de 6"
A112: fet-feature-6-inch-woofers | B112: Lean More / Compare / Audio & Features / Audio | C112: 6" woofers | D112: 6" woofers | E112: 6" woofers | F112: 6″-woofere | G112: 6" Tieftöner | H112: 6" Tieftöner | I112: woofers de 6 pouces | J112: woofers de 6 pouces | K112: woofers de 6 pouces | L112: Caissons de basses de 6 po | M112: Woofer da 6 pollici | N112: Woofer da 6 pollici | O112: 6インチウーファー | P112: Woofers de 6" | Q112: 6-inch woofers | R112: 6" woofere | S112: Woofers de 6" | T112: 6-tums woofers | U112: 6" woofers | V112: 6" woofers | W112: 6" woofers | X112: 6英寸低音扬声器 | Y112: 6palcové basové měniče | Z112: 6 tuuman bassokaiuttimet | AA112: Głośniki niskotonowe o średnicy 152 mm | AB112: 6" Tieftöner | AC112: woofers de 6 pouces | AD112: Woofers de 6"
A113: fet-feature-elliptical-midwoofer | B113: Lean More / Compare / Audio & Features / Audio | C113: Elliptical midwoofer | D113: Elliptical midwoofer | E113: Elliptical mid-woofer | F113: Elliptisk midwoofer | G113: Elliptischer Mitteltöner | H113: Elliptischer Mitteltöner | I113: Mid-woofer elliptique | J113: Mid-woofer elliptique | K113: Mid-woofer elliptique | L113: Haut-parleur de graves médians elliptique | M113: Mid-woofer ellittico | N113: Mid-woofer ellittico | O113: 楕円形ミッドウーファー | P113: Woofer elíptico de rango medio | Q113: Elliptische midwoofer | R113: Elliptisk mellom-woofer | S113: Altavoz de medios elíptico | T113: Elliptisk mid-woofer | U113: Elliptical mid-woofer | V113: Elliptical mid-woofer | W113: Elliptical mid-woofer | X113: 椭圆形中低音扬声器 | Y113: Eliptický středobasový měnič | Z113: Elliptinen bassokaiutin | AA113: Eliptyczny głośnik średniotonowy | AB113: Elliptischer Mitteltöner | AC113: Mid-woofer elliptique | AD113: Woofer elíptico de rango medio
A114: fet-feature-elliptical-midwoofers | B114: Lean More / Compare / Audio & Features / Audio | C114: Elliptical midwoofers | D114: Elliptical midwoofers | E114: Elliptical mid-woofers | F114: Elliptiske midwoofere | G114: Elliptische Mitteltöner | H114: Elliptische Mitteltöner | I114: Mid-woofers elliptiques | J114: Mid-woofers elliptiques | K114: Mid-woofers elliptiques | L114: Haut-parleurs de graves médians elliptiques | M114: Mid-woofer ellittici | N114: Mid-woofer ellittici | O114: 楕円形ミッドウーファー | P114: Woofers elípticos de rango medio | Q114: Elliptische midwoofers | R114: Elliptiske mellom-woofere | S114: Altavoces de medios elípticos | T114: Elliptiska mid-woofers | U114: Elliptical mid-woofers | V114: Elliptical mid-woofers | W114: Elliptical mid-woofers | X114: 椭圆形中低音扬声器 | Y114: Eliptické středobasové měniče | Z114: Elliptiset bassokaiuttimet | AA114: Eliptyczne głośniki średniotonowe | AB114: Elliptische Mitteltöner | AC114: Mid-woofers elliptiques | AD114: Woofers elípticos de rango medio
A115: fet-feature-custom-40mm-dynamice-drivers | B115: Lean More / Compare / Audio & Features / Audio | C115: Custom-designed 40mm dynamic drivers | D115: Custom-designed 40 mm dynamic drivers | E115: Custom-designed 40 mm dynamic drivers | F115: Specialudviklede dynamiske drivere på 40 mm | G115: Spezielle dynamische 40-mm-Treiber | H115: Spezielle dynamische 40-mm-Treiber | I115: Haut-parleurs dynamiques de 40 mm conçus sur mesure | J115: Haut-parleurs dynamiques de 40 mm conçus sur mesure | K115: Haut-parleurs dynamiques de 40 mm conçus sur mesure | L115: Haut-parleurs dynamiques de 40 mm conçus sur mesure | M115: Driver dinamici da 40 mm progettati su misura | N115: Driver dinamici da 40 mm progettati su misura | O115: カスタム設計の40mmダイナミックドライバー | P115: Diafragmas dinámicos de diseño exclusivo de 40 mm | Q115: Speciaal ontworpen 40 mm dynamische drivers | R115: Spesialkonstruerte 40 mm dynamiske drivere | S115: Altavoces dinámicos de 40 mm diseñados a medida | T115: Specialdesignade, dynamiska högtalarelement på 40 mm | U115: Custom-designed 40 mm dynamic drivers | V115: Custom-designed 40 mm dynamic drivers | W115: Custom-designed 40 mm dynamic drivers | X115: 定制设计40毫米动态驱动器 | Y115: Na míru vytvořené 40mm dynamické ovladače | Z115: Kustomoidut 40 mm:n dynaamiset ohjaimet | AA115: Specjalnie zaprojektowane przetworniki dynamiczne o średnicy 40 mm | AB115: Spezielle dynamische 40-mm-Treiber | AC115: Haut-parleurs dynamiques de 40 mm conçus sur mesure | AD115: Diafragmas dinámicos de diseño exclusivo de 40 mm
A116: fet-feature-active-noise-cancellation-capitalized | B116: Lean More / Compare / Audio & Features / Audio | C116: Active Noise Cancellation | D116: Active Noise Cancellation | E116: Active Noise Cancellation | F116: Aktiv støjreduktion | G116: Aktive Geräuschunterdrückung | H116: Aktive Geräuschunterdrückung | I116: Réduction active du bruit | J116: Réduction active du bruit | K116: Réduction active du bruit | L116: Élimination active des bruits | M116: Cancellazione attiva del rumore | N116: Cancellazione attiva del rumore | O116: ノイズキャンセリング機能 | P116: Cancelación activa de ruido | Q116: Actieve ruisonderdrukking | R116: Aktiv støykansellering | S116: Cancelación activa de ruido | T116: Aktiv brusreducering | U116: Active Noise Cancellation | V116: Active Noise Cancellation | W116: Active Noise Cancellation | X116: 主动消噪 | Y116: Aktivní potlačení hluku | Z116: Aktiivinen melunvaimennus | AA116: Aktywne tłumienie hałasu | AB116: Aktive Geräuschunterdrückung | AC116: Réduction active du bruit | AD116: Cancelación activa de ruido
A117: fet-feature-aware-mode | B117: Lean More / Compare / Audio & Features / Audio | C117: Aware mode | D117: Aware mode | E117: Aware mode | F117: Aware mode | G117: Aware Modus | H117: Aware Modus | I117: Mode Aware | J117: Mode Aware | K117: Mode Aware | L117: Mode conscient | M117: Modalità Trasparenza | N117: Modalità Trasparenza | O117: アウェアモード | P117: Modo Ambiente | Q117: Aware-modus | R117: Bevisst modus | S117: Modo Aware | T117: Transparensläge | U117: Aware mode | V117: Aware mode | W117: Aware mode | X117: 感知模式 | Y117: Režim pozornosti | Z117: Valppaustila | AA117: Tryb kontaktu | AB117: Aware Modus | AC117: Mode Aware | AD117: Modo Ambiente
A118: fet-feature-microphones | B118: Lean More / Tech Specs / Audio | C118: Microphones | D118: Microphones | E118: Microphones | F118: Mikrofoner | G118: Mikrofone | H118: Mikrofone | I118: Microphones | J118: Microphones | K118: Microphones | L118: Microphones | M118: Microfoni | N118: Microfoni | O118: マイク | P118: Micrófonos | Q118: Microfoons | R118: Mikrofoner | S118: Micrófonos | T118: Mikrofoner | U118: Microphones | V118: Microphones | W118: Microphones | X118: 麦克风 | Y118: Mikrofony | Z118: Mikrofonit | AA118: Mikrofony | AB118: Mikrofone | AC118: Microphones | AD118: Micrófonos
A119: fet-feature-microphones-arc-beam | B119: Lean More / Tech Specs / Audio | C119: The far-field microphone array uses advanced beamforming and multi-channel echo cancellation for quick and accurate voice control. | D119: The far-field microphone array uses advanced beamforming and multi-channel echo cancellation for quick and accurate voice control. | E119: The far-field microphone array uses advanced beamforming and multi-channel echo cancellation for quick and accurate voice control. | F119: Fjernfeltsmikrofonen med avanceret stråleformning og multikanals ekkodæmpning giver hurtig og præcis aktivering af stemmeassistent. | G119: Fernfeldmikrofone ermöglichen eine präzise Positionsbestimmung von Audioquellen und hervorragende Mehrkanal-Echounterdrückung für eine schnelle und präzise Sprachsteuerung. | H119: Fernfeldmikrofone ermöglichen eine präzise Positionsbestimmung von Audioquellen und hervorragende Mehrkanal-Echounterdrückung für eine schnelle und präzise Sprachsteuerung. | I119: Le réseau de micros longue portée utilise des technologies avancées de formation de faisceaux et d’annulation de l’écho sur tous les canaux, pour un contrôle vocal rapide et précis. | J119: Le réseau de micros longue portée utilise des technologies avancées de formation de faisceaux et d’annulation de l’écho sur tous les canaux, pour un contrôle vocal rapide et précis. | K119: Le réseau de micros longue portée utilise des technologies avancées de formation de faisceaux et d’annulation de l’écho sur tous les canaux, pour un contrôle vocal rapide et précis. | L119: L’ensemble de microphones à grande portée assure la formation avancée de faisceaux et la suppression active de l’écho sur plusieurs canaux pour utiliser le contrôle vocal avec rapidité et précision. | M119: L’assetto far-field dei microfoni con beamforming avanzato e cancellazione dell’eco multicanale consente un controllo vocale rapido e preciso. | N119: L’assetto far-field dei microfoni con beamforming avanzato e cancellazione dell’eco multicanale consente un controllo vocale rapido e preciso. | O119: 遠距離対応マイクロホンアレイが高度なビームフォーミングとマルチチャンネルのエコー除去機能を利用して、音声操作をすばやく正確に起動。 | P119: La matriz de micrófonos de largo alcance utiliza detección avanzada de fuentes de sonido y cancelación multicanal de ecos para un control por voz rápido y preciso. | Q119: De far field-microfoons maken gebruik van geavanceerde beamforming en meerkanaals echo-onderdrukking voor snelle en nauwkeurige stembediening. | R119: Mikrofonsettet bruker avansert stråleforming og flerkanals ekkokansellering for rask og nøyaktig stemmestyring. | S119: Una matriz de micrófonos de largo alcance se encarga de formar haces avanzados y evitar el eco multicanal para que el control por voz se active de forma rápida y precisa. | T119: Fjärrfältsmikrofonerna använder avancerad strålformning och flerkanalig ekoreducering för att ge snabb och korrekt röststyrning. | U119: The far-field microphone array uses advanced beamforming and multi-channel echo cancellation for quick and accurate voice control. | V119: The far-field microphone array uses advanced beamforming and multi-channel echo cancellation for quick and accurate voice control. | W119: The far-field microphone array uses advanced beamforming and multi-channel echo cancellation for quick and accurate voice control. | X119: 远场麦克风阵列使用高级波束赋形技术和多通道回波消除技术，可实现快速精确的语音控制。 | Y119: Sada mikrofonů s dalekým dosahem využívá pokročilou technologii Beamforming a vícekanálové rušení ozvěny pro rychlé a přesné ovládání hlasu. | Z119: Kaukokenttämikrofoniryhmä käyttää edistynyttä äänikeilaa ja monikanavaista kaiunpoistoa, mikä mahdollistaa nopean puheohjauksen*. *Puheohjaus ei saatavilla Suomessa. | AA119: Układ dalekosiężnych mikrofonów wykorzystuje zaawansowane kształtowanie wiązki i wielokanałową eliminację pogłosu, co umożliwia szybką i precyzyjną aktywację sterowania głosowego. | AB119: Fernfeldmikrofone ermöglichen eine präzise Positionsbestimmung von Audioquellen und hervorragende Mehrkanal-Echounterdrückung für eine schnelle und präzise Sprachsteuerung. | AC119: Le réseau de micros longue portée utilise des technologies avancées de formation de faisceaux et d’annulation de l’écho sur tous les canaux, pour un contrôle vocal rapide et précis. | AD119: La matriz de micrófonos de largo alcance utiliza detección avanzada de fuentes de sonido y cancelación multicanal de ecos para un control por voz rápido y preciso.
